Workbook

Sheet form
A1: monthly_v2.0

Sheet Instructions and Glossary
A1: Project Tracker - Instructions
B4: Purpose | C4: The Project Tracker is a tool for capital analysts to capture information about each board's projects. This data provides a line of sight into project progress and details that is critical to both analysts, other folks within the branch, and management. The data gathered here facilitates project accountability and oversight of project milestones and finances.
B6: Instructions
B7: During Meetings with the Board | C7: When analysts meet with their board to discuss projects, you should use this tool to guide your meetings and capture information. Make sure you update the meeting date on the Monthly Tracker worksheet. You'll notice that this sheet has conditional formatting that greys out the sheet when the meeting date is not set to the current day. This is done so you have a visual reminder to update this date before you talk with your boards. Taking comprehensive minutes is especially important part of your meetings with the boards. The template provides space for you to enter project-specific minutes, as well as a section for minuting any more general information discussed that might not fall under one specific project. The data is scraped regularly and then the template is regenerated with updated information. During this process, minutes are archived and relocated to the far-left side of the template (column BD), sorted with the most recent minutes closest to the left.
B8: As Needed | C8: If you need to update information at any time other than during a meeting with the board, you are free to do so and the revised information will be captured the next time the data team extracts data from worksheet. Do NOT change the meeting date during any such ad-hoc updates. You should only change the meeting dates when you actually meet with the school board.
B9: General Information & Error Checking | C9: As mentioned above, the Monthly Update worksheet contains conditional formatting that incentivizes you not to forget to enter a meeting date when you talk with the school board. You will notice that once the meeting date is has passed (i.e., it is something other than the current date), the whole sheet goes grey. This provides a visual cue for you to update the date prior to meeting with your board. The sheet also contains some automatic error checking. Cells contain errors when they are highlighted in purple. To determine the reason for the error, scroll over to columns CY to ES. This section contains the same columns as the main table; cells in this table will only contains text if there is an error. That text will describe the cause of the error in the corresponding cell in the main table.
B11: Within-Budget Acknowledgement Process
B12: Analyst Checks | C12: Confirm that the board has submitted all necessary documentation: •Class A/B cost estimate •Revised CPBF form that reflects the Class A/B cost estimate. •80% design drawings that align with the cost estimate and approved space template. •Child care floor plan approval letter (if applicable). Ensure that all documents are saved in the appropriate folder on the Share Drive. Once you have checked and confirmed all documents, send an email to the board acknowledging receipt of the pre/post tender package.
B13: Record Keeping | C13: Create a folder in the following directory: \\csc.ad.gov.on.ca\dfs$\GrpData\CBSD\CAPITAL\STRATEGY\Operations\BOARDS\^Project Commitment\Pre & Post Tender Check-In •The folder should be named using the following naming format: project id # YYYY-MM-DD Example: 12-123 # 2025-12-30 •The date in the folder name should be the date of the email acknowledging receipt of the documents and confirming the board can proceed. •Save the following in the folder you created above: o The CPBF form that reflects the pre-tender/post-tender budget. o The email to the school board (sent within 7 days of the board’s submission) confirming all documents have been submitted and that the ministry has no concerns with the board proceeding to tender/awarding the contract.
A15: Project Tracker Glossary
B17: Overview of the Worksheets within the Project Tracker
B18: Board Contacts | C18: Use this worksheet to enter the contact information for your boards. This is a central location for Capital Analysts to store this information, as well as a place where management and other analysts can go if they need this information. This is important to support coverage for analysts who are absent.
B19: Monthly Update | C19: Use this tab to memorialize meetings with the school boards. See instructions above and glossary below for more information.
B20: Basic Project Info | C20: Use this worksheet to enter the official school name, the school's location information, sign installation information, and the opening ceremony date. See below for a glossary, defining what should be entered in each column.
B21: Ad-Hoc or Potential Projects | C21: Use this worksheet to enter data about potential projects that have not yet been approved or about ad-hoc, minor projects that don't show up on the Monthly Tracker sheet.
B22: Project Commitment | C22: This sheet is for your reference only. It is not editable. It provides information about the current project commitment for the projects for this board.
A24: Glossary - Basic Project Info Tab
A26: ='Basic Project Info'!A2 -> Section 1: Project Details
A27: Col 1 | B27: =_xlfn.XLOOKUP(A27,'Basic Project Info'!$A$3:$L$3, 'Basic Project Info'!$A$4:$L$4) -> Project ID | C27: =C44 -> Automatically generated and uneditable. Each project is assigned a unique ID for tracking throughout its lifecycle. The ID displayed here is the ID for the construction portion of the project.
A28: ="Col " & ROW() -ROW($A$27)+1 -> Col 2 | B28: =_xlfn.XLOOKUP(A28,'Basic Project Info'!$A$3:$L$3, 'Basic Project Info'!$A$4:$L$4) -> Project Name | C28: Automatically generated and uneditable. This is the name assigned to the project when it is first approved. It cannot be changed and is constant throughout the project's lifecycle.
A29: ="Col " & ROW() -ROW($A$27)+1 -> Col 3 | B29: =_xlfn.XLOOKUP(A29,'Basic Project Info'!$A$3:$L$3, 'Basic Project Info'!$A$4:$L$4) -> Official School Name | C29: Use this field to update the official school name that will be used after the school is open. Please use the complete name and do not use abbreviations (e.g. use "Example Public School" instead of "Example" or "Example P.S.". If this project is an addition, this field can be completed as soon as the project is approved.
A30: ="Col " & ROW() -ROW($A$27)+1 -> Col 4 | B30: =_xlfn.XLOOKUP(A30,'Basic Project Info'!$A$3:$L$3, 'Basic Project Info'!$A$4:$L$4) -> Project Type | C30: =C47 -> Automatically generated and uneditable. Project types potentially included in this tracker are: New Construction, Retrofit, Addition, and Purchase.
A31: ="Col " & ROW() -ROW($A$27)+1 -> Col 5 | B31: =_xlfn.XLOOKUP(A31,'Basic Project Info'!$A$3:$L$3, 'Basic Project Info'!$A$4:$L$4) -> Project Category | C31: =C48 -> Automatically generated and uneditable. This field identifies the need that is met by the project. Potential project categories that could be included on this tracker are: Accommodation Pressure, Child Care, Facility Condition, Consolidation, and French Language Access.
A32: ="Col " & ROW() -ROW($A$27)+1 -> Col 6 | B32: =_xlfn.XLOOKUP(A32,'Basic Project Info'!$A$3:$L$3, 'Basic Project Info'!$A$4:$L$4) -> Address | C32: Enter the address for the school. If it's not yet known, leave it blank.
A33: ="Col " & ROW() -ROW($A$27)+1 -> Col 7 | B33: =_xlfn.XLOOKUP(A33,'Basic Project Info'!$A$3:$L$3, 'Basic Project Info'!$A$4:$L$4) -> City | C33: Use this field to enter the city/town where the project is located. This should be known at the time of project approval and be pre-populated on the template. Therefore, this field can be left unedited except for very rare circumstances.
A34: ="Col " & ROW() -ROW($A$27)+1 -> Col 8 | B34: =_xlfn.XLOOKUP(A34,'Basic Project Info'!$A$3:$L$3, 'Basic Project Info'!$A$4:$L$4) -> Postal Code | C34: Enter the postal code of the school. If the it's not yet known, leave it blank.
A35: ="Col " & ROW() -ROW($A$27)+1 -> Col 9 | B35: =_xlfn.XLOOKUP(A35,'Basic Project Info'!$A$3:$L$3, 'Basic Project Info'!$A$4:$L$4) -> Latitude | C35: Enter the latitude of the school. This information should be updated once the site has been purchased.
A36: ="Col " & ROW() -ROW($A$27)+1 -> Col 10 | B36: =_xlfn.XLOOKUP(A36,'Basic Project Info'!$A$3:$L$3, 'Basic Project Info'!$A$4:$L$4) -> Longitude | C36: Enter the longitude of the school. This information should be updated once the site has been purchased.
A37: ='Basic Project Info'!K2 -> Section 2: Communications Issues
A38: ="Col " & ROW() -ROW($A$27) -> Col 11 | B38: =_xlfn.XLOOKUP(A38,'Basic Project Info'!$A$3:$L$3, 'Basic Project Info'!$A$4:$L$4) -> Sign Installed | C38: Indicate whether the board has installed a sign on the project site.
A39: ="Col " & ROW() -ROW($A$27) -> Col 12 | B39: =_xlfn.XLOOKUP(A39,'Basic Project Info'!$A$3:$L$3, 'Basic Project Info'!$A$4:$L$4) -> Opening Ceremony - Date | C39: Use this once the project approaches completion if the board plans an opening ceremony. Otherwise, leave this blank.
A41: Glossary - Monthly Update Tab
A43: ='Monthly Update'!A5 -> Section 1: Project Details
A44: Col 1 | B44: =_xlfn.XLOOKUP(A44, 'Monthly Update'!$A$6:$AU$6, 'Monthly Update'!$A$7:$AU$7) -> Project ID | C44: Automatically generated and uneditable. Each project is assigned a unique ID for tracking throughout its lifecycle. The ID displayed here is the ID for the construction portion of the project.
A45: Col 2 | B45: =_xlfn.XLOOKUP(A45, 'Monthly Update'!$A$6:$AU$6, 'Monthly Update'!$A$7:$AU$7) -> Project Name | C45: Automatically generated and uneditable. This is the name assigned to the project when it is first approved. It cannot be changed and is constant throughout the project's lifecycle. The official name of the school can be modified on the Basic Project Info tab.
A46: Col 3 | B46: =_xlfn.XLOOKUP(A46, 'Monthly Update'!$A$6:$AU$6, 'Monthly Update'!$A$7:$AU$7) -> Meeting Minutes | C46: Enter details about each project based on conversations with the school board.
A47: Col 4 | B47: =_xlfn.XLOOKUP(A47, 'Monthly Update'!$A$6:$AU$6, 'Monthly Update'!$A$7:$AU$7) -> Project Type | C47: Automatically generated and uneditable. Project types potentially included in this tracker are: New Construction, Retrofit, Addition, and Purchase.
A48: Col 5 | B48: =_xlfn.XLOOKUP(A48, 'Monthly Update'!$A$6:$AU$6, 'Monthly Update'!$A$7:$AU$7) -> Project Category | C48: Automatically generated and uneditable. This field identifies the need that is met by the project. Potential project categories that could be included on this tracker are: Accommodation Pressure, Child Care, Facility Condition, Consolidation, and French Language Access.
A49: Col 6 | B49: =_xlfn.XLOOKUP(A49, 'Monthly Update'!$A$6:$AU$6, 'Monthly Update'!$A$7:$AU$7) -> Record Status | C49: This drop-down determines which projects will be removed from your trackers. If you want to remove a project, you must identify whether it has been completed or cancelled. The default is for projects to remain on the tracker. When projects are removed from the tracker, it triggers an email notification to your manager and director.
A50: Col 7 | B50: =_xlfn.XLOOKUP(A50, 'Monthly Update'!$A$6:$AU$6, 'Monthly Update'!$A$7:$AU$7) -> Construction Status | C50: Automatically generated and uneditable. This field is calculated based on the dates provided to the right in this sheet. If the meeting date is after the opening date, the construction status is "Open"; if the meeting date is after the construction date, the status is "Under Construction". Otherwise the project status is "Planning".
A51: ='Monthly Update'!H5 -> Section 2: Project Commitment Progress
A52: Col 8 | B52: =_xlfn.XLOOKUP(A52, 'Monthly Update'!$A$6:$AU$6, 'Monthly Update'!$A$7:$AU$7) -> Pre-Tender Submission Date | C52: This is the estimated/actual submission date for the pre-tender budget. This field must be a date value.
A53: Col 9 | B53: =_xlfn.XLOOKUP(A53, 'Monthly Update'!$A$6:$AU$6, 'Monthly Update'!$A$7:$AU$7) -> Pre-Tender Package Type | C53: Use this dropdown to indicate whether the pretender budget is within existing funding or requires additional ministry funds.
A54: Col 10 | B54: =_xlfn.XLOOKUP(A54, 'Monthly Update'!$A$6:$AU$6, 'Monthly Update'!$A$7:$AU$7) -> Pre-Tender Package Complete | C54: Automatically generated and uneditable. This indicates whether we have a record of the pre-tender budget in our data system and, if so, the date of the approval (for packages approved by the minister) or notification (for within-budget acknowledgments).
A55: Col 11 | B55: =_xlfn.XLOOKUP(A55, 'Monthly Update'!$A$6:$AU$6, 'Monthly Update'!$A$7:$AU$7) -> CA Reviewed All Pre-Tender Documents | C55: This is a manual confirmation that the CA has completed their review of the pre-tender package.
A56: Col 12 | B56: =_xlfn.XLOOKUP(A56, 'Monthly Update'!$A$6:$AU$6, 'Monthly Update'!$A$7:$AU$7) -> Post-Tender Submission Date | C56: This is the estimated/actual submission date for the post-tender budget. This field must be a date value.
A57: Col 13 | B57: =_xlfn.XLOOKUP(A57, 'Monthly Update'!$A$6:$AU$6, 'Monthly Update'!$A$7:$AU$7) -> Post-Tender Package Type | C57: Use this dropdown to indicate whether the post-tender budget is within existing funding or requires additional ministry funds.
A58: Col 14 | B58: =_xlfn.XLOOKUP(A58, 'Monthly Update'!$A$6:$AU$6, 'Monthly Update'!$A$7:$AU$7) -> Post-Tender Package Complete | C58: Automatically generated and uneditable. This indicates whether we have a record of the post-tender budget in our data system and, if so, the date of the approval (for packages approved by the minister) or notification (for within-budget acknowledgments).
A59: Col 15 | B59: =_xlfn.XLOOKUP(A59, 'Monthly Update'!$A$6:$AU$6, 'Monthly Update'!$A$7:$AU$7) -> CA Reviewed All Post-Tender Documents | C59: This is a manual confirmation that the CA has completed their review of the post-tender package.
A60: ='Monthly Update'!P5 -> Section 3: Pre-Tender
A61: Col 16 | B61: =_xlfn.XLOOKUP(A61, 'Monthly Update'!$A$6:$AU$6, 'Monthly Update'!$A$7:$AU$7) -> Site Ownership Status | C61: Use this dropdown to indicate the site status. Only use "Not Applicable" if the project is an addition/retrofit and does not require a site purchase.
A62: Col 17 | B62: =_xlfn.XLOOKUP(A62, 'Monthly Update'!$A$6:$AU$6, 'Monthly Update'!$A$7:$AU$7) -> Site Purchase Date | C62: This field must be a date value or blank. Indicate when the board will gain/gained ownership of the site or leave it blank if Site Ownership Status is "Not Applicable".
A63: Col 18 | B63: =_xlfn.XLOOKUP(A63, 'Monthly Update'!$A$6:$AU$6, 'Monthly Update'!$A$7:$AU$7) -> Design Status | C63: Use this dropdown to identify the progress on the project's designs.
A64: Col 19 | B64: =_xlfn.XLOOKUP(A64, 'Monthly Update'!$A$6:$AU$6, 'Monthly Update'!$A$7:$AU$7) -> Space Template Approval Date | C64: This field must be a date value. Indicate expected/actual date of the space template approval.
A65: Col 20 | B65: =_xlfn.XLOOKUP(A65, 'Monthly Update'!$A$6:$AU$6, 'Monthly Update'!$A$7:$AU$7) -> Child Care Floorplan Approval Date | C65: This field must be a date value or blank. Indicate the expected/actual date of the child care floorplan approval. Leave blank only if the project does not include child care.
A66: Col 21 | B66: =_xlfn.XLOOKUP(A66, 'Monthly Update'!$A$6:$AU$6, 'Monthly Update'!$A$7:$AU$7) -> Initial Site Plan Submission Date | C66: This field must be a date value. Provide the expected/actual initial site plan submission date.
A67: Col 22 | B67: =_xlfn.XLOOKUP(A67, 'Monthly Update'!$A$6:$AU$6, 'Monthly Update'!$A$7:$AU$7) -> Site Plan Approval Date | C67: This field must be a date value. Provide the expected/actual site plan submission date.
A68: Col 23 | B68: =_xlfn.XLOOKUP(A68, 'Monthly Update'!$A$6:$AU$6, 'Monthly Update'!$A$7:$AU$7) -> Site Plan Approval Date Error Explanation | C68: ="Use the field only if "& A67& " ("&B67&") indicates an error (cell is highlighted in purple) but you believe the information is correct, explain the descrpancy in this cell and it will remove the error formatting in "&A67&"." -> Use the field only if Col 22 (Site Plan Approval Date) indicates an error (cell is highlighted in purple) but you believe the information is correct, explain the descrpancy in this cell and it will remove the error formatting in Col 22.
A69: Col 24 | B69: =_xlfn.XLOOKUP(A69, 'Monthly Update'!$A$6:$AU$6, 'Monthly Update'!$A$7:$AU$7) -> Build Permit Obtained Date | C69: This field must be a date value. Enter the expected/actual date the board received a building permit for this project.
A70: Col 25 | B70: =_xlfn.XLOOKUP(A70, 'Monthly Update'!$A$6:$AU$6, 'Monthly Update'!$A$7:$AU$7) -> Build Permit Obtained Date Error Explanation | C70: ="Use the field only if "& A69& " ("&B69&") indicates an error (cell is highlighted in purple) but you believe the information is correct, explain the descrpancy in this cell and it will remove the error formatting in "&A69&"." -> Use the field only if Col 24 (Build Permit Obtained Date) indicates an error (cell is highlighted in purple) but you believe the information is correct, explain the descrpancy in this cell and it will remove the error formatting in Col 24.
A71: Col 26 | B71: =_xlfn.XLOOKUP(A71, 'Monthly Update'!$A$6:$AU$6, 'Monthly Update'!$A$7:$AU$7) -> Tender Issued Date | C71: This field must be a date value. Enter the expected/actual date the board opened the tender process.
A72: Col 27 | B72: =_xlfn.XLOOKUP(A72, 'Monthly Update'!$A$6:$AU$6, 'Monthly Update'!$A$7:$AU$7) -> Tender Closed Date | C72: This field must be a date value. Enter the expected/actual date the board closed the tender process.
A73: ='Monthly Update'!AB5 -> Section 4: Construction
A74: Col 28 | B74: =_xlfn.XLOOKUP(A74, 'Monthly Update'!$A$6:$AU$6, 'Monthly Update'!$A$7:$AU$7) -> Contract Awarded Date | C74: This field must be a date value. Enter the expected/actual date the board awards the contract to the successful bid.
A75: Col 29 | B75: =_xlfn.XLOOKUP(A75, 'Monthly Update'!$A$6:$AU$6, 'Monthly Update'!$A$7:$AU$7) -> Construction Start Date | C75: This field must be a date value. Enter the expected/actual date that construction work will actually begin on the school site. This date must follow all tender dates and the contract awarded date.
A76: Col 30 | B76: =_xlfn.XLOOKUP(A76, 'Monthly Update'!$A$6:$AU$6, 'Monthly Update'!$A$7:$AU$7) -> Construction Start Date Error Explanation | C76: ="Use the field only if "& A75& " ("&B75&") indicates an error (cell is highlighted in purple) but you believe the information is correct, explain the descrpancy in this cell and it will remove the error formatting in "&A75&"." -> Use the field only if Col 29 (Construction Start Date) indicates an error (cell is highlighted in purple) but you believe the information is correct, explain the descrpancy in this cell and it will remove the error formatting in Col 29.
A77: Col 31 | B77: =_xlfn.XLOOKUP(A77, 'Monthly Update'!$A$6:$AU$6, 'Monthly Update'!$A$7:$AU$7) -> Substantial Completion Date | C77: This field must be a date value. Enter the expected/actual date the project will be substantially complete - that is, the project is complete up to the point that it can be utilized for its intended purpose. Under all but very rare circumstances this date will precede the opening date.
A78: Col 32 | B78: =_xlfn.XLOOKUP(A78, 'Monthly Update'!$A$6:$AU$6, 'Monthly Update'!$A$7:$AU$7) -> Substantial Completion Date Error Explanation | C78: ="Use the field only if "& A77& " ("&B77&") indicates an error (cell is highlighted in purple) but you believe the information is correct, explain the descrpancy in this cell and it will remove the error formatting in "&A77&"." -> Use the field only if Col 31 (Substantial Completion Date) indicates an error (cell is highlighted in purple) but you believe the information is correct, explain the descrpancy in this cell and it will remove the error formatting in Col 31.
A79: ='Monthly Update'!AG5 -> Section 5: Project Completion
A80: Col 33 | B80: =_xlfn.XLOOKUP(A80, 'Monthly Update'!$A$6:$AU$6, 'Monthly Update'!$A$7:$AU$7) -> School Opening Date | C80: This field must be a date value. Enter the expected/actual date the school portion of the project will be open (i.e., the date when kids will be in new seats).
A81: Col 34 | B81: =_xlfn.XLOOKUP(A81, 'Monthly Update'!$A$6:$AU$6, 'Monthly Update'!$A$7:$AU$7) -> School Opening Date Error Explanation | C81: ="Use the field only if "& A80& " ("&B80&") indicates an error (cell is highlighted in purple) but you believe the information is correct, explain the descrpancy in this cell and it will remove the error formatting in "&A80&"." -> Use the field only if Col 33 (School Opening Date ) indicates an error (cell is highlighted in purple) but you believe the information is correct, explain the descrpancy in this cell and it will remove the error formatting in Col 33.
A82: Col 35 | B82: =_xlfn.XLOOKUP(A82, 'Monthly Update'!$A$6:$AU$6, 'Monthly Update'!$A$7:$AU$7) -> Child Care Opening Date | C82: This field must be a date value or blank. Enter the expected/actual date the child care portion of the project will be open (when will the center be taking care of children?). This must be completed unless the project does not include child care.
A83: Col 36 | B83: =_xlfn.XLOOKUP(A83, 'Monthly Update'!$A$6:$AU$6, 'Monthly Update'!$A$7:$AU$7) -> Child Care Opening Date Error Explanation | C83: ="Use the field only if "& A82& " ("&B82&") indicates an error (cell is highlighted in purple) but you believe the information is correct, explain the descrpancy in this cell and it will remove the error formatting in "&A82&"." -> Use the field only if Col 35 (Child Care Opening Date) indicates an error (cell is highlighted in purple) but you believe the information is correct, explain the descrpancy in this cell and it will remove the error formatting in Col 35.
A84: Col 37 | B84: =_xlfn.XLOOKUP(A84, 'Monthly Update'!$A$6:$AU$6, 'Monthly Update'!$A$7:$AU$7) -> Financial Close-Out Date | C84: This field must be a date value. Enter the expected/actual date of financial close out for the project. At this point, all construction is complete, all deficiencies have been addressed and the financial close-out form has been submitted for final budget/cost reconciliation. This is generally 12-18 months after the opening date.
A85: ='Monthly Update'!AL5 -> Section 6: Approved Project Funding
A86: Col 38 | B86: =_xlfn.XLOOKUP(A86, 'Monthly Update'!$A$6:$AU$6, 'Monthly Update'!$A$7:$AU$7) -> Funding - All Associated Projects | C86: Automatically generated and uneditable.
A87: Col 39 | B87: =_xlfn.XLOOKUP(A87, 'Monthly Update'!$A$6:$AU$6, 'Monthly Update'!$A$7:$AU$7) -> Funding - Construction Project | C87: Automatically generated and uneditable.
A88: Col 40 | B88: =_xlfn.XLOOKUP(A88, 'Monthly Update'!$A$6:$AU$6, 'Monthly Update'!$A$7:$AU$7) -> Funding - Site Acquisition | C88: Automatically generated and uneditable.
A89: Col 41 | B89: =_xlfn.XLOOKUP(A89, 'Monthly Update'!$A$6:$AU$6, 'Monthly Update'!$A$7:$AU$7) -> Funding - Demolition | C89: Automatically generated and uneditable.
A90: Col 42 | B90: =_xlfn.XLOOKUP(A90, 'Monthly Update'!$A$6:$AU$6, 'Monthly Update'!$A$7:$AU$7) -> Funding - All Other Associated Projects | C90: Automatically generated and uneditable.
A91: ='Monthly Update'!AQ5 -> Section 7: Projected Cost
A92: Col 43 | B92: =_xlfn.XLOOKUP(A92, 'Monthly Update'!$A$6:$AU$6, 'Monthly Update'!$A$7:$AU$7) -> Basis of Cost Estimate | C92: Use the drop-down to indicate how the board determined the cost estimate.
A93: Col 44 | B93: =_xlfn.XLOOKUP(A93, 'Monthly Update'!$A$6:$AU$6, 'Monthly Update'!$A$7:$AU$7) -> Estimated Cost - Construction Project | C93: Enter the board's estimate of the total cost of the construction project. This includes the cost of the school portion, child care portion, site costs, and any other portion not captured in columns 45 to 47
A94: Col 45 | B94: =_xlfn.XLOOKUP(A94, 'Monthly Update'!$A$6:$AU$6, 'Monthly Update'!$A$7:$AU$7) -> Estimated Cost - Land | C94: Enter the estimated/actual cost of any land purchase associated with this project. Leave it blank if no land is needed for this project.
A95: Col 46 | B95: =_xlfn.XLOOKUP(A95, 'Monthly Update'!$A$6:$AU$6, 'Monthly Update'!$A$7:$AU$7) -> Estimated Cost - Demolition | C95: Use this only if the project will be associated with a separate project ID assigned to a demolition project. This would only happen if the board is demolishing an entire building as part of the project.
A96: Col 47 | B96: =_xlfn.XLOOKUP(A96, 'Monthly Update'!$A$6:$AU$6, 'Monthly Update'!$A$7:$AU$7) -> Estimated Cost - All Other Associated Projects | C96: Use this only in the rare circumstance where there is/will be any other project ID(s) associated with this project.

Sheet Board Contacts
A1: School Board Contact List
A4: Name | B4: Role | C4: Title | D4: Email | E4: Phone
A5: Milka Zlomislic | B5: Senior Buisness Official | C5: Superintendent of Capital Development and Asset Renewal | D5: milka.zlomislic@tcdsb.org
A6: Amal
A7: Michael Loberto | B7: Senior Buisness Official | C7: Superintendent of Planning and Development Services | D7: michael.loberto@tcdsb.org
A8: Barbara Leporati | B8: Primary Contact | C8: Head of Plannin Services Planning and Development | D8: barbara.leporati@tcdsb.org | E8: 416-222-8282 ext. 72270 or 416-522-8861 (cell)

Sheet Basic Project Info
A1: Basic Project Information
A2: =Translation!A5 -> Section 1: Project Details | K2: Section 2: Communications Issues
A3: ="Col "&COLUMN() -> Col 1 | B3: ="Col "&COLUMN() -> Col 2 | C3: ="Col "&COLUMN() -> Col 3 | D3: ="Col "&COLUMN() -> Col 4 | E3: ="Col "&COLUMN() -> Col 5 | F3: ="Col "&COLUMN() -> Col 6 | G3: ="Col "&COLUMN() -> Col 7 | H3: ="Col "&COLUMN() -> Col 8 | ... L3: ="Col "&COLUMN() -> Col 12
A4: =Translation!A6 -> Project ID | B4: =Translation!A7 -> Project Name | C4: Official School Name | D4: =Translation!A11 -> Project Type | E4: =Translation!A13 -> Project Category | F4: =Translation!A8 -> Address | G4: =Translation!A9 -> City | H4: =Translation!A10 -> Postal Code | I4: Latitude | J4: Longitude | K4: Sign Installed | L4: =Translation!A70 -> Opening Ceremony - Date
A5: No. de projet | B5: Nom du projet | D5: Type de projet | E5: Catégorie de projet
A7: 40-010-01 | B7: Blessed Cardinal Newman Catholic Secondary School | D7: New Construction | E7: Accommodation Pressure | F7: 100 BRIMLEY RD S | G7: SCARBOROUGH | H7: M1M3X4 | I7: 43.71291 | J7: -79.24269
A8: 40-017 | B8: Dante Alighieri Catholic Secondary School | D8: New Construction | E8: Accommodation Pressure | F8: 60 PLAYFAIR AVE | G8: NORTH YORK | H8: M6B2P9 | I8: 43.71017 | J8: -79.45802
A9: 40-076-01 | B9: St. Fidelis Catholic Elementary School | D9: New Construction | E9: Accommodation Pressure | F9: 155 FALSTAFF AVE | G9: NORTH YORK | H9: M6L2E5 | I9: 43.71768 | J9: -79.495826
A10: 40-109-01 | B10: St. Raymond Catholic Elementary School | C10: St. Peter Catholic Elementary School | D10: New Construction | E10: Consolidation | F10: 270 BARTON AVE | G10: TORONTO | H10: M6G1R4 | I10: 43.66592 | J10: -79.42317
A11: 40-127 | B11: St. Antoine Daniel Catholic Elementary School | D11: New Construction | E11: Accommodation Pressure | F11: 160 FINCH AVE W | G11: NORTH YORK | H11: M2N2J2 | I11: 43.777552 | J11: -79.429777
A12: 40-128 | B12: Regina Mundi Catholic Elementary School | D12: Retrofit | E12: Condition | F12: 70 PLAYFAIR AVE | G12: NORTH YORK | H12: M6B2P9 | I12: 43.71006 | J12: -79.4593
A13: 40-151 | B13: St. Michael's Choir Catholic Elementary School | D13: New Construction | E13: Condition | G13: TORONTO
A14: 40-152 | B14: Holy Angels Catholic Elementary School | D14: New Construction | E14: Accommodation Pressure | F14: 65 JUTLAND RD | G14: ETOBICOKE | H14: M8Z2G6 | I14: 43.628248 | J14: -79.517714
A15: 40-153 | B15: St. Matthias Catholic Elementary School | C15: Divine Mercy Catholic Elementary School | D15: New Construction | E15: Consolidation | F15: 101 VAN HORNE AVE | G15: NORTH YORK | H15: M2J2S8 | I15: 43.784481 | J15: -79.35948
A16: 40-154 | B16: St. Margaret Catholic Elementary School | D16: Addition | E16: Accommodation Pressure | F16: 85 CARMICHAEL AVE | G16: NORTH YORK | H16: M5M2X1 | I16: 43.73611 | J16: -79.42667
A17: 40-156 | B17: Baycrest Catholic Elementary School | D17: New Construction | E17: Accommodation Pressure | F17: 145 BAYCREST AVE | G17: NORTH YORK | H17: M6A1W4 | I17: 43.726739 | J17: -79.44428
A18: 40-157 | B18: Buttonwood Catholic Elementary School | D18: New Construction | E18: Accommodation Pressure | F18: 100 ALLANHURST DR | G18: TORONTO | H18: M9A4K4 | I18: 43.68026 | J18: -79.519277
A19: 40-158 | B19: Buttonwood Catholic Secondary School | D19: New Construction | E19: Accommodation Pressure | F19: 15 TREHORNE DR | G19: ETOBICOKE | H19: M9P1N8 | I19: 43.680688 | J19: -79.519123
A20: 40-159 | B20: Bishop Allen Academy Catholic Secondary School | D20: New Construction | E20: Accommodation Pressure | F20: 721 ROYAL YORK RD | G20: ETOBICOKE | H20: M8Y2T3 | I20: 43.634 | J20: -79.50543
A21: 40-160 | B21: Loretto Abbey Catholic Secondary School | D21: Addition | E21: Accommodation Pressure | F21: 101 MASON BLVD | G21: NORTH YORK | H21: M5M3E2 | I21: 43.74088 | J21: -79.4111
A22: 40-167 | B22: St. Elizabeth Catholic Elementary School | D22: New Construction | E22: Accommodation Pressure | G22: ETOBICOKE | H22: M9B1J8
A23: 40-168 | B23: St. Monica Catholic Elementary School | D23: New Construction | E23: Accommodation Pressure | G23: TORONTO | H23: M4P1T4
A24: 40-175 | B24: Block 9 Concord Place | D24: New Construction | E24: Accommodation Pressure | F24: SHEPPARD/LESLIE AREA | G24: NORTH YORK
A100: 1 | B100: 1 | C100: 1 | D100: 1 | E100: 1 | F100: 1 | G100: 1 | H100: 1 | I100: 1 | J100: 1 | K100: 1 | L100: 1

Sheet Monthly Update
A1: Monthly Project Updates | C1: 40 - Toronto Catholic DSB
E2: =COLUMNS($D$3:$AU$3) - COUNTIF($D$3:$AU$3, "") -> 0 | F2: 0
A3: Meeting Date | C3: 46072 | CX3: =COUNTA(CY9:ES104) -> 545 | CY3: TRUE | CZ3: =AND(CZ4, ISBLANK(CZ11)) -> FALSE | DA3: =AND(CAA4, ISBLANK(CAA11)) -> TRUE | DB3: =AND(CAB4, ISBLANK(CAB11)) -> TRUE | DC3: =AND(CAC4, ISBLANK(CAC11)) -> TRUE | DD3: =AND(CAD4, ISBLANK(CAD11)) -> TRUE | DE3: =AND(CAE4, ISBLANK(CAE11)) -> TRUE | DF3: =AND(CAF4, ISBLANK(CAF11)) -> TRUE | DG3: =AND(CAG4, ISBLANK(CAG11)) -> TRUE | DH3: =AND(CAH4, ISBLANK(CAH11)) -> TRUE | ... ES3: =AND(CBS4, ISBLANK(CBS11)) -> TRUE
B4: General Meeting Minutes: | AT4: Historical General Meeting Minutes -------------> | CX4: 97 | CY4: =ISNUMBER(SEARCH("formula", CY10)) -> FALSE | CZ4: =ISNUMBER(SEARCH("formula", CZ10)) -> FALSE | DA4: =ISNUMBER(SEARCH("formula", CAA10)) -> FALSE | DB4: =ISNUMBER(SEARCH("formula", CAB10)) -> FALSE | DC4: =ISNUMBER(SEARCH("formula", CAC10)) -> FALSE | DD4: =ISNUMBER(SEARCH("formula", CAD10)) -> FALSE | DE4: =ISNUMBER(SEARCH("formula", CAE10)) -> FALSE | DF4: =ISNUMBER(SEARCH("formula", CAF10)) -> FALSE | DG4: =ISNUMBER(SEARCH("formula", CAG10)) -> FALSE | DH4: =ISNUMBER(SEARCH("formula", CAH10)) -> FALSE | ... ES4: =ISNUMBER(SEARCH("formula", CBS10)) -> FALSE
A5: Section 1: Project Details | H5: Section 2: Project Commitment Progress | P5: Section 3: Pre-Tender | AB5: Section 4: Construction | AG5: Section 5: Project Completion | AL5: Section 6: Approved Project Funding | AQ5: Section 7: Projected Cost | AV5: Section 10: Project Risks and Mitigation Stategies | BD5: Section 8: Historical Meeting Minutes | CY5: Error Messages | DD5: Error Messages | DM5: Error Messages | DR5: Error Messages | DV5: Error Messages | DY5: Error Messages | EB5: Error Messages | EG5: Error Messages | EL5: Error Messages | EQ5: Error Messages
A6: Col 1 | B6: ="Col "&COLUMN() -> Col 2 | C6: ="Col "&COLUMN() -> Col 3 | D6: ="Col "&COLUMN() -> Col 4 | E6: ="Col "&COLUMN() -> Col 5 | F6: ="Col "&COLUMN() -> Col 6 | G6: ="Col "&COLUMN() -> Col 7 | H6: ="Col "&COLUMN() -> Col 8 | I6: ="Col "&COLUMN() -> Col 9 | ... AV6: ="Col "&COLUMN() -> Col 48 | BC6: ="Col "&COLUMN() -> Col 55 | BD6: ="Col "&COLUMN() -> Col 56 | BE6: ="Col "&COLUMN() -> Col 57 | BF6: ="Col "&COLUMN() -> Col 58 | BG6: ="Col "&COLUMN() -> Col 59 | BH6: ="Col "&COLUMN() -> Col 60 | BI6: ="Col "&COLUMN() -> Col 61 | BJ6: ="Col "&COLUMN() -> Col 62 | ... CA6: ="Col "&COLUMN() -> Col 79 | CY6: =A6 -> Col 1 | CZ6: =B6 -> Col 2 | DA6: =C6 -> Col 3 | DB6: =D6 -> Col 4 | DC6: =E6 -> Col 5 | DD6: =F6 -> Col 6 | DE6: =G6 -> Col 7 | DF6: =H6 -> Col 8 | ... ES6: =AU6 -> Col 47 | EW6: Col 11 | EX6: Col 11 | EY6: =EX6 -> Col 11 | EZ6: =EY6 -> Col 11 | FA6: Col 15 | FB6: Col 15 | FC6: =FB6 -> Col 15 | FD6: =FC6 -> Col 15 | FE6: Col 16 | FF6: Col 16 | FG6: =FF6 -> Col 16 | FH6: =FG6 -> Col 16 | FI6: Col 17 | FJ6: Col 17 | FK6: =FJ6 -> Col 17 | FL6: =FK6 -> Col 17
A7: Project ID | B7: Project Name | C7: Meeting Minutes | D7: Project Type | E7: Project Category | F7: Record Status | G7: Construction Status | H7: Pre-Tender Submission Date | I7: Pre-Tender Package Type | J7: Pre-Tender Package Complete | K7: CA Reviewed All Pre-Tender Documents | L7: Post-Tender Submission Date | M7: Post-Tender Package Type | N7: Post-Tender Package Complete | O7: CA Reviewed All Post-Tender Documents | P7: Site Ownership Status | Q7: Site Purchase Date | R7: Design Status | S7: Space Template Approval Date | T7: Child Care Floorplan Approval Date | U7: Initial Site Plan Submission Date | V7: Site Plan Approval Date | W7: Site Plan Approval Date Error Explanation | X7: Build Permit Obtained Date | Y7: Build Permit Obtained Date Error Explanation | Z7: Tender Issued Date | AA7: Tender Closed Date | AB7: Contract Awarded Date | AC7: Construction Start Date | AD7: Construction Start Date Error Explanation | AE7: Substantial Completion Date | AF7: Substantial Completion Date Error Explanation | AG7: School Opening Date | AH7: School Opening Date Error Explanation | AI7: Child Care Opening Date | AJ7: Child Care Opening Date Error Explanation | AK7: Financial Close-Out Date | AL7: Funding - All Associated Projects | AM7: Funding - Construction Project | AN7: Funding - Site Acquisition | AO7: Funding - Demolition | AP7: Funding - All Other Associated Projects | AQ7: Basis of Cost Estimate | AR7: Estimated Cost - Construction Project | AS7: Estimated Cost - Land | AT7: Estimated Cost - Demolition | AU7: Estimated Cost - All Other Associated Projects | AV7: Risk Type | AW7: Risk Rating | AX7: Risk Exposure Start Date | AY7: Min Cost of Risk ($M) | AZ7: Max Cost of Risk ($M) | BA7: Min Delay of Risk (Months) | BB7: Max Delay of Risk (Months) | BC7: Mitigation Stategies/Comments | BD7: December 04, 2025 | BE7: October 23, 2025 | BF7: September 29, 2025 | BG7: August 21, 2025 | BH7: August 27, 2024 | BI7: August 01, 2024 | BJ7: June 25, 2024 | BK7: May 30, 2024 | BL7: May 09, 2024 | BM7: April 04, 2024 | BN7: June 16, 2023 | CC7: *((table_end*((meeting_minutes_heading | CE7: cc_amount | CF7: Site Purchase Date | CG7: Space Template Approval Date | CH7: Child Care Floorplan Approval Date | CI7: Initial Site Plan Submission Date | CJ7: Site Plan Approval Date | CK7: Build Permit Obtained Date | CL7: Pre-Tender Submission Date | CM7: Tender Issued Date | CN7: Tender Closed Date | CO7: Post-Tender Submission Date | CP7: Contract Awarded Date | CQ7: Construction Start Date | CR7: Substantial Completion Date | CS7: School Opening Date | CT7: Child Care Opening Date | CU7: Financial Close-Out Date | CY7: =A7 -> Project ID | CZ7: =B7 -> Project Name | DA7: =C7 -> Meeting Minutes | DB7: =D7 -> Project Type | DC7: =E7 -> Project Category | DD7: =F7 -> Record Status | DE7: =G7 -> Construction Status | DF7: =H7 -> Pre-Tender Submission Date | ... ES7: =AU7 -> Estimated Cost - All Other Associated Projects
A8: No. de projet | B8: Nom du projet | D8: Type de projet | E8: Catégorie de projet | AN8: IP | AO8: Service de garde | AP8: Autre | AQ8: Base de l'estimation des coûts | AU8: Coûts du site
A10: 40-010-01 | B10: Blessed Cardinal Newman Catholic Secondary School | C10: The TCDSB team shared with the school community the tender price due to the escalation cost was much higher than the ministry allocation. The school board is now considering a re-design to fit within the ministry allocation. School board informed the contractor that the project is not moving at the moment. Costs incurred to date on this project (on architect designs, studies) is approximately $5M. Board will reconcile the funding. After the reconciliation, the board will part with the current architect and prepare another RFP for a new architectural team to take over (confidential information at the moment). Board plans to hire consultants to undertake a feasibility study and review designs to fit within budget and within the site limitations. Enrolment projections - Ministry to contact Planning to get revised enrolment numbers to see if the 1100pp is still correct. | D10: New Construction | E10: Accommodation Pressure | F10: In Progress | G10: =_xlfn.IFS($C$3>AK10, "Complete", $C$3>AG10, "Open", $C$3>AC10, "Under Construction", TRUE, "Planning") -> Planning | H10: 46418 | I10: Not Yet Known | J10: Not yet submitted/reviewed | K10: Not yet submitted/reviewed | L10: 46568 | M10: Not Yet Known | N10: Not yet submitted/reviewed | O10: Not yet submitted/reviewed | P10: Site Purchased | Q10: 41456 | R10: >80% Complete | S10: 43536 | V10: 45596 | X10: 46428 | Z10: 46428 | AA10: 46456 | AB10: 46583 | AC10: 46600 | AE10: 47611 | AG10: 47731 | AK10: 48096 | AL10: =SUM(AM10:AP10) -> 96240494 | AM10: 73057674 | AN10: 17452257 | AO10: 5730563 | AQ10: Based on Tender Results | BD10: Need update post letter - what is the board looking into, OTG scaledown?, Recommendation has not made public yet - Derek will organize an in person meeting to school community hopefully by the end of the year. SB has had problems with the city and the site plan (NOAC approved with manu conditions that are cleared at the end ofthe project). Legal was going to pursue the site plan with the city, but the SB indicated to stop all work due to confidential issues. Contractor who bid on the project has reached out to the Supervisor of the SB to discuss the project. It is likley possible the Contractor is not aware of the final ministry decision. | BE10: Tender is still open, contractor is holding the price until a decision is made. If the board needs to re-design the project - a change to the design, muncipal SPA, building permit etc will need to happen. The heritage designation happened after the project design began. The first SPA submission (May 2020) the buildings were NOT designated heritage. The original plan was to demolish all three buildings on site. The heritage designated happened in October 2021, the board recieved an intension to designate the structures in March 2021. | BF10: Tender is still open, contractor is holding the price until a decision is made. If the board needs to re-design the project - a change to the design, muncipal SPA, building permit etc will need to happen. The heritage designation happened after the project design began. The first SPA submission (May 2020) the buildings were NOT designated heritage. The original plan was to demolish all three buildings on site. The heritage designated happened in October 2021, the board recieved an intension to designate the structures in March 2021. | BG10: Tender is still open, and extending the tender month by month. What is the proposed schedule to demolish the non-heritage buildings/wing on site? Will remain on site until a ministry reponse is given. | CD10: =IF(AND(Q10="", A10<>"", P10<>"Site Purchased Prior to Capital Approval"), 1, 0) -> 0 | CE10: 0 | CF10: =_xlfn.XLOOKUP($A10, 'Project Commitment'!$A:$A, 'Project Commitment'!M:M, "") -> 0 | CG10: =_xlfn.XLOOKUP($A10, 'Project Commitment'!$A:$A, 'Project Commitment'!N:N, "") -> 0 | CH10: =_xlfn.XLOOKUP($A10, 'Project Commitment'!$A:$A, 'Project Commitment'!O:O, "") -> 0 | CI10: =_xlfn.XLOOKUP($A10, 'Project Commitment'!$A:$A, 'Project Commitment'!P:P, "") -> 0 | CJ10: =_xlfn.XLOOKUP($A10, 'Project Commitment'!$A:$A, 'Project Commitment'!Q:Q, "") -> 0 | CK10: =_xlfn.XLOOKUP($A10, 'Project Commitment'!$A:$A, 'Project Commitment'!R:R, "") -> 0 | CL10: =_xlfn.XLOOKUP($A10, 'Project Commitment'!$A:$A, 'Project Commitment'!S:S, "") -> #VALUE! | CM10: =_xlfn.XLOOKUP($A10, 'Project Commitment'!$A:$A, 'Project Commitment'!T:T, "") -> 0 | CN10: =_xlfn.XLOOKUP($A10, 'Project Commitment'!$A:$A, 'Project Commitment'!U:U, "") -> #VALUE! | CO10: =_xlfn.XLOOKUP($A10, 'Project Commitment'!$A:$A, 'Project Commitment'!V:V, "") -> #VALUE! | CP10: =_xlfn.XLOOKUP($A10, 'Project Commitment'!$A:$A, 'Project Commitment'!W:W, "") -> 0 | CQ10: =_xlfn.XLOOKUP($A10, 'Project Commitment'!$A:$A, 'Project Commitment'!X:X, "") -> -942 | CR10: =_xlfn.XLOOKUP($A10, 'Project Commitment'!$A:$A, 'Project Commitment'!Y:Y, "") -> #VALUE! | CS10: =_xlfn.XLOOKUP($A10, 'Project Commitment'!$A:$A, 'Project Commitment'!Z:Z, "") -> -1100 | CT10: =_xlfn.XLOOKUP($A10, 'Project Commitment'!$A:$A, 'Project Commitment'!AA:AA, "") -> 0 | CU10: =_xlfn.XLOOKUP($A10, 'Project Commitment'!$A:$A, 'Project Commitment'!AB:AB, "") -> #VALUE! | DA10: =IF(C10="", "Meeting Minutes cannot be blank", "") | DF10: =_xlfn.IFS(AND(J10="Not Applicable", H10<>""), "No date is needed if Column 10 is Not Applicable",J10= "Not Applicable", "", H10="",DF$7&" cannot be blank", $AC10="", "", H10>$AC10, DF$7&" must preceed construction start date.", TRUE, "") | DG10: =_xlfn.IFS(I10="", DG$7&" cannot be left blank.",H10="", "", AND( H10 < TODAY(), I10="Not Yet Known"), "After the submission date, the pre-tender package type must be selected.", TRUE, "") | DI10: =EW10 | DJ10: =_xlfn.IFS(AND(N10="Not Applicable", L10<>""), "No date is needed if Column 14 is Not Applicable",N10= "Not Applicable", "", L10="",DJ$7&" cannot be blank", $AC10="", "", L10>$AC10, DJ$7&" must preceed construction start date.", TRUE, "") | DK10: =_xlfn.IFS(M10="", DK$7&" cannot be left blank.",L10="", "", AND( L10 < TODAY(), M10="Not Yet Known"), "After the submission date, the pre-tender package type must be selected.", TRUE, "") | DM10: =FA10 | DN10: =FE10 | DO10: =FI10 | DP10: =IF(R10="", DP$7&" cannot be blank", "") | DQ10: =_xlfn.IFS(S10="",DQ$7&" cannot be blank",AND(J10<>"Not yet submitted/reviewed",S10>TODAY()),DQ$7&" cannot be in the future if project is ready for a pre-tender package.",TRUE,"") | DR10: =_xlfn.IFS(CE10=0, "", T10="",DR$7&" cannot be blank if project includes child care.", AND(J10="Not Applicable",T10>TODAY()), "Projects under construction must have a "&DR$7, J10="Not Applicable", "", T10<I10, T6&" must preceed pre-tender package submission date",TRUE, "") | DS10: =_xlfn.IFS(U10="",DS$7&" cannot be blank", $AC10="", "", U10>$AC10, DS$7&" must preceed construction start date.", TRUE, "") -> Initial Site Plan Submission Date cannot be blank | DT10: =_xlfn.IFS(W10<>"", "", V10="",DT$7&" cannot be blank", $AC10="", "", V10>$AC10, DT$7&" must preceed construction start date.", TRUE, "") | DV10: =_xlfn.IFS(Y10<>"", "", X10="",DV$7&" cannot be blank", $AC10="", "", X10>$AC10, DV$7&" must preceed construction start date.", TRUE, "") | DX10: =_xlfn.IFS(Z10="",DX$7&" cannot be blank", $AC10="", "", Z10>$AC10, DX$7&" must preceed construction start date.", TRUE, "") | DY10: =_xlfn.IFS(AA10="",DY$7&" cannot be blank", $AC10="", "", AA10>$AC10, DY$7&" must preceed construction start date.", TRUE, "") | DZ10: =_xlfn.IFS(AB10="",DZ$7&" cannot be blank", $AC10="", "", AB10>$AC10, DZ$7&" must preceed construction start date.", TRUE, "") | EA10: =_xlfn.IFS(AD10<>"", "", AC10="",EA$7&" cannot be blank", $AG10="", "", AC10>EDATE($AG10,-12), EA$7&" must preceed school opening date by more than 12 months.", TRUE, "") | EC10: =_xlfn.IFS(AF10<>"", "", AE10="",EC$7&" cannot be blank", $AG10="", "", AE10>EDATE($AG10,-1), EC$7&" must preceed school opening date by more than one month.", TRUE, "") | EE10: =_xlfn.IFS(AK10="", "", AG10="",EE$7&" cannot be blank",AH10<>"", "", $AG10="", "", AG10>=EDATE($AK10,-11), EE$7&" must preceed financial close date by at least 12 months.", TRUE, "") | EG10: =_xlfn.IFS(CE10=0, "", AI10="",EG$7&" cannot be blank",$AK10="", "",AJ10<>"", "", AI10>=EDATE($AK10,0), EG$7&" must preceed financial close date.", TRUE, "") | EI10: =_xlfn.IFS( AK10="",EI$7&" cannot be blank", TRUE, "") | EO10: =_xlfn.IFS(AQ10="", "Basis of Cost Estimate cannot be blank", AND(AC10<TODAY(), AQ10<>"Based on Tender Results"), "Contract awarded date suggests estimate should be based on tender results", AND(H10<TODAY(), AQ10<>"Based on Class A or B Cost Report"), "If project has already come in for a pre-tender budget, they must have a class A or B cost estimate.", TRUE, "") | EP10: =_xlfn.IFS(OR(AM10=0, AM10=""), "", AR10="", EP$7&" cannot be blank.", TRUE, "") -> Estimated Cost - Construction Project cannot be blank. | EQ10: =_xlfn.IFS(OR(AN10=0, AN10=""), "", AS10="", EQ$7&" cannot be blank.", TRUE, "") -> Estimated Cost - Land cannot be blank. | ER10: =_xlfn.IFS(OR(AO10=0, AO10=""), "", AT10="", ER$7&" cannot be blank.", TRUE, "") -> Estimated Cost - Demolition cannot be blank. | ES10: =_xlfn.IFS(OR(AP10=0, AP10=""), "", AU10="", ES$7&" cannot be blank.", TRUE, "") | EW10: =_xlfn.IFS(EX10<>"", EX10, EY10<>"", EY10, EZ10<>"", EZ10, TRUE, "") | EX10: =IF(J10="MISSING", "This package is missing!", "") | EY10: =IF(K10="", "Confirm you reviewed the pretender checkin documents", "") | EZ10: =IF(AND(K10="Not yet submitted/reviewed", J10<>"Not yet submitted/reviewed"), "Pretender package submitted; col 9 cann't indicate otherwise.", "") | FA10: =_xlfn.IFS(FB10<>"", FB10, FC10<>"", FC10, FD10<>"", FD10, TRUE, "") | FB10: =IF(N10="MISSING", "The post tender package is missing!", "") | FC10: =IF(O10="", "Confirm you reviewed the post tender check-in documents", "") | FD10: =IF(AND(O10="Not yet submitted/reviewed", N10<>"Not yet submitted/reviewed"), "Post-tender package submitted; col 9 cann't indicate otherwise.", "") | FE10: =_xlfn.IFS(FF10<>"", FF10, FG10<>"", FG10, TRUE, FH10) | FF10: =IF(P10<>"", "", "Site Ownership Status cannot be blank") | FG10: =_xlfn.IFS(AND(Q10="", OR(P10="Site Purchased Prior to Capital Approval", P10="Site Purchased")), "", AND(OR(P10="Site Purchased Prior to Capital Approval", P10="Site Purchased"), Q10>TODAY()), "Site purchase date is in the future, but site ownership status indicates site is already purchaseed", TRUE, "") | FH10: =IF(AND(AND(P10<>"Site Purchased Prior to Capital Approval", P10<>"Site Purchased"), Q10<=TODAY()), "Site purchase date is in the past, but site ownership status indicates site has not yet been purchaseed", "") | FI10: =_xlfn.IFS(FJ10<>"", FJ10, FK10<>"", FK10, TRUE,FL10 ) | FJ10: =IF(AND(P10<>"Not Applicable",Q10=""),"Site Purchased Date cannot be blank","") | FK10: =FE10 | FL10: =_xlfn.IFS(Q10="", "", U10="", "", Q10>U10, "Site Purchase Date must preceed Site Plan Submission.", TRUE, "")
A11: 40-017 | B11: Dante Alighieri Catholic Secondary School | C11: Construction underway - completing water tight. Utilities not connected at this point, but in the next few days. Enbridge working to get heat to the site. Waiting for windows. Hoping to have the building fully enclosed for end of February. Progressing well, no concerns with opening and budget. | D11: New Construction | E11: Accommodation Pressure | F11: In Progress | G11: =_xlfn.IFS($C$3>AK11, "Complete", $C$3>AG11, "Open", $C$3>AC11, "Under Construction", TRUE, "Planning") -> Under Construction | H11: 45140 | I11: Not Applicable | J11: Not Applicable | K11: Not Applicable | L11: 45245 | M11: Not Applicable | N11: Not Applicable | O11: Not Applicable | P11: Not Applicable | R11: >80% Complete | S11: 43692 | V11: 45531 | X11: 45531 | Z11: 45214 | AA11: 45245 | AB11: 45267 | AC11: 45338 | AE11: 46203 | AG11: 46273 | AK11: 46688 | AL11: =SUM(AM11:AP11) -> 62436028 | AM11: 60656214 | AO11: 1779814 | AQ11: Based on Tender Results | BD11: Dante construction is underway and on schedule. As of December, the project is not water tight, SB was hopignt ohave this complete before winter. Some windows in, frames are installed, glazing not finished, green roof not finished (some issues). If not water tight and winter sets in, there will be added costs. Still not 100% water tight. Amal to provide update next meeting re. if the project is water tight at that point. Working out utilities and encountering problems currently with Enbridge, Rogers etc. BOard has resolved Hydro issues at the moment. Supply challenges with elevators (vertex), SB has is using Vertex on six other schools (problem with low bidding). The Regina Mundi playground and parking lot is almost complete. City - placed a hold on digging underground along the street (due to recent paving), not sure how the u/g servicing will be done. Servicing may need to be above ground. Redesign needs to happen. This also happened with the Baycrest project - new trees planted where drop off area is designed to be. | BE11: Dante construction is underway and on schedule. At this point, the contractor has finished water tight, working on windows before the winter season. Working out utilities - Enbridge, Rogers etc. Supply challenges with elevators (vertex), other schools also have challeges with elevators. The Regina Mundi playground and parking lot is almost complete. | BF11: Dante construction is underway and on schedule. At this point, the contractor is working to have the building water tight (water proofing, windows in, roof complete) before the winter season. The Regina Mundi playground and parking lot is almost complete. | BG11: RMC Playground is almost complete. Gates might be installed at a later date. Dante construction is underway and on schedule. | CD11: =IF(AND(Q11="", A11<>"", P11<>"Site Purchased Prior to Capital Approval"), 1, 0) -> 1 | CE11: 0 | CF11: =_xlfn.XLOOKUP($A11, 'Project Commitment'!$A:$A, 'Project Commitment'!M:M, "") -> 0 | CG11: =_xlfn.XLOOKUP($A11, 'Project Commitment'!$A:$A, 'Project Commitment'!N:N, "") -> 0 | CH11: =_xlfn.XLOOKUP($A11, 'Project Commitment'!$A:$A, 'Project Commitment'!O:O, "") -> 0 | CI11: =_xlfn.XLOOKUP($A11, 'Project Commitment'!$A:$A, 'Project Commitment'!P:P, "") -> 0 | CJ11: =_xlfn.XLOOKUP($A11, 'Project Commitment'!$A:$A, 'Project Commitment'!Q:Q, "") -> 0 | CK11: =_xlfn.XLOOKUP($A11, 'Project Commitment'!$A:$A, 'Project Commitment'!R:R, "") -> 0 | CL11: =_xlfn.XLOOKUP($A11, 'Project Commitment'!$A:$A, 'Project Commitment'!S:S, "") -> #VALUE! | CM11: =_xlfn.XLOOKUP($A11, 'Project Commitment'!$A:$A, 'Project Commitment'!T:T, "") -> 0 | CN11: =_xlfn.XLOOKUP($A11, 'Project Commitment'!$A:$A, 'Project Commitment'!U:U, "") -> 22 | CO11: =_xlfn.XLOOKUP($A11, 'Project Commitment'!$A:$A, 'Project Commitment'!V:V, "") -> #VALUE! | CP11: =_xlfn.XLOOKUP($A11, 'Project Commitment'!$A:$A, 'Project Commitment'!W:W, "") -> 0 | CQ11: =_xlfn.XLOOKUP($A11, 'Project Commitment'!$A:$A, 'Project Commitment'!X:X, "") -> 0 | CR11: =_xlfn.XLOOKUP($A11, 'Project Commitment'!$A:$A, 'Project Commitment'!Y:Y, "") -> 0 | CS11: =_xlfn.XLOOKUP($A11, 'Project Commitment'!$A:$A, 'Project Commitment'!Z:Z, "") -> 0 | CT11: =_xlfn.XLOOKUP($A11, 'Project Commitment'!$A:$A, 'Project Commitment'!AA:AA, "") -> 0 | CU11: =_xlfn.XLOOKUP($A11, 'Project Commitment'!$A:$A, 'Project Commitment'!AB:AB, "") -> -50 | DA11: =IF(C11="", "Meeting Minutes cannot be blank", "") | DF11: =_xlfn.IFS(AND(J11="Not Applicable", H11<>""), "No date is needed if Column 10 is Not Applicable",J11= "Not Applicable", "", H11="",DF$7&" cannot be blank", $AC11="", "", H11>$AC11, DF$7&" must preceed construction start date.", TRUE, "") -> No date is needed if Column 10 is Not Applicable | DG11: =_xlfn.IFS(I11="", DG$7&" cannot be left blank.",H11="", "", AND( H11 < TODAY(), I11="Not Yet Known"), "After the submission date, the pre-tender package type must be selected.", TRUE, "") | DI11: =EW11 | DJ11: =_xlfn.IFS(AND(N11="Not Applicable", L11<>""), "No date is needed if Column 14 is Not Applicable",N11= "Not Applicable", "", L11="",DJ$7&" cannot be blank", $AC11="", "", L11>$AC11, DJ$7&" must preceed construction start date.", TRUE, "") -> No date is needed if Column 14 is Not Applicable | DK11: =_xlfn.IFS(M11="", DK$7&" cannot be left blank.",L11="", "", AND( L11 < TODAY(), M11="Not Yet Known"), "After the submission date, the pre-tender package type must be selected.", TRUE, "") | DM11: =FA11 | DN11: =FE11 | DO11: =FI11 | DP11: =IF(R11="", DP$7&" cannot be blank", "") | DQ11: =_xlfn.IFS(S11="",DQ$7&" cannot be blank",AND(J11<>"Not yet submitted/reviewed",S11>TODAY()),DQ$7&" cannot be in the future if project is ready for a pre-tender package.",TRUE,"") | DR11: =_xlfn.IFS(CE11=0, "", T11="",DR$7&" cannot be blank if project includes child care.", AND(J11="Not Applicable",T11>TODAY()), "Projects under construction must have a "&DR$7, J11="Not Applicable", "", T11<I11, T7&" must preceed pre-tender package submission date",TRUE, "") | DS11: =_xlfn.IFS(U11="",DS$7&" cannot be blank", $AC11="", "", U11>$AC11, DS$7&" must preceed construction start date.", TRUE, "") -> Initial Site Plan Submission Date cannot be blank | DT11: =_xlfn.IFS(W11<>"", "", V11="",DT$7&" cannot be blank", $AC11="", "", V11>$AC11, DT$7&" must preceed construction start date.", TRUE, "") -> Site Plan Approval Date must preceed construction start date. | DV11: =_xlfn.IFS(Y11<>"", "", X11="",DV$7&" cannot be blank", $AC11="", "", X11>$AC11, DV$7&" must preceed construction start date.", TRUE, "") -> Build Permit Obtained Date must preceed construction start date. | DX11: =_xlfn.IFS(Z11="",DX$7&" cannot be blank", $AC11="", "", Z11>$AC11, DX$7&" must preceed construction start date.", TRUE, "") | DY11: =_xlfn.IFS(AA11="",DY$7&" cannot be blank", $AC11="", "", AA11>$AC11, DY$7&" must preceed construction start date.", TRUE, "") | DZ11: =_xlfn.IFS(AB11="",DZ$7&" cannot be blank", $AC11="", "", AB11>$AC11, DZ$7&" must preceed construction start date.", TRUE, "") | EA11: =_xlfn.IFS(AD11<>"", "", AC11="",EA$7&" cannot be blank", $AG11="", "", AC11>EDATE($AG11,-12), EA$7&" must preceed school opening date by more than 12 months.", TRUE, "") | EC11: =_xlfn.IFS(AF11<>"", "", AE11="",EC$7&" cannot be blank", $AG11="", "", AE11>EDATE($AG11,-1), EC$7&" must preceed school opening date by more than one month.", TRUE, "") | EE11: =_xlfn.IFS(AK11="", "", AG11="",EE$7&" cannot be blank",AH11<>"", "", $AG11="", "", AG11>=EDATE($AK11,-11), EE$7&" must preceed financial close date by at least 12 months.", TRUE, "") | EG11: =_xlfn.IFS(CE11=0, "", AI11="",EG$7&" cannot be blank",$AK11="", "",AJ11<>"", "", AI11>=EDATE($AK11,0), EG$7&" must preceed financial close date.", TRUE, "") | EI11: =_xlfn.IFS( AK11="",EI$7&" cannot be blank", TRUE, "") | EO11: =_xlfn.IFS(AQ11="", "Basis of Cost Estimate cannot be blank", AND(AC11<TODAY(), AQ11<>"Based on Tender Results"), "Contract awarded date suggests estimate should be based on tender results", AND(H11<TODAY(), AQ11<>"Based on Class A or B Cost Report"), "If project has already come in for a pre-tender budget, they must have a class A or B cost estimate.", TRUE, "") -> If project has already come in for a pre-tender budget, they must have a class A or B cost estimate. | EP11: =_xlfn.IFS(OR(AM11=0, AM11=""), "", AR11="", EP$7&" cannot be blank.", TRUE, "") -> Estimated Cost - Construction Project cannot be blank. | EQ11: =_xlfn.IFS(OR(AN11=0, AN11=""), "", AS11="", EQ$7&" cannot be blank.", TRUE, "") | ER11: =_xlfn.IFS(OR(AO11=0, AO11=""), "", AT11="", ER$7&" cannot be blank.", TRUE, "") -> Estimated Cost - Demolition cannot be blank. | ES11: =_xlfn.IFS(OR(AP11=0, AP11=""), "", AU11="", ES$7&" cannot be blank.", TRUE, "") | EW11: =_xlfn.IFS(EX11<>"", EX11, EY11<>"", EY11, EZ11<>"", EZ11, TRUE, "") | EX11: =IF(J11="MISSING", "This package is missing!", "") | EY11: =IF(K11="", "Confirm you reviewed the pretender checkin documents", "") | EZ11: =IF(AND(K11="Not yet submitted/reviewed", J11<>"Not yet submitted/reviewed"), "Pretender package submitted; col 9 cann't indicate otherwise.", "") | FA11: =_xlfn.IFS(FB11<>"", FB11, FC11<>"", FC11, FD11<>"", FD11, TRUE, "") | FB11: =IF(N11="MISSING", "The post tender package is missing!", "") | FC11: =IF(O11="", "Confirm you reviewed the post tender check-in documents", "") | FD11: =IF(AND(O11="Not yet submitted/reviewed", N11<>"Not yet submitted/reviewed"), "Post-tender package submitted; col 9 cann't indicate otherwise.", "") | FE11: =_xlfn.IFS(FF11<>"", FF11, FG11<>"", FG11, TRUE, FH11) | FF11: =IF(P11<>"", "", "Site Ownership Status cannot be blank") | FG11: =_xlfn.IFS(AND(Q11="", OR(P11="Site Purchased Prior to Capital Approval", P11="Site Purchased")), "", AND(OR(P11="Site Purchased Prior to Capital Approval", P11="Site Purchased"), Q11>TODAY()), "Site purchase date is in the future, but site ownership status indicates site is already purchaseed", TRUE, "") | FH11: =IF(AND(AND(P11<>"Site Purchased Prior to Capital Approval", P11<>"Site Purchased"), Q11<=TODAY()), "Site purchase date is in the past, but site ownership status indicates site has not yet been purchaseed", "") | FI11: =_xlfn.IFS(FJ11<>"", FJ11, FK11<>"", FK11, TRUE,FL11 ) | FJ11: =IF(AND(P11<>"Not Applicable",Q11=""),"Site Purchased Date cannot be blank","") | FK11: =FE11 | FL11: =_xlfn.IFS(Q11="", "", U11="", "", Q11>U11, "Site Purchase Date must preceed Site Plan Submission.", TRUE, "")
A12: 40-076-01 | B12: St. Fidelis Catholic Elementary School | C12: School opened in September 2025, with a partial occupancy permit. Board still doesnt have full occupancy permit due to the elevator installation not completion. The child care centre construction is complete but part of licensing is that a full occupnancy permit is in place. The Elevator operator (Vertix) has not been to the site since September. They are billing for work that doesn’t match the work that has progressed to date. School board is working with legal team to remove the elevator contractor from the job. Once the legal has been sorted out and another elevator contractor can be hired and brought in,. Installation scheduling will need to be scheduled when students aren't in the facility. | D12: New Construction | E12: Accommodation Pressure | F12: In Progress | G12: =_xlfn.IFS($C$3>AK12, "Complete", $C$3>AG12, "Open", $C$3>AC12, "Under Construction", TRUE, "Planning") -> Open | I12: Not Applicable | J12: Not Applicable | K12: Not Applicable | M12: Not Applicable | N12: Not Applicable | O12: Not Applicable | P12: Site Purchased | Q12: 43525 | R12: >80% Complete | S12: 42408 | V12: 45194 | AB12: 44953 | AC12: 45065 | AE12: 45810 | AG12: 45902 | AI12: 46296 | AK12: 46689 | AL12: =SUM(AM12:AP12) -> 48842266 | AM12: 30245269 | AN12: 15750000 | AO12: 2846997 | AQ12: Based on Tender Results | BD12: School opened September 2, 2025, with partial occupancy - gymnasium and child care were not complete. Gymnasium was completed in November while child care centre is expected to open January 5, 2026. Board hopes to get occupancy of the building, but it wont be full occupancy due to the elevator not installed. Vertex dropped off the elevator equipment in the chlid care centre. The general contractor cant touch the equpment bc it becomes his responsibility. ...so the elevator equipment is sitting in the cc centre. General contractor is requesting "up front payment" for work not undertaken yet regarding the elevator. SB holding off on it. | BE12: School expected to open September 2, 2025. School opened with partial occupancy, not full occupancy, b/c gymnasium and child care were not complete. Currently contractor is working on construction deficiencies and finishing the licensing requirements for the child care centre. Child care centre is expected to open January 5, 2026. It is expected the school will have full occupnacy by end of November, at which point the child care and gymnasium will be in use. Gym should be complete for November. | BF12: School expected to open September 2, 2025. School opened with partial occupancy, not full occupancy, b/c gymnasium and child care were not complete. Currently contractor is working on construction deficiencies and finishing the licensing requirements for the child care centre. Child care centre is expected to open January 5, 2026. It is expected the school will have full occupnacy by end of November, at which point the child care and gymnasium will be in use. | BG12: School expected to open September 2, 2025. Child care centre is expected to open January 5, 2026, the delay is a result of licensing. | CD12: =IF(AND(Q12="", A12<>"", P12<>"Site Purchased Prior to Capital Approval"), 1, 0) -> 0 | CE12: 39 | CF12: =_xlfn.XLOOKUP($A12, 'Project Commitment'!$A:$A, 'Project Commitment'!M:M, "") -> 0 | CG12: =_xlfn.XLOOKUP($A12, 'Project Commitment'!$A:$A, 'Project Commitment'!N:N, "") -> 0 | CH12: =_xlfn.XLOOKUP($A12, 'Project Commitment'!$A:$A, 'Project Commitment'!O:O, "") -> 0 | CI12: =_xlfn.XLOOKUP($A12, 'Project Commitment'!$A:$A, 'Project Commitment'!P:P, "") -> 0 | CJ12: =_xlfn.XLOOKUP($A12, 'Project Commitment'!$A:$A, 'Project Commitment'!Q:Q, "") -> 0 | CK12: =_xlfn.XLOOKUP($A12, 'Project Commitment'!$A:$A, 'Project Commitment'!R:R, "") -> 0 | CL12: =_xlfn.XLOOKUP($A12, 'Project Commitment'!$A:$A, 'Project Commitment'!S:S, "") -> #VALUE! | CM12: =_xlfn.XLOOKUP($A12, 'Project Commitment'!$A:$A, 'Project Commitment'!T:T, "") -> 0 | CN12: =_xlfn.XLOOKUP($A12, 'Project Commitment'!$A:$A, 'Project Commitment'!U:U, "") -> 44953 | CO12: =_xlfn.XLOOKUP($A12, 'Project Commitment'!$A:$A, 'Project Commitment'!V:V, "") -> #VALUE! | CP12: =_xlfn.XLOOKUP($A12, 'Project Commitment'!$A:$A, 'Project Commitment'!W:W, "") -> 0 | CQ12: =_xlfn.XLOOKUP($A12, 'Project Commitment'!$A:$A, 'Project Commitment'!X:X, "") -> 0 | CR12: =_xlfn.XLOOKUP($A12, 'Project Commitment'!$A:$A, 'Project Commitment'!Y:Y, "") -> 39 | CS12: =_xlfn.XLOOKUP($A12, 'Project Commitment'!$A:$A, 'Project Commitment'!Z:Z, "") -> 0 | CT12: =_xlfn.XLOOKUP($A12, 'Project Commitment'!$A:$A, 'Project Commitment'!AA:AA, "") -> 0 | CU12: =_xlfn.XLOOKUP($A12, 'Project Commitment'!$A:$A, 'Project Commitment'!AB:AB, "") -> -422 | DA12: =IF(C12="", "Meeting Minutes cannot be blank", "") | DF12: =_xlfn.IFS(AND(J12="Not Applicable", H12<>""), "No date is needed if Column 10 is Not Applicable",J12= "Not Applicable", "", H12="",DF$7&" cannot be blank", $AC12="", "", H12>$AC12, DF$7&" must preceed construction start date.", TRUE, "") | DG12: =_xlfn.IFS(I12="", DG$7&" cannot be left blank.",H12="", "", AND( H12 < TODAY(), I12="Not Yet Known"), "After the submission date, the pre-tender package type must be selected.", TRUE, "") | DI12: =EW12 | DJ12: =_xlfn.IFS(AND(N12="Not Applicable", L12<>""), "No date is needed if Column 14 is Not Applicable",N12= "Not Applicable", "", L12="",DJ$7&" cannot be blank", $AC12="", "", L12>$AC12, DJ$7&" must preceed construction start date.", TRUE, "") | DK12: =_xlfn.IFS(M12="", DK$7&" cannot be left blank.",L12="", "", AND( L12 < TODAY(), M12="Not Yet Known"), "After the submission date, the pre-tender package type must be selected.", TRUE, "") | DM12: =FA12 | DN12: =FE12 | DO12: =FI12 | DP12: =IF(R12="", DP$7&" cannot be blank", "") | DQ12: =_xlfn.IFS(S12="",DQ$7&" cannot be blank",AND(J12<>"Not yet submitted/reviewed",S12>TODAY()),DQ$7&" cannot be in the future if project is ready for a pre-tender package.",TRUE,"") | DR12: =_xlfn.IFS(CE12=0, "", T12="",DR$7&" cannot be blank if project includes child care.", AND(J12="Not Applicable",T12>TODAY()), "Projects under construction must have a "&DR$7, J12="Not Applicable", "", T12<I12, T8&" must preceed pre-tender package submission date",TRUE, "") -> Child Care Floorplan Approval Date cannot be blank if project includes child care. | DS12: =_xlfn.IFS(U12="",DS$7&" cannot be blank", $AC12="", "", U12>$AC12, DS$7&" must preceed construction start date.", TRUE, "") -> Initial Site Plan Submission Date cannot be blank | DT12: =_xlfn.IFS(W12<>"", "", V12="",DT$7&" cannot be blank", $AC12="", "", V12>$AC12, DT$7&" must preceed construction start date.", TRUE, "") -> Site Plan Approval Date must preceed construction start date. | DV12: =_xlfn.IFS(Y12<>"", "", X12="",DV$7&" cannot be blank", $AC12="", "", X12>$AC12, DV$7&" must preceed construction start date.", TRUE, "") -> Build Permit Obtained Date cannot be blank | DX12: =_xlfn.IFS(Z12="",DX$7&" cannot be blank", $AC12="", "", Z12>$AC12, DX$7&" must preceed construction start date.", TRUE, "") -> Tender Issued Date cannot be blank | DY12: =_xlfn.IFS(AA12="",DY$7&" cannot be blank", $AC12="", "", AA12>$AC12, DY$7&" must preceed construction start date.", TRUE, "") -> Tender Closed Date cannot be blank | DZ12: =_xlfn.IFS(AB12="",DZ$7&" cannot be blank", $AC12="", "", AB12>$AC12, DZ$7&" must preceed construction start date.", TRUE, "") | EA12: =_xlfn.IFS(AD12<>"", "", AC12="",EA$7&" cannot be blank", $AG12="", "", AC12>EDATE($AG12,-12), EA$7&" must preceed school opening date by more than 12 months.", TRUE, "") | EC12: =_xlfn.IFS(AF12<>"", "", AE12="",EC$7&" cannot be blank", $AG12="", "", AE12>EDATE($AG12,-1), EC$7&" must preceed school opening date by more than one month.", TRUE, "") | EE12: =_xlfn.IFS(AK12="", "", AG12="",EE$7&" cannot be blank",AH12<>"", "", $AG12="", "", AG12>=EDATE($AK12,-11), EE$7&" must preceed financial close date by at least 12 months.", TRUE, "") | EG12: =_xlfn.IFS(CE12=0, "", AI12="",EG$7&" cannot be blank",$AK12="", "",AJ12<>"", "", AI12>=EDATE($AK12,0), EG$7&" must preceed financial close date.", TRUE, "") | EI12: =_xlfn.IFS( AK12="",EI$7&" cannot be blank", TRUE, "") | EO12: =_xlfn.IFS(AQ12="", "Basis of Cost Estimate cannot be blank", AND(AC12<TODAY(), AQ12<>"Based on Tender Results"), "Contract awarded date suggests estimate should be based on tender results", AND(H12<TODAY(), AQ12<>"Based on Class A or B Cost Report"), "If project has already come in for a pre-tender budget, they must have a class A or B cost estimate.", TRUE, "") | EP12: =_xlfn.IFS(OR(AM12=0, AM12=""), "", AR12="", EP$7&" cannot be blank.", TRUE, "") -> Estimated Cost - Construction Project cannot be blank. | EQ12: =_xlfn.IFS(OR(AN12=0, AN12=""), "", AS12="", EQ$7&" cannot be blank.", TRUE, "") -> Estimated Cost - Land cannot be blank. | ER12: =_xlfn.IFS(OR(AO12=0, AO12=""), "", AT12="", ER$7&" cannot be blank.", TRUE, "") -> Estimated Cost - Demolition cannot be blank. | ES12: =_xlfn.IFS(OR(AP12=0, AP12=""), "", AU12="", ES$7&" cannot be blank.", TRUE, "") | EW12: =_xlfn.IFS(EX12<>"", EX12, EY12<>"", EY12, EZ12<>"", EZ12, TRUE, "") | EX12: =IF(J12="MISSING", "This package is missing!", "") | EY12: =IF(K12="", "Confirm you reviewed the pretender checkin documents", "") | EZ12: =IF(AND(K12="Not yet submitted/reviewed", J12<>"Not yet submitted/reviewed"), "Pretender package submitted; col 9 cann't indicate otherwise.", "") | FA12: =_xlfn.IFS(FB12<>"", FB12, FC12<>"", FC12, FD12<>"", FD12, TRUE, "") | FB12: =IF(N12="MISSING", "The post tender package is missing!", "") | FC12: =IF(O12="", "Confirm you reviewed the post tender check-in documents", "") | FD12: =IF(AND(O12="Not yet submitted/reviewed", N12<>"Not yet submitted/reviewed"), "Post-tender package submitted; col 9 cann't indicate otherwise.", "") | FE12: =_xlfn.IFS(FF12<>"", FF12, FG12<>"", FG12, TRUE, FH12) | FF12: =IF(P12<>"", "", "Site Ownership Status cannot be blank") | FG12: =_xlfn.IFS(AND(Q12="", OR(P12="Site Purchased Prior to Capital Approval", P12="Site Purchased")), "", AND(OR(P12="Site Purchased Prior to Capital Approval", P12="Site Purchased"), Q12>TODAY()), "Site purchase date is in the future, but site ownership status indicates site is already purchaseed", TRUE, "") | FH12: =IF(AND(AND(P12<>"Site Purchased Prior to Capital Approval", P12<>"Site Purchased"), Q12<=TODAY()), "Site purchase date is in the past, but site ownership status indicates site has not yet been purchaseed", "") | FI12: =_xlfn.IFS(FJ12<>"", FJ12, FK12<>"", FK12, TRUE,FL12 ) | FJ12: =IF(AND(P12<>"Not Applicable",Q12=""),"Site Purchased Date cannot be blank","") | FK12: =FE12 | FL12: =_xlfn.IFS(Q12="", "", U12="", "", Q12>U12, "Site Purchase Date must preceed Site Plan Submission.", TRUE, "")
A13: 40-109-01 | B13: St. Raymond Catholic Elementary School | C13: The project was originally scheduled to open in September 2025 but its been delayed to September 2026. The main issue is with the Site Plan Approval (SPA), which remains unapproved as the municipality continues to add requirements (e.g., sidewalk widening, crosswalks, road work, encroachments). Although school construction is complete, these outstanding SPA conditions prevent occupancy and site readiness. The board cannot open the school while site work continues, particularly given its specialized use for the hearing and deaf community. Also recent inspections flagged HVAC issues, raising further concerns. The city has come back asking for phasing of the municipal work, doesnt want all work at once. This is a huge change order and the contractor has stopped all work and will only continue once additional funding is provided to them. At this point, board has contingency to cover some costs, however this change order and municipal expectation (phasing in), will likely result in an additional funding request. The phasing in adds time to the project, but also to mobilize and re-mobilize trades, equipment etc, will be expensive. School board and municipality have had meetings re. phasing. Board checked with legal dept, and legal indicated the municipality is within their right to request these items. Some of the municipal work includes: three laneways around the site need to be wideneed and convey "clean land" (the land under sidewalk is given back to muncipality. Before conveying, school board needs to make sure the land is not contaminated. Before this work can happen, the school baord needs to have all utilities companies to sign that they are aware this is occuring. In this situation, there are 28 utilities companies. Note: The site is complex, with slope, contaminated soil, and a heritage chimney occupied by chimney sweep birds. | D13: New Construction | E13: Consolidation | F13: In Progress | G13: =_xlfn.IFS($C$3>AK13, "Complete", $C$3>AG13, "Open", $C$3>AC13, "Under Construction", TRUE, "Planning") -> Under Construction | I13: Not Applicable | J13: Not Applicable | K13: Not Applicable | M13: Not Applicable | N13: Not Applicable | O13: Not Applicable | P13: Not Applicable | R13: >80% Complete | S13: 42787 | V13: 45868 | AB13: 44636 | AC13: 45036 | AE13: 46234 | AG13: 46273 | AI13: 46631 | AK13: 46997 | AL13: =SUM(AM13:AP13) -> 32092513 | AM13: 30519486 | AO13: 1573027 | AQ13: Based on Tender Results | BD13: The project was originally scheduled to open in September 2025 but its been delayed to September 2026. The main issue is with the Site Plan Approval (SPA), which remains unapproved as the municipality continues to add requirements (e.g., sidewalk widening, crosswalks, road work, encroachments). Although school construction is complete, these outstanding SPA conditions prevent occupancy and site readiness. The board cannot open the school while site work continues, particularly given its specialized use for the hearing and deaf community. Also recent inspections also flagged HVAC issues, raising further concerns. Very little movement over the last month with this project. Issues b/w architect and general contractor. Note: The site is complex, with slope, contaminated soil, and a heritage chimney occupied by chimney sweep birds. | BE13: The project was originally scheduled to open in September 2025 but has been delayed to January 5, 2026, and then moved to spring 2026. The main issue is with the Site Plan Approval (SPA), which remains unapproved as the municipality continues to add requirements (e.g., sidewalk widening, crosswalks, road work, encroachments). Although school construction is complete, these outstanding SPA conditions prevent occupancy and site readiness. The board cannot open the school while site work continues, particularly given its specialized use for the hearing and deaf community. Also recent inspections also flagged HVAC issues, raising further concerns. At this point, the board has little confidence the school will be ready for January, and have moved opening to spring 2026. Walk throughs have happened. Note: The site is complex, with slope, contaminated soil, and a heritage chimney occupied by chimney sweep birds. | BF13: The project was originally scheduled to open in September 2025 but has been delayed to January 5, 2026. The main issue is with the Site Plan Approval (SPA), which remains unapproved as the municipality continues to add requirements (e.g., sidewalk widening, crosswalks, road work, encroachments). Although school construction is complete, these outstanding SPA conditions prevent occupancy and site readiness. The board cannot open the school while site work continues, particularly given its specialized use for the hearing and deaf community. Also recent inspections also flagged HVAC issues, raising further concerns. At this point, the board has little confidence the school will be ready for January, and no new opening date has been announced. Note: The site is complex, with slope, contaminated soil, and a heritage chimney occupied by chimney sweep birds. | BG13: Project delayed - January 5, 2026. Community is aware of the opening delay. Main reason for the challenge and delay is with the SPA. The school board is pretty much building a city block around with the sschool. SPA is still not approved and additional requirements are downloaded onto the school board. Ie. Sidewalk widening, sidewalks across the street, road work,encroachment. Municipality is still adding items to the SPA, and that is not allowing the project . The school construction is complete, but the municipality is adding items open SPA, and therefore it wont be ready for sept.. THe board cannot open the school with the site work still ongoing, due to the shcool communtiy (school for the hearing and deaf). | CD13: =IF(AND(Q13="", A13<>"", P13<>"Site Purchased Prior to Capital Approval"), 1, 0) -> 1 | CE13: 49 | CF13: =_xlfn.XLOOKUP($A13, 'Project Commitment'!$A:$A, 'Project Commitment'!M:M, "") -> 0 | CG13: =_xlfn.XLOOKUP($A13, 'Project Commitment'!$A:$A, 'Project Commitment'!N:N, "") -> 0 | CH13: =_xlfn.XLOOKUP($A13, 'Project Commitment'!$A:$A, 'Project Commitment'!O:O, "") -> 0 | CI13: =_xlfn.XLOOKUP($A13, 'Project Commitment'!$A:$A, 'Project Commitment'!P:P, "") -> 0 | CJ13: =_xlfn.XLOOKUP($A13, 'Project Commitment'!$A:$A, 'Project Commitment'!Q:Q, "") -> 0 | CK13: =_xlfn.XLOOKUP($A13, 'Project Commitment'!$A:$A, 'Project Commitment'!R:R, "") -> 0 | CL13: =_xlfn.XLOOKUP($A13, 'Project Commitment'!$A:$A, 'Project Commitment'!S:S, "") -> #VALUE! | CM13: =_xlfn.XLOOKUP($A13, 'Project Commitment'!$A:$A, 'Project Commitment'!T:T, "") -> 0 | CN13: =_xlfn.XLOOKUP($A13, 'Project Commitment'!$A:$A, 'Project Commitment'!U:U, "") -> 44636 | CO13: =_xlfn.XLOOKUP($A13, 'Project Commitment'!$A:$A, 'Project Commitment'!V:V, "") -> #VALUE! | CP13: =_xlfn.XLOOKUP($A13, 'Project Commitment'!$A:$A, 'Project Commitment'!W:W, "") -> 0 | CQ13: =_xlfn.XLOOKUP($A13, 'Project Commitment'!$A:$A, 'Project Commitment'!X:X, "") -> 0 | CR13: =_xlfn.XLOOKUP($A13, 'Project Commitment'!$A:$A, 'Project Commitment'!Y:Y, "") -> -396 | CS13: =_xlfn.XLOOKUP($A13, 'Project Commitment'!$A:$A, 'Project Commitment'!Z:Z, "") -> -371 | CT13: =_xlfn.XLOOKUP($A13, 'Project Commitment'!$A:$A, 'Project Commitment'!AA:AA, "") -> 0 | CU13: =_xlfn.XLOOKUP($A13, 'Project Commitment'!$A:$A, 'Project Commitment'!AB:AB, "") -> -730 | DA13: =IF(C13="", "Meeting Minutes cannot be blank", "") | DF13: =_xlfn.IFS(AND(J13="Not Applicable", H13<>""), "No date is needed if Column 10 is Not Applicable",J13= "Not Applicable", "", H13="",DF$7&" cannot be blank", $AC13="", "", H13>$AC13, DF$7&" must preceed construction start date.", TRUE, "") | DG13: =_xlfn.IFS(I13="", DG$7&" cannot be left blank.",H13="", "", AND( H13 < TODAY(), I13="Not Yet Known"), "After the submission date, the pre-tender package type must be selected.", TRUE, "") | DI13: =EW13 | DJ13: =_xlfn.IFS(AND(N13="Not Applicable", L13<>""), "No date is needed if Column 14 is Not Applicable",N13= "Not Applicable", "", L13="",DJ$7&" cannot be blank", $AC13="", "", L13>$AC13, DJ$7&" must preceed construction start date.", TRUE, "") | DK13: =_xlfn.IFS(M13="", DK$7&" cannot be left blank.",L13="", "", AND( L13 < TODAY(), M13="Not Yet Known"), "After the submission date, the pre-tender package type must be selected.", TRUE, "") | DM13: =FA13 | DN13: =FE13 | DO13: =FI13 | DP13: =IF(R13="", DP$7&" cannot be blank", "") | DQ13: =_xlfn.IFS(S13="",DQ$7&" cannot be blank",AND(J13<>"Not yet submitted/reviewed",S13>TODAY()),DQ$7&" cannot be in the future if project is ready for a pre-tender package.",TRUE,"") | DR13: =_xlfn.IFS(CE13=0, "", T13="",DR$7&" cannot be blank if project includes child care.", AND(J13="Not Applicable",T13>TODAY()), "Projects under construction must have a "&DR$7, J13="Not Applicable", "", T13<I13, T9&" must preceed pre-tender package submission date",TRUE, "") -> Child Care Floorplan Approval Date cannot be blank if project includes child care. | DS13: =_xlfn.IFS(U13="",DS$7&" cannot be blank", $AC13="", "", U13>$AC13, DS$7&" must preceed construction start date.", TRUE, "") -> Initial Site Plan Submission Date cannot be blank | DT13: =_xlfn.IFS(W13<>"", "", V13="",DT$7&" cannot be blank", $AC13="", "", V13>$AC13, DT$7&" must preceed construction start date.", TRUE, "") -> Site Plan Approval Date must preceed construction start date. | DV13: =_xlfn.IFS(Y13<>"", "", X13="",DV$7&" cannot be blank", $AC13="", "", X13>$AC13, DV$7&" must preceed construction start date.", TRUE, "") -> Build Permit Obtained Date cannot be blank | DX13: =_xlfn.IFS(Z13="",DX$7&" cannot be blank", $AC13="", "", Z13>$AC13, DX$7&" must preceed construction start date.", TRUE, "") -> Tender Issued Date cannot be blank | DY13: =_xlfn.IFS(AA13="",DY$7&" cannot be blank", $AC13="", "", AA13>$AC13, DY$7&" must preceed construction start date.", TRUE, "") -> Tender Closed Date cannot be blank | DZ13: =_xlfn.IFS(AB13="",DZ$7&" cannot be blank", $AC13="", "", AB13>$AC13, DZ$7&" must preceed construction start date.", TRUE, "") | EA13: =_xlfn.IFS(AD13<>"", "", AC13="",EA$7&" cannot be blank", $AG13="", "", AC13>EDATE($AG13,-12), EA$7&" must preceed school opening date by more than 12 months.", TRUE, "") | EC13: =_xlfn.IFS(AF13<>"", "", AE13="",EC$7&" cannot be blank", $AG13="", "", AE13>EDATE($AG13,-1), EC$7&" must preceed school opening date by more than one month.", TRUE, "") | EE13: =_xlfn.IFS(AK13="", "", AG13="",EE$7&" cannot be blank",AH13<>"", "", $AG13="", "", AG13>=EDATE($AK13,-11), EE$7&" must preceed financial close date by at least 12 months.", TRUE, "") | EG13: =_xlfn.IFS(CE13=0, "", AI13="",EG$7&" cannot be blank",$AK13="", "",AJ13<>"", "", AI13>=EDATE($AK13,0), EG$7&" must preceed financial close date.", TRUE, "") | EI13: =_xlfn.IFS( AK13="",EI$7&" cannot be blank", TRUE, "") | EO13: =_xlfn.IFS(AQ13="", "Basis of Cost Estimate cannot be blank", AND(AC13<TODAY(), AQ13<>"Based on Tender Results"), "Contract awarded date suggests estimate should be based on tender results", AND(H13<TODAY(), AQ13<>"Based on Class A or B Cost Report"), "If project has already come in for a pre-tender budget, they must have a class A or B cost estimate.", TRUE, "") | EP13: =_xlfn.IFS(OR(AM13=0, AM13=""), "", AR13="", EP$7&" cannot be blank.", TRUE, "") -> Estimated Cost - Construction Project cannot be blank. | EQ13: =_xlfn.IFS(OR(AN13=0, AN13=""), "", AS13="", EQ$7&" cannot be blank.", TRUE, "") | ER13: =_xlfn.IFS(OR(AO13=0, AO13=""), "", AT13="", ER$7&" cannot be blank.", TRUE, "") -> Estimated Cost - Demolition cannot be blank. | ES13: =_xlfn.IFS(OR(AP13=0, AP13=""), "", AU13="", ES$7&" cannot be blank.", TRUE, "") | EW13: =_xlfn.IFS(EX13<>"", EX13, EY13<>"", EY13, EZ13<>"", EZ13, TRUE, "") | EX13: =IF(J13="MISSING", "This package is missing!", "") | EY13: =IF(K13="", "Confirm you reviewed the pretender checkin documents", "") | EZ13: =IF(AND(K13="Not yet submitted/reviewed", J13<>"Not yet submitted/reviewed"), "Pretender package submitted; col 9 cann't indicate otherwise.", "") | FA13: =_xlfn.IFS(FB13<>"", FB13, FC13<>"", FC13, FD13<>"", FD13, TRUE, "") | FB13: =IF(N13="MISSING", "The post tender package is missing!", "") | FC13: =IF(O13="", "Confirm you reviewed the post tender check-in documents", "") | FD13: =IF(AND(O13="Not yet submitted/reviewed", N13<>"Not yet submitted/reviewed"), "Post-tender package submitted; col 9 cann't indicate otherwise.", "") | FE13: =_xlfn.IFS(FF13<>"", FF13, FG13<>"", FG13, TRUE, FH13) | FF13: =IF(P13<>"", "", "Site Ownership Status cannot be blank") | FG13: =_xlfn.IFS(AND(Q13="", OR(P13="Site Purchased Prior to Capital Approval", P13="Site Purchased")), "", AND(OR(P13="Site Purchased Prior to Capital Approval", P13="Site Purchased"), Q13>TODAY()), "Site purchase date is in the future, but site ownership status indicates site is already purchaseed", TRUE, "") | FH13: =IF(AND(AND(P13<>"Site Purchased Prior to Capital Approval", P13<>"Site Purchased"), Q13<=TODAY()), "Site purchase date is in the past, but site ownership status indicates site has not yet been purchaseed", "") | FI13: =_xlfn.IFS(FJ13<>"", FJ13, FK13<>"", FK13, TRUE,FL13 ) | FJ13: =IF(AND(P13<>"Not Applicable",Q13=""),"Site Purchased Date cannot be blank","") | FK13: =FE13 | FL13: =_xlfn.IFS(Q13="", "", U13="", "", Q13>U13, "Site Purchase Date must preceed Site Plan Submission.", TRUE, "")
A14: 40-127 | B14: St. Antoine Daniel Catholic Elementary School | C14: Construction is wrapping up and the school is expected to open March 23, 2026 (after March Break). Little blip - Some PA system components where delivered on site after ceiling work complete, so workers need to go back and install, testing and verify it works. This is happening this week. | D14: New Construction | E14: Accommodation Pressure | F14: In Progress | G14: =_xlfn.IFS($C$3>AK14, "Complete", $C$3>AG14, "Open", $C$3>AC14, "Under Construction", TRUE, "Planning") -> Under Construction | I14: Not Applicable | J14: Not Applicable | K14: Not Applicable | M14: Not Applicable | N14: Not Applicable | O14: Not Applicable | P14: Not Applicable | R14: >80% Complete | S14: 42796 | T14: 44495 | U14: 44882 | V14: 45100 | Z14: 45199 | AA14: 45230 | AB14: 45280 | AC14: 45320 | AE14: 46076 | AG14: 46104 | AI14: 46273 | AK14: 46639 | AL14: =SUM(AM14:AP14) -> 31531487 | AM14: 30861032 | AO14: 670455 | AQ14: Based on Tender Results | BD14: The project has been delayed and will open March 23, 2026, after March Break. The delay stems from trade challenges, including the drywall contractor going out of business, which pushed back the building’s weather-tight milestone and overall schedule. Current issues - challenges with Enbridge. SB cant move ahead with connections, until Enbridge has connected the gas to the building. Board has been escalating up the line for Enbridge, but it hasnt worked. Community pressure - SB decision to open the school for March Break. students are bussed 1hr away (jane and wilson area). It would be nice to have the grade 8 students back in the new facility for the last few months. Board is aware / concerned about the loss of enrolment....all these reasons have made the SB commit to the March Break date. | BE14: The project has been delayed to spring 2026. The delay stems from trade challenges, including the drywall contractor going out of business, which pushed back the building’s weather-tight milestone and overall schedule. | BF14: The project has been delayed to January 5, 2026. The delay stems from trade challenges, including the drywall contractor going out of business, which pushed back the building’s weather-tight milestone and overall schedule. While the contractor is targeting completion by December 15 (revised from November 1), the school board is not confident the timeline allows for a January opening. Based on current site activity, completion before the holidays appears unlikely, and no final decision has been made. | BG14: Project delayed - January 5, 2026. Community is aware of the delay. Delay is a result of trade challenges (Drywall trade went out of business) and therefore that delayed the schedule. Delayed the weather tight of the building, impacting the schedule. | CD14: =IF(AND(Q14="", A14<>"", P14<>"Site Purchased Prior to Capital Approval"), 1, 0) -> 1 | CE14: 88 | CF14: =_xlfn.XLOOKUP($A14, 'Project Commitment'!$A:$A, 'Project Commitment'!M:M, "") -> 0 | CG14: =_xlfn.XLOOKUP($A14, 'Project Commitment'!$A:$A, 'Project Commitment'!N:N, "") -> 0 | CH14: =_xlfn.XLOOKUP($A14, 'Project Commitment'!$A:$A, 'Project Commitment'!O:O, "") -> 0 | CI14: =_xlfn.XLOOKUP($A14, 'Project Commitment'!$A:$A, 'Project Commitment'!P:P, "") -> 0 | CJ14: =_xlfn.XLOOKUP($A14, 'Project Commitment'!$A:$A, 'Project Commitment'!Q:Q, "") -> 0 | CK14: =_xlfn.XLOOKUP($A14, 'Project Commitment'!$A:$A, 'Project Commitment'!R:R, "") -> 0 | CL14: =_xlfn.XLOOKUP($A14, 'Project Commitment'!$A:$A, 'Project Commitment'!S:S, "") -> #VALUE! | CM14: =_xlfn.XLOOKUP($A14, 'Project Commitment'!$A:$A, 'Project Commitment'!T:T, "") -> 0 | CN14: =_xlfn.XLOOKUP($A14, 'Project Commitment'!$A:$A, 'Project Commitment'!U:U, "") -> -35 | CO14: =_xlfn.XLOOKUP($A14, 'Project Commitment'!$A:$A, 'Project Commitment'!V:V, "") -> #VALUE! | CP14: =_xlfn.XLOOKUP($A14, 'Project Commitment'!$A:$A, 'Project Commitment'!W:W, "") -> 0 | CQ14: =_xlfn.XLOOKUP($A14, 'Project Commitment'!$A:$A, 'Project Commitment'!X:X, "") -> 0 | CR14: =_xlfn.XLOOKUP($A14, 'Project Commitment'!$A:$A, 'Project Commitment'!Y:Y, "") -> -241 | CS14: =_xlfn.XLOOKUP($A14, 'Project Commitment'!$A:$A, 'Project Commitment'!Z:Z, "") -> -202 | CT14: =_xlfn.XLOOKUP($A14, 'Project Commitment'!$A:$A, 'Project Commitment'!AA:AA, "") -> 0 | CU14: =_xlfn.XLOOKUP($A14, 'Project Commitment'!$A:$A, 'Project Commitment'!AB:AB, "") -> -372 | DA14: =IF(C14="", "Meeting Minutes cannot be blank", "") | DF14: =_xlfn.IFS(AND(J14="Not Applicable", H14<>""), "No date is needed if Column 10 is Not Applicable",J14= "Not Applicable", "", H14="",DF$7&" cannot be blank", $AC14="", "", H14>$AC14, DF$7&" must preceed construction start date.", TRUE, "") | DG14: =_xlfn.IFS(I14="", DG$7&" cannot be left blank.",H14="", "", AND( H14 < TODAY(), I14="Not Yet Known"), "After the submission date, the pre-tender package type must be selected.", TRUE, "") | DI14: =EW14 | DJ14: =_xlfn.IFS(AND(N14="Not Applicable", L14<>""), "No date is needed if Column 14 is Not Applicable",N14= "Not Applicable", "", L14="",DJ$7&" cannot be blank", $AC14="", "", L14>$AC14, DJ$7&" must preceed construction start date.", TRUE, "") | DK14: =_xlfn.IFS(M14="", DK$7&" cannot be left blank.",L14="", "", AND( L14 < TODAY(), M14="Not Yet Known"), "After the submission date, the pre-tender package type must be selected.", TRUE, "") | DM14: =FA14 | DN14: =FE14 | DO14: =FI14 | DP14: =IF(R14="", DP$7&" cannot be blank", "") | DQ14: =_xlfn.IFS(S14="",DQ$7&" cannot be blank",AND(J14<>"Not yet submitted/reviewed",S14>TODAY()),DQ$7&" cannot be in the future if project is ready for a pre-tender package.",TRUE,"") | DR14: =_xlfn.IFS(CE14=0, "", T14="",DR$7&" cannot be blank if project includes child care.", AND(J14="Not Applicable",T14>TODAY()), "Projects under construction must have a "&DR$7, J14="Not Applicable", "", T14<I14, T10&" must preceed pre-tender package submission date",TRUE, "") | DS14: =_xlfn.IFS(U14="",DS$7&" cannot be blank", $AC14="", "", U14>$AC14, DS$7&" must preceed construction start date.", TRUE, "") | DT14: =_xlfn.IFS(W14<>"", "", V14="",DT$7&" cannot be blank", $AC14="", "", V14>$AC14, DT$7&" must preceed construction start date.", TRUE, "") | DV14: =_xlfn.IFS(Y14<>"", "", X14="",DV$7&" cannot be blank", $AC14="", "", X14>$AC14, DV$7&" must preceed construction start date.", TRUE, "") -> Build Permit Obtained Date cannot be blank | DX14: =_xlfn.IFS(Z14="",DX$7&" cannot be blank", $AC14="", "", Z14>$AC14, DX$7&" must preceed construction start date.", TRUE, "") | DY14: =_xlfn.IFS(AA14="",DY$7&" cannot be blank", $AC14="", "", AA14>$AC14, DY$7&" must preceed construction start date.", TRUE, "") | DZ14: =_xlfn.IFS(AB14="",DZ$7&" cannot be blank", $AC14="", "", AB14>$AC14, DZ$7&" must preceed construction start date.", TRUE, "") | EA14: =_xlfn.IFS(AD14<>"", "", AC14="",EA$7&" cannot be blank", $AG14="", "", AC14>EDATE($AG14,-12), EA$7&" must preceed school opening date by more than 12 months.", TRUE, "") | EC14: =_xlfn.IFS(AF14<>"", "", AE14="",EC$7&" cannot be blank", $AG14="", "", AE14>EDATE($AG14,-1), EC$7&" must preceed school opening date by more than one month.", TRUE, "") | EE14: =_xlfn.IFS(AK14="", "", AG14="",EE$7&" cannot be blank",AH14<>"", "", $AG14="", "", AG14>=EDATE($AK14,-11), EE$7&" must preceed financial close date by at least 12 months.", TRUE, "") | EG14: =_xlfn.IFS(CE14=0, "", AI14="",EG$7&" cannot be blank",$AK14="", "",AJ14<>"", "", AI14>=EDATE($AK14,0), EG$7&" must preceed financial close date.", TRUE, "") | EI14: =_xlfn.IFS( AK14="",EI$7&" cannot be blank", TRUE, "") | EO14: =_xlfn.IFS(AQ14="", "Basis of Cost Estimate cannot be blank", AND(AC14<TODAY(), AQ14<>"Based on Tender Results"), "Contract awarded date suggests estimate should be based on tender results", AND(H14<TODAY(), AQ14<>"Based on Class A or B Cost Report"), "If project has already come in for a pre-tender budget, they must have a class A or B cost estimate.", TRUE, "") | EP14: =_xlfn.IFS(OR(AM14=0, AM14=""), "", AR14="", EP$7&" cannot be blank.", TRUE, "") -> Estimated Cost - Construction Project cannot be blank. | EQ14: =_xlfn.IFS(OR(AN14=0, AN14=""), "", AS14="", EQ$7&" cannot be blank.", TRUE, "") | ER14: =_xlfn.IFS(OR(AO14=0, AO14=""), "", AT14="", ER$7&" cannot be blank.", TRUE, "") -> Estimated Cost - Demolition cannot be blank. | ES14: =_xlfn.IFS(OR(AP14=0, AP14=""), "", AU14="", ES$7&" cannot be blank.", TRUE, "") | EW14: =_xlfn.IFS(EX14<>"", EX14, EY14<>"", EY14, EZ14<>"", EZ14, TRUE, "") | EX14: =IF(J14="MISSING", "This package is missing!", "") | EY14: =IF(K14="", "Confirm you reviewed the pretender checkin documents", "") | EZ14: =IF(AND(K14="Not yet submitted/reviewed", J14<>"Not yet submitted/reviewed"), "Pretender package submitted; col 9 cann't indicate otherwise.", "") | FA14: =_xlfn.IFS(FB14<>"", FB14, FC14<>"", FC14, FD14<>"", FD14, TRUE, "") | FB14: =IF(N14="MISSING", "The post tender package is missing!", "") | FC14: =IF(O14="", "Confirm you reviewed the post tender check-in documents", "") | FD14: =IF(AND(O14="Not yet submitted/reviewed", N14<>"Not yet submitted/reviewed"), "Post-tender package submitted; col 9 cann't indicate otherwise.", "") | FE14: =_xlfn.IFS(FF14<>"", FF14, FG14<>"", FG14, TRUE, FH14) | FF14: =IF(P14<>"", "", "Site Ownership Status cannot be blank") | FG14: =_xlfn.IFS(AND(Q14="", OR(P14="Site Purchased Prior to Capital Approval", P14="Site Purchased")), "", AND(OR(P14="Site Purchased Prior to Capital Approval", P14="Site Purchased"), Q14>TODAY()), "Site purchase date is in the future, but site ownership status indicates site is already purchaseed", TRUE, "") | FH14: =IF(AND(AND(P14<>"Site Purchased Prior to Capital Approval", P14<>"Site Purchased"), Q14<=TODAY()), "Site purchase date is in the past, but site ownership status indicates site has not yet been purchaseed", "") | FI14: =_xlfn.IFS(FJ14<>"", FJ14, FK14<>"", FK14, TRUE,FL14 ) | FJ14: =IF(AND(P14<>"Not Applicable",Q14=""),"Site Purchased Date cannot be blank","") | FK14: =FE14 | FL14: =_xlfn.IFS(Q14="", "", U14="", "", Q14>U14, "Site Purchase Date must preceed Site Plan Submission.", TRUE, "")
A15: 40-128 | B15: Regina Mundi Catholic Elementary School | C15: This school will be 100% complete, including play yard and parking lots. The driving way is the only component still to be complete, as it is shared with Dante Alighieri (currently under construction). | D15: Retrofit | E15: Condition | F15: In Progress | G15: =_xlfn.IFS($C$3>AK15, "Complete", $C$3>AG15, "Open", $C$3>AC15, "Under Construction", TRUE, "Planning") -> Open | I15: Not Applicable | J15: Not Applicable | K15: Not Applicable | M15: Not Applicable | N15: Not Applicable | O15: Not Applicable | P15: Not Applicable | R15: >80% Complete | AC15: 44692 | AE15: 45264 | AG15: 45299 | AI15: 45299 | AK15: 46323 | AL15: =SUM(AM15:AP15) -> 11444978 | AM15: 11444978 | AQ15: Based on Tender Results | BD15: Play yard is complete. Parking lot still needs to be complete. These components are tied with the Dante Alighieri project, which is under construction. This school will be 100% complete, until Dante is complete (due to shared driveway…interconnected due to campus) | BE15: Play yard is complete. Parking lot still needs to be complete. This won't be done until Dante Alighieri is complete, as it is in use now for construction. | CD15: =IF(AND(Q15="", A15<>"", P15<>"Site Purchased Prior to Capital Approval"), 1, 0) -> 1 | CE15: 88 | CF15: =_xlfn.XLOOKUP($A15, 'Project Commitment'!$A:$A, 'Project Commitment'!M:M, "") | CG15: =_xlfn.XLOOKUP($A15, 'Project Commitment'!$A:$A, 'Project Commitment'!N:N, "") | CH15: =_xlfn.XLOOKUP($A15, 'Project Commitment'!$A:$A, 'Project Commitment'!O:O, "") | CI15: =_xlfn.XLOOKUP($A15, 'Project Commitment'!$A:$A, 'Project Commitment'!P:P, "") | CJ15: =_xlfn.XLOOKUP($A15, 'Project Commitment'!$A:$A, 'Project Commitment'!Q:Q, "") | CK15: =_xlfn.XLOOKUP($A15, 'Project Commitment'!$A:$A, 'Project Commitment'!R:R, "") | CL15: =_xlfn.XLOOKUP($A15, 'Project Commitment'!$A:$A, 'Project Commitment'!S:S, "") | CM15: =_xlfn.XLOOKUP($A15, 'Project Commitment'!$A:$A, 'Project Commitment'!T:T, "") | CN15: =_xlfn.XLOOKUP($A15, 'Project Commitment'!$A:$A, 'Project Commitment'!U:U, "") | CO15: =_xlfn.XLOOKUP($A15, 'Project Commitment'!$A:$A, 'Project Commitment'!V:V, "") | CP15: =_xlfn.XLOOKUP($A15, 'Project Commitment'!$A:$A, 'Project Commitment'!W:W, "") | CQ15: =_xlfn.XLOOKUP($A15, 'Project Commitment'!$A:$A, 'Project Commitment'!X:X, "") | CR15: =_xlfn.XLOOKUP($A15, 'Project Commitment'!$A:$A, 'Project Commitment'!Y:Y, "") | CS15: =_xlfn.XLOOKUP($A15, 'Project Commitment'!$A:$A, 'Project Commitment'!Z:Z, "") | CT15: =_xlfn.XLOOKUP($A15, 'Project Commitment'!$A:$A, 'Project Commitment'!AA:AA, "") | CU15: =_xlfn.XLOOKUP($A15, 'Project Commitment'!$A:$A, 'Project Commitment'!AB:AB, "") | DA15: =IF(C15="", "Meeting Minutes cannot be blank", "") | DF15: =_xlfn.IFS(AND(J15="Not Applicable", H15<>""), "No date is needed if Column 10 is Not Applicable",J15= "Not Applicable", "", H15="",DF$7&" cannot be blank", $AC15="", "", H15>$AC15, DF$7&" must preceed construction start date.", TRUE, "") | DG15: =_xlfn.IFS(I15="", DG$7&" cannot be left blank.",H15="", "", AND( H15 < TODAY(), I15="Not Yet Known"), "After the submission date, the pre-tender package type must be selected.", TRUE, "") | DI15: =EW15 | DJ15: =_xlfn.IFS(AND(N15="Not Applicable", L15<>""), "No date is needed if Column 14 is Not Applicable",N15= "Not Applicable", "", L15="",DJ$7&" cannot be blank", $AC15="", "", L15>$AC15, DJ$7&" must preceed construction start date.", TRUE, "") | DK15: =_xlfn.IFS(M15="", DK$7&" cannot be left blank.",L15="", "", AND( L15 < TODAY(), M15="Not Yet Known"), "After the submission date, the pre-tender package type must be selected.", TRUE, "") | DM15: =FA15 | DN15: =FE15 | DO15: =FI15 | DP15: =IF(R15="", DP$7&" cannot be blank", "") | DQ15: =_xlfn.IFS(S15="",DQ$7&" cannot be blank",AND(J15<>"Not yet submitted/reviewed",S15>TODAY()),DQ$7&" cannot be in the future if project is ready for a pre-tender package.",TRUE,"") -> Space Template Approval Date cannot be blank | DR15: =_xlfn.IFS(CE15=0, "", T15="",DR$7&" cannot be blank if project includes child care.", AND(J15="Not Applicable",T15>TODAY()), "Projects under construction must have a "&DR$7, J15="Not Applicable", "", T15<I15, T11&" must preceed pre-tender package submission date",TRUE, "") -> Child Care Floorplan Approval Date cannot be blank if project includes child care. | DS15: =_xlfn.IFS(U15="",DS$7&" cannot be blank", $AC15="", "", U15>$AC15, DS$7&" must preceed construction start date.", TRUE, "") -> Initial Site Plan Submission Date cannot be blank | DT15: =_xlfn.IFS(W15<>"", "", V15="",DT$7&" cannot be blank", $AC15="", "", V15>$AC15, DT$7&" must preceed construction start date.", TRUE, "") -> Site Plan Approval Date cannot be blank | DV15: =_xlfn.IFS(Y15<>"", "", X15="",DV$7&" cannot be blank", $AC15="", "", X15>$AC15, DV$7&" must preceed construction start date.", TRUE, "") -> Build Permit Obtained Date cannot be blank | DX15: =_xlfn.IFS(Z15="",DX$7&" cannot be blank", $AC15="", "", Z15>$AC15, DX$7&" must preceed construction start date.", TRUE, "") -> Tender Issued Date cannot be blank | DY15: =_xlfn.IFS(AA15="",DY$7&" cannot be blank", $AC15="", "", AA15>$AC15, DY$7&" must preceed construction start date.", TRUE, "") -> Tender Closed Date cannot be blank | DZ15: =_xlfn.IFS(AB15="",DZ$7&" cannot be blank", $AC15="", "", AB15>$AC15, DZ$7&" must preceed construction start date.", TRUE, "") -> Contract Awarded Date cannot be blank | EA15: =_xlfn.IFS(AD15<>"", "", AC15="",EA$7&" cannot be blank", $AG15="", "", AC15>EDATE($AG15,-12), EA$7&" must preceed school opening date by more than 12 months.", TRUE, "") | EC15: =_xlfn.IFS(AF15<>"", "", AE15="",EC$7&" cannot be blank", $AG15="", "", AE15>EDATE($AG15,-1), EC$7&" must preceed school opening date by more than one month.", TRUE, "") | EE15: =_xlfn.IFS(AK15="", "", AG15="",EE$7&" cannot be blank",AH15<>"", "", $AG15="", "", AG15>=EDATE($AK15,-11), EE$7&" must preceed financial close date by at least 12 months.", TRUE, "") | EG15: =_xlfn.IFS(CE15=0, "", AI15="",EG$7&" cannot be blank",$AK15="", "",AJ15<>"", "", AI15>=EDATE($AK15,0), EG$7&" must preceed financial close date.", TRUE, "") | EI15: =_xlfn.IFS( AK15="",EI$7&" cannot be blank", TRUE, "") | EO15: =_xlfn.IFS(AQ15="", "Basis of Cost Estimate cannot be blank", AND(AC15<TODAY(), AQ15<>"Based on Tender Results"), "Contract awarded date suggests estimate should be based on tender results", AND(H15<TODAY(), AQ15<>"Based on Class A or B Cost Report"), "If project has already come in for a pre-tender budget, they must have a class A or B cost estimate.", TRUE, "") | EP15: =_xlfn.IFS(OR(AM15=0, AM15=""), "", AR15="", EP$7&" cannot be blank.", TRUE, "") -> Estimated Cost - Construction Project cannot be blank. | EQ15: =_xlfn.IFS(OR(AN15=0, AN15=""), "", AS15="", EQ$7&" cannot be blank.", TRUE, "") | ER15: =_xlfn.IFS(OR(AO15=0, AO15=""), "", AT15="", ER$7&" cannot be blank.", TRUE, "") | ES15: =_xlfn.IFS(OR(AP15=0, AP15=""), "", AU15="", ES$7&" cannot be blank.", TRUE, "") | EW15: =_xlfn.IFS(EX15<>"", EX15, EY15<>"", EY15, EZ15<>"", EZ15, TRUE, "") | EX15: =IF(J15="MISSING", "This package is missing!", "") | EY15: =IF(K15="", "Confirm you reviewed the pretender checkin documents", "") | EZ15: =IF(AND(K15="Not yet submitted/reviewed", J15<>"Not yet submitted/reviewed"), "Pretender package submitted; col 9 cann't indicate otherwise.", "") | FA15: =_xlfn.IFS(FB15<>"", FB15, FC15<>"", FC15, FD15<>"", FD15, TRUE, "") | FB15: =IF(N15="MISSING", "The post tender package is missing!", "") | FC15: =IF(O15="", "Confirm you reviewed the post tender check-in documents", "") | FD15: =IF(AND(O15="Not yet submitted/reviewed", N15<>"Not yet submitted/reviewed"), "Post-tender package submitted; col 9 cann't indicate otherwise.", "") | FE15: =_xlfn.IFS(FF15<>"", FF15, FG15<>"", FG15, TRUE, FH15) | FF15: =IF(P15<>"", "", "Site Ownership Status cannot be blank") | FG15: =_xlfn.IFS(AND(Q15="", OR(P15="Site Purchased Prior to Capital Approval", P15="Site Purchased")), "", AND(OR(P15="Site Purchased Prior to Capital Approval", P15="Site Purchased"), Q15>TODAY()), "Site purchase date is in the future, but site ownership status indicates site is already purchaseed", TRUE, "") | FH15: =IF(AND(AND(P15<>"Site Purchased Prior to Capital Approval", P15<>"Site Purchased"), Q15<=TODAY()), "Site purchase date is in the past, but site ownership status indicates site has not yet been purchaseed", "") | FI15: =_xlfn.IFS(FJ15<>"", FJ15, FK15<>"", FK15, TRUE,FL15 ) | FJ15: =IF(AND(P15<>"Not Applicable",Q15=""),"Site Purchased Date cannot be blank","") | FK15: =FE15 | FL15: =_xlfn.IFS(Q15="", "", U15="", "", Q15>U15, "Site Purchase Date must preceed Site Plan Submission.", TRUE, "")
A16: 40-151 | B16: St. Michael's Choir Catholic Elementary School | C16: The board is reviewing the feasibility study (finalized early 2026), as cost estimates came in higher than expected. The architect is now value-engineering the design. In Jan 2026 - Ministry staff met with school board to discuss the scope and status update. Information was shared regarding the Archdiocese's financial commitment to the project and supporting letters indicating they would support costs above ministry allocation. With staff turnover at the school board since this project was discussed with Diocese, and school board staff now will re-engage conversations and see what can be covered from their end. Ministry also asked for board to clearly show what space is strictly school board and what is shared with the Diocese, to understand the size/scope of each element. School board working on this request. | D16: New Construction | E16: Condition | F16: In Progress | G16: =_xlfn.IFS($C$3>AK16, "Complete", $C$3>AG16, "Open", $C$3>AC16, "Under Construction", TRUE, "Planning") -> Planning | H16: 46296 | I16: Not Yet Known | J16: Not yet submitted/reviewed | K16: Not yet submitted/reviewed | M16: Not Yet Known | N16: Not yet submitted/reviewed | O16: Not yet submitted/reviewed | P16: Not Applicable | R16: 30%-80% Complete | S16: 43836 | V16: 46204 | AC16: 46341 | AE16: 47301 | AG16: 47364 | AK16: 47425 | AL16: =SUM(AM16:AP16) -> 11155222 | AM16: 11155222 | AQ16: Based on estimate of $/sq ft | BD16: The board is reviewing the feasibility study, as cost estimates came in higher than expected. The architect is now value-engineering the design. The board has also met with the community to discuss space utilization, emphasizing maximizing use of existing spaces and keeping the overall size smaller to manage costs. The project scope includes constructing an addition on top of the current school. | BE16: The board is reviewing the feasibility study, as cost estimates came in higher than expected. The architect is now value-engineering the design. The board has also met with the community to discuss space utilization, emphasizing maximizing use of existing spaces and keeping the overall size smaller to manage costs. The project scope includes constructing an addition on top of the current school. | BF16: The board is reviewing the feasibility study, as cost estimates came in higher than expected. The architect is now value-engineering the design. The board has also met with the community to discuss space utilization, emphasizing maximizing use of existing spaces and keeping the overall size smaller to manage costs. The project scope includes constructing an addition on top of the current school. | BG16: Board reviewing the feasibility study. Cost Estimate came in higher than expected and now architect is value engineering the design. SB met with the community to discuss space utilization -- how much of the building is being used, keep all spaces utilized at all time, keep the size smaller to keep the funding lower. Existing school and the SB is building on top of the existing building | CD16: =IF(AND(Q16="", A16<>"", P16<>"Site Purchased Prior to Capital Approval"), 1, 0) -> 1 | CE16: 0 | CF16: =_xlfn.XLOOKUP($A16, 'Project Commitment'!$A:$A, 'Project Commitment'!M:M, "") -> 0 | CG16: =_xlfn.XLOOKUP($A16, 'Project Commitment'!$A:$A, 'Project Commitment'!N:N, "") -> 0 | CH16: =_xlfn.XLOOKUP($A16, 'Project Commitment'!$A:$A, 'Project Commitment'!O:O, "") -> 0 | CI16: =_xlfn.XLOOKUP($A16, 'Project Commitment'!$A:$A, 'Project Commitment'!P:P, "") -> 0 | CJ16: =_xlfn.XLOOKUP($A16, 'Project Commitment'!$A:$A, 'Project Commitment'!Q:Q, "") -> 0 | CK16: =_xlfn.XLOOKUP($A16, 'Project Commitment'!$A:$A, 'Project Commitment'!R:R, "") -> 0 | CL16: =_xlfn.XLOOKUP($A16, 'Project Commitment'!$A:$A, 'Project Commitment'!S:S, "") -> #VALUE! | CM16: =_xlfn.XLOOKUP($A16, 'Project Commitment'!$A:$A, 'Project Commitment'!T:T, "") -> 0 | CN16: =_xlfn.XLOOKUP($A16, 'Project Commitment'!$A:$A, 'Project Commitment'!U:U, "") -> #VALUE! | CO16: =_xlfn.XLOOKUP($A16, 'Project Commitment'!$A:$A, 'Project Commitment'!V:V, "") -> #VALUE! | CP16: =_xlfn.XLOOKUP($A16, 'Project Commitment'!$A:$A, 'Project Commitment'!W:W, "") -> 0 | CQ16: =_xlfn.XLOOKUP($A16, 'Project Commitment'!$A:$A, 'Project Commitment'!X:X, "") -> -14 | CR16: =_xlfn.XLOOKUP($A16, 'Project Commitment'!$A:$A, 'Project Commitment'!Y:Y, "") -> #VALUE! | CS16: =_xlfn.XLOOKUP($A16, 'Project Commitment'!$A:$A, 'Project Commitment'!Z:Z, "") -> -2 | CT16: =_xlfn.XLOOKUP($A16, 'Project Commitment'!$A:$A, 'Project Commitment'!AA:AA, "") -> 0 | CU16: =_xlfn.XLOOKUP($A16, 'Project Commitment'!$A:$A, 'Project Commitment'!AB:AB, "") -> #VALUE! | DA16: =IF(C16="", "Meeting Minutes cannot be blank", "") | DF16: =_xlfn.IFS(AND(J16="Not Applicable", H16<>""), "No date is needed if Column 10 is Not Applicable",J16= "Not Applicable", "", H16="",DF$7&" cannot be blank", $AC16="", "", H16>$AC16, DF$7&" must preceed construction start date.", TRUE, "") | DG16: =_xlfn.IFS(I16="", DG$7&" cannot be left blank.",H16="", "", AND( H16 < TODAY(), I16="Not Yet Known"), "After the submission date, the pre-tender package type must be selected.", TRUE, "") | DI16: =EW16 | DJ16: =_xlfn.IFS(AND(N16="Not Applicable", L16<>""), "No date is needed if Column 14 is Not Applicable",N16= "Not Applicable", "", L16="",DJ$7&" cannot be blank", $AC16="", "", L16>$AC16, DJ$7&" must preceed construction start date.", TRUE, "") -> Post-Tender Submission Date cannot be blank | DK16: =_xlfn.IFS(M16="", DK$7&" cannot be left blank.",L16="", "", AND( L16 < TODAY(), M16="Not Yet Known"), "After the submission date, the pre-tender package type must be selected.", TRUE, "") | DM16: =FA16 | DN16: =FE16 | DO16: =FI16 | DP16: =IF(R16="", DP$7&" cannot be blank", "") | DQ16: =_xlfn.IFS(S16="",DQ$7&" cannot be blank",AND(J16<>"Not yet submitted/reviewed",S16>TODAY()),DQ$7&" cannot be in the future if project is ready for a pre-tender package.",TRUE,"") | DR16: =_xlfn.IFS(CE16=0, "", T16="",DR$7&" cannot be blank if project includes child care.", AND(J16="Not Applicable",T16>TODAY()), "Projects under construction must have a "&DR$7, J16="Not Applicable", "", T16<I16, T12&" must preceed pre-tender package submission date",TRUE, "") | DS16: =_xlfn.IFS(U16="",DS$7&" cannot be blank", $AC16="", "", U16>$AC16, DS$7&" must preceed construction start date.", TRUE, "") -> Initial Site Plan Submission Date cannot be blank | DT16: =_xlfn.IFS(W16<>"", "", V16="",DT$7&" cannot be blank", $AC16="", "", V16>$AC16, DT$7&" must preceed construction start date.", TRUE, "") | DV16: =_xlfn.IFS(Y16<>"", "", X16="",DV$7&" cannot be blank", $AC16="", "", X16>$AC16, DV$7&" must preceed construction start date.", TRUE, "") -> Build Permit Obtained Date cannot be blank | DX16: =_xlfn.IFS(Z16="",DX$7&" cannot be blank", $AC16="", "", Z16>$AC16, DX$7&" must preceed construction start date.", TRUE, "") -> Tender Issued Date cannot be blank | DY16: =_xlfn.IFS(AA16="",DY$7&" cannot be blank", $AC16="", "", AA16>$AC16, DY$7&" must preceed construction start date.", TRUE, "") -> Tender Closed Date cannot be blank | DZ16: =_xlfn.IFS(AB16="",DZ$7&" cannot be blank", $AC16="", "", AB16>$AC16, DZ$7&" must preceed construction start date.", TRUE, "") -> Contract Awarded Date cannot be blank | EA16: =_xlfn.IFS(AD16<>"", "", AC16="",EA$7&" cannot be blank", $AG16="", "", AC16>EDATE($AG16,-12), EA$7&" must preceed school opening date by more than 12 months.", TRUE, "") | EC16: =_xlfn.IFS(AF16<>"", "", AE16="",EC$7&" cannot be blank", $AG16="", "", AE16>EDATE($AG16,-1), EC$7&" must preceed school opening date by more than one month.", TRUE, "") | EE16: =_xlfn.IFS(AK16="", "", AG16="",EE$7&" cannot be blank",AH16<>"", "", $AG16="", "", AG16>=EDATE($AK16,-11), EE$7&" must preceed financial close date by at least 12 months.", TRUE, "") -> School Opening Date must preceed financial close date by at least 12 months. | EG16: =_xlfn.IFS(CE16=0, "", AI16="",EG$7&" cannot be blank",$AK16="", "",AJ16<>"", "", AI16>=EDATE($AK16,0), EG$7&" must preceed financial close date.", TRUE, "") | EI16: =_xlfn.IFS( AK16="",EI$7&" cannot be blank", TRUE, "") | EO16: =_xlfn.IFS(AQ16="", "Basis of Cost Estimate cannot be blank", AND(AC16<TODAY(), AQ16<>"Based on Tender Results"), "Contract awarded date suggests estimate should be based on tender results", AND(H16<TODAY(), AQ16<>"Based on Class A or B Cost Report"), "If project has already come in for a pre-tender budget, they must have a class A or B cost estimate.", TRUE, "") | EP16: =_xlfn.IFS(OR(AM16=0, AM16=""), "", AR16="", EP$7&" cannot be blank.", TRUE, "") -> Estimated Cost - Construction Project cannot be blank. | EQ16: =_xlfn.IFS(OR(AN16=0, AN16=""), "", AS16="", EQ$7&" cannot be blank.", TRUE, "") | ER16: =_xlfn.IFS(OR(AO16=0, AO16=""), "", AT16="", ER$7&" cannot be blank.", TRUE, "") | ES16: =_xlfn.IFS(OR(AP16=0, AP16=""), "", AU16="", ES$7&" cannot be blank.", TRUE, "") | EW16: =_xlfn.IFS(EX16<>"", EX16, EY16<>"", EY16, EZ16<>"", EZ16, TRUE, "") | EX16: =IF(J16="MISSING", "This package is missing!", "") | EY16: =IF(K16="", "Confirm you reviewed the pretender checkin documents", "") | EZ16: =IF(AND(K16="Not yet submitted/reviewed", J16<>"Not yet submitted/reviewed"), "Pretender package submitted; col 9 cann't indicate otherwise.", "") | FA16: =_xlfn.IFS(FB16<>"", FB16, FC16<>"", FC16, FD16<>"", FD16, TRUE, "") | FB16: =IF(N16="MISSING", "The post tender package is missing!", "") | FC16: =IF(O16="", "Confirm you reviewed the post tender check-in documents", "") | FD16: =IF(AND(O16="Not yet submitted/reviewed", N16<>"Not yet submitted/reviewed"), "Post-tender package submitted; col 9 cann't indicate otherwise.", "") | FE16: =_xlfn.IFS(FF16<>"", FF16, FG16<>"", FG16, TRUE, FH16) | FF16: =IF(P16<>"", "", "Site Ownership Status cannot be blank") | FG16: =_xlfn.IFS(AND(Q16="", OR(P16="Site Purchased Prior to Capital Approval", P16="Site Purchased")), "", AND(OR(P16="Site Purchased Prior to Capital Approval", P16="Site Purchased"), Q16>TODAY()), "Site purchase date is in the future, but site ownership status indicates site is already purchaseed", TRUE, "") | FH16: =IF(AND(AND(P16<>"Site Purchased Prior to Capital Approval", P16<>"Site Purchased"), Q16<=TODAY()), "Site purchase date is in the past, but site ownership status indicates site has not yet been purchaseed", "") | FI16: =_xlfn.IFS(FJ16<>"", FJ16, FK16<>"", FK16, TRUE,FL16 ) | FJ16: =IF(AND(P16<>"Not Applicable",Q16=""),"Site Purchased Date cannot be blank","") | FK16: =FE16 | FL16: =_xlfn.IFS(Q16="", "", U16="", "", Q16>U16, "Site Purchase Date must preceed Site Plan Submission.", TRUE, "")
A17: 40-152 | B17: Holy Angels Catholic Elementary School | C17: Open - Final walk-through of the site and deficiencies are being finalized. One year warrantly coming to an end. Final deficiencies review and finances are currently reviewed by SB, and they are aware of the financial reconciliation process. | D17: New Construction | E17: Accommodation Pressure | F17: In Progress | G17: =_xlfn.IFS($C$3>AK17, "Complete", $C$3>AG17, "Open", $C$3>AC17, "Under Construction", TRUE, "Planning") -> Open | I17: Not Applicable | J17: Not Applicable | K17: Not Applicable | M17: Not Applicable | N17: Not Applicable | O17: Not Applicable | P17: Site Purchased | Q17: 42430 | R17: >80% Complete | AC17: 44690 | AE17: 45475 | AG17: 45538 | AI17: 45538 | AK17: 46266 | AL17: =SUM(AM17:AP17) -> 28705675 | AM17: 26472844 | AN17: 1240631 | AO17: 992200 | AQ17: Based on Tender Results | BD17: Open - Final walk-through of the site and deficiencies are being finalized. One year warrantly coming to an end soon. Final deficiencies review and finances are currently reviewed by SB. | BE17: Open - Final walk-through of the site and deficiencies are being finalized. | BF17: Open - Final walk-through of the site and deficiencies are being finalized. | BG17: Open | CD17: =IF(AND(Q17="", A17<>"", P17<>"Site Purchased Prior to Capital Approval"), 1, 0) -> 0 | CE17: 88 | CF17: =_xlfn.XLOOKUP($A17, 'Project Commitment'!$A:$A, 'Project Commitment'!M:M, "") | CG17: =_xlfn.XLOOKUP($A17, 'Project Commitment'!$A:$A, 'Project Commitment'!N:N, "") | CH17: =_xlfn.XLOOKUP($A17, 'Project Commitment'!$A:$A, 'Project Commitment'!O:O, "") | CI17: =_xlfn.XLOOKUP($A17, 'Project Commitment'!$A:$A, 'Project Commitment'!P:P, "") | CJ17: =_xlfn.XLOOKUP($A17, 'Project Commitment'!$A:$A, 'Project Commitment'!Q:Q, "") | CK17: =_xlfn.XLOOKUP($A17, 'Project Commitment'!$A:$A, 'Project Commitment'!R:R, "") | CL17: =_xlfn.XLOOKUP($A17, 'Project Commitment'!$A:$A, 'Project Commitment'!S:S, "") | CM17: =_xlfn.XLOOKUP($A17, 'Project Commitment'!$A:$A, 'Project Commitment'!T:T, "") | CN17: =_xlfn.XLOOKUP($A17, 'Project Commitment'!$A:$A, 'Project Commitment'!U:U, "") | CO17: =_xlfn.XLOOKUP($A17, 'Project Commitment'!$A:$A, 'Project Commitment'!V:V, "") | CP17: =_xlfn.XLOOKUP($A17, 'Project Commitment'!$A:$A, 'Project Commitment'!W:W, "") | CQ17: =_xlfn.XLOOKUP($A17, 'Project Commitment'!$A:$A, 'Project Commitment'!X:X, "") | CR17: =_xlfn.XLOOKUP($A17, 'Project Commitment'!$A:$A, 'Project Commitment'!Y:Y, "") | CS17: =_xlfn.XLOOKUP($A17, 'Project Commitment'!$A:$A, 'Project Commitment'!Z:Z, "") | CT17: =_xlfn.XLOOKUP($A17, 'Project Commitment'!$A:$A, 'Project Commitment'!AA:AA, "") | CU17: =_xlfn.XLOOKUP($A17, 'Project Commitment'!$A:$A, 'Project Commitment'!AB:AB, "") | DA17: =IF(C17="", "Meeting Minutes cannot be blank", "") | DF17: =_xlfn.IFS(AND(J17="Not Applicable", H17<>""), "No date is needed if Column 10 is Not Applicable",J17= "Not Applicable", "", H17="",DF$7&" cannot be blank", $AC17="", "", H17>$AC17, DF$7&" must preceed construction start date.", TRUE, "") | DG17: =_xlfn.IFS(I17="", DG$7&" cannot be left blank.",H17="", "", AND( H17 < TODAY(), I17="Not Yet Known"), "After the submission date, the pre-tender package type must be selected.", TRUE, "") | DI17: =EW17 | DJ17: =_xlfn.IFS(AND(N17="Not Applicable", L17<>""), "No date is needed if Column 14 is Not Applicable",N17= "Not Applicable", "", L17="",DJ$7&" cannot be blank", $AC17="", "", L17>$AC17, DJ$7&" must preceed construction start date.", TRUE, "") | DK17: =_xlfn.IFS(M17="", DK$7&" cannot be left blank.",L17="", "", AND( L17 < TODAY(), M17="Not Yet Known"), "After the submission date, the pre-tender package type must be selected.", TRUE, "") | DM17: =FA17 | DN17: =FE17 | DO17: =FI17 | DP17: =IF(R17="", DP$7&" cannot be blank", "") | DQ17: =_xlfn.IFS(S17="",DQ$7&" cannot be blank",AND(J17<>"Not yet submitted/reviewed",S17>TODAY()),DQ$7&" cannot be in the future if project is ready for a pre-tender package.",TRUE,"") -> Space Template Approval Date cannot be blank | DR17: =_xlfn.IFS(CE17=0, "", T17="",DR$7&" cannot be blank if project includes child care.", AND(J17="Not Applicable",T17>TODAY()), "Projects under construction must have a "&DR$7, J17="Not Applicable", "", T17<I17, T13&" must preceed pre-tender package submission date",TRUE, "") -> Child Care Floorplan Approval Date cannot be blank if project includes child care. | DS17: =_xlfn.IFS(U17="",DS$7&" cannot be blank", $AC17="", "", U17>$AC17, DS$7&" must preceed construction start date.", TRUE, "") -> Initial Site Plan Submission Date cannot be blank | DT17: =_xlfn.IFS(W17<>"", "", V17="",DT$7&" cannot be blank", $AC17="", "", V17>$AC17, DT$7&" must preceed construction start date.", TRUE, "") -> Site Plan Approval Date cannot be blank | DV17: =_xlfn.IFS(Y17<>"", "", X17="",DV$7&" cannot be blank", $AC17="", "", X17>$AC17, DV$7&" must preceed construction start date.", TRUE, "") -> Build Permit Obtained Date cannot be blank | DX17: =_xlfn.IFS(Z17="",DX$7&" cannot be blank", $AC17="", "", Z17>$AC17, DX$7&" must preceed construction start date.", TRUE, "") -> Tender Issued Date cannot be blank | DY17: =_xlfn.IFS(AA17="",DY$7&" cannot be blank", $AC17="", "", AA17>$AC17, DY$7&" must preceed construction start date.", TRUE, "") -> Tender Closed Date cannot be blank | DZ17: =_xlfn.IFS(AB17="",DZ$7&" cannot be blank", $AC17="", "", AB17>$AC17, DZ$7&" must preceed construction start date.", TRUE, "") -> Contract Awarded Date cannot be blank | EA17: =_xlfn.IFS(AD17<>"", "", AC17="",EA$7&" cannot be blank", $AG17="", "", AC17>EDATE($AG17,-12), EA$7&" must preceed school opening date by more than 12 months.", TRUE, "") | EC17: =_xlfn.IFS(AF17<>"", "", AE17="",EC$7&" cannot be blank", $AG17="", "", AE17>EDATE($AG17,-1), EC$7&" must preceed school opening date by more than one month.", TRUE, "") | EE17: =_xlfn.IFS(AK17="", "", AG17="",EE$7&" cannot be blank",AH17<>"", "", $AG17="", "", AG17>=EDATE($AK17,-11), EE$7&" must preceed financial close date by at least 12 months.", TRUE, "") | EG17: =_xlfn.IFS(CE17=0, "", AI17="",EG$7&" cannot be blank",$AK17="", "",AJ17<>"", "", AI17>=EDATE($AK17,0), EG$7&" must preceed financial close date.", TRUE, "") | EI17: =_xlfn.IFS( AK17="",EI$7&" cannot be blank", TRUE, "") | EO17: =_xlfn.IFS(AQ17="", "Basis of Cost Estimate cannot be blank", AND(AC17<TODAY(), AQ17<>"Based on Tender Results"), "Contract awarded date suggests estimate should be based on tender results", AND(H17<TODAY(), AQ17<>"Based on Class A or B Cost Report"), "If project has already come in for a pre-tender budget, they must have a class A or B cost estimate.", TRUE, "") | EP17: =_xlfn.IFS(OR(AM17=0, AM17=""), "", AR17="", EP$7&" cannot be blank.", TRUE, "") -> Estimated Cost - Construction Project cannot be blank. | EQ17: =_xlfn.IFS(OR(AN17=0, AN17=""), "", AS17="", EQ$7&" cannot be blank.", TRUE, "") -> Estimated Cost - Land cannot be blank. | ER17: =_xlfn.IFS(OR(AO17=0, AO17=""), "", AT17="", ER$7&" cannot be blank.", TRUE, "") -> Estimated Cost - Demolition cannot be blank. | ES17: =_xlfn.IFS(OR(AP17=0, AP17=""), "", AU17="", ES$7&" cannot be blank.", TRUE, "") | EW17: =_xlfn.IFS(EX17<>"", EX17, EY17<>"", EY17, EZ17<>"", EZ17, TRUE, "") | EX17: =IF(J17="MISSING", "This package is missing!", "") | EY17: =IF(K17="", "Confirm you reviewed the pretender checkin documents", "") | EZ17: =IF(AND(K17="Not yet submitted/reviewed", J17<>"Not yet submitted/reviewed"), "Pretender package submitted; col 9 cann't indicate otherwise.", "") | FA17: =_xlfn.IFS(FB17<>"", FB17, FC17<>"", FC17, FD17<>"", FD17, TRUE, "") | FB17: =IF(N17="MISSING", "The post tender package is missing!", "") | FC17: =IF(O17="", "Confirm you reviewed the post tender check-in documents", "") | FD17: =IF(AND(O17="Not yet submitted/reviewed", N17<>"Not yet submitted/reviewed"), "Post-tender package submitted; col 9 cann't indicate otherwise.", "") | FE17: =_xlfn.IFS(FF17<>"", FF17, FG17<>"", FG17, TRUE, FH17) | FF17: =IF(P17<>"", "", "Site Ownership Status cannot be blank") | FG17: =_xlfn.IFS(AND(Q17="", OR(P17="Site Purchased Prior to Capital Approval", P17="Site Purchased")), "", AND(OR(P17="Site Purchased Prior to Capital Approval", P17="Site Purchased"), Q17>TODAY()), "Site purchase date is in the future, but site ownership status indicates site is already purchaseed", TRUE, "") | FH17: =IF(AND(AND(P17<>"Site Purchased Prior to Capital Approval", P17<>"Site Purchased"), Q17<=TODAY()), "Site purchase date is in the past, but site ownership status indicates site has not yet been purchaseed", "") | FI17: =_xlfn.IFS(FJ17<>"", FJ17, FK17<>"", FK17, TRUE,FL17 ) | FJ17: =IF(AND(P17<>"Not Applicable",Q17=""),"Site Purchased Date cannot be blank","") | FK17: =FE17 | FL17: =_xlfn.IFS(Q17="", "", U17="", "", Q17>U17, "Site Purchase Date must preceed Site Plan Submission.", TRUE, "")
A18: 40-153 | B18: St. Matthias Catholic Elementary School | C18: Open - Financial reconciliation underway. | D18: New Construction | E18: Consolidation | F18: In Progress | G18: =_xlfn.IFS($C$3>AK18, "Complete", $C$3>AG18, "Open", $C$3>AC18, "Under Construction", TRUE, "Planning") -> Open | I18: Not Applicable | J18: Not Applicable | K18: Not Applicable | M18: Not Applicable | N18: Not Applicable | O18: Not Applicable | P18: Not Applicable | R18: >80% Complete | AC18: 44910 | AE18: 45627 | AG18: 45663 | AI18: 45748 | AK18: 46266 | AL18: =SUM(AM18:AP18) -> 28088478 | AM18: 27329038 | AO18: 759440 | AQ18: Based on Tender Results | BD18: Open - Financial reconciliation underway. | BE18: Open - Financial reconciliation underway. | BF18: Open - Financial reconciliation underway. | BG18: Open | CD18: =IF(AND(Q18="", A18<>"", P18<>"Site Purchased Prior to Capital Approval"), 1, 0) -> 1 | CE18: 88 | CF18: =_xlfn.XLOOKUP($A18, 'Project Commitment'!$A:$A, 'Project Commitment'!M:M, "") | CG18: =_xlfn.XLOOKUP($A18, 'Project Commitment'!$A:$A, 'Project Commitment'!N:N, "") | CH18: =_xlfn.XLOOKUP($A18, 'Project Commitment'!$A:$A, 'Project Commitment'!O:O, "") | CI18: =_xlfn.XLOOKUP($A18, 'Project Commitment'!$A:$A, 'Project Commitment'!P:P, "") | CJ18: =_xlfn.XLOOKUP($A18, 'Project Commitment'!$A:$A, 'Project Commitment'!Q:Q, "") | CK18: =_xlfn.XLOOKUP($A18, 'Project Commitment'!$A:$A, 'Project Commitment'!R:R, "") | CL18: =_xlfn.XLOOKUP($A18, 'Project Commitment'!$A:$A, 'Project Commitment'!S:S, "") | CM18: =_xlfn.XLOOKUP($A18, 'Project Commitment'!$A:$A, 'Project Commitment'!T:T, "") | CN18: =_xlfn.XLOOKUP($A18, 'Project Commitment'!$A:$A, 'Project Commitment'!U:U, "") | CO18: =_xlfn.XLOOKUP($A18, 'Project Commitment'!$A:$A, 'Project Commitment'!V:V, "") | CP18: =_xlfn.XLOOKUP($A18, 'Project Commitment'!$A:$A, 'Project Commitment'!W:W, "") | CQ18: =_xlfn.XLOOKUP($A18, 'Project Commitment'!$A:$A, 'Project Commitment'!X:X, "") | CR18: =_xlfn.XLOOKUP($A18, 'Project Commitment'!$A:$A, 'Project Commitment'!Y:Y, "") | CS18: =_xlfn.XLOOKUP($A18, 'Project Commitment'!$A:$A, 'Project Commitment'!Z:Z, "") | CT18: =_xlfn.XLOOKUP($A18, 'Project Commitment'!$A:$A, 'Project Commitment'!AA:AA, "") | CU18: =_xlfn.XLOOKUP($A18, 'Project Commitment'!$A:$A, 'Project Commitment'!AB:AB, "") | DA18: =IF(C18="", "Meeting Minutes cannot be blank", "") | DF18: =_xlfn.IFS(AND(J18="Not Applicable", H18<>""), "No date is needed if Column 10 is Not Applicable",J18= "Not Applicable", "", H18="",DF$7&" cannot be blank", $AC18="", "", H18>$AC18, DF$7&" must preceed construction start date.", TRUE, "") | DG18: =_xlfn.IFS(I18="", DG$7&" cannot be left blank.",H18="", "", AND( H18 < TODAY(), I18="Not Yet Known"), "After the submission date, the pre-tender package type must be selected.", TRUE, "") | DI18: =EW18 | DJ18: =_xlfn.IFS(AND(N18="Not Applicable", L18<>""), "No date is needed if Column 14 is Not Applicable",N18= "Not Applicable", "", L18="",DJ$7&" cannot be blank", $AC18="", "", L18>$AC18, DJ$7&" must preceed construction start date.", TRUE, "") | DK18: =_xlfn.IFS(M18="", DK$7&" cannot be left blank.",L18="", "", AND( L18 < TODAY(), M18="Not Yet Known"), "After the submission date, the pre-tender package type must be selected.", TRUE, "") | DM18: =FA18 | DN18: =FE18 | DO18: =FI18 | DP18: =IF(R18="", DP$7&" cannot be blank", "") | DQ18: =_xlfn.IFS(S18="",DQ$7&" cannot be blank",AND(J18<>"Not yet submitted/reviewed",S18>TODAY()),DQ$7&" cannot be in the future if project is ready for a pre-tender package.",TRUE,"") -> Space Template Approval Date cannot be blank | DR18: =_xlfn.IFS(CE18=0, "", T18="",DR$7&" cannot be blank if project includes child care.", AND(J18="Not Applicable",T18>TODAY()), "Projects under construction must have a "&DR$7, J18="Not Applicable", "", T18<I18, T14&" must preceed pre-tender package submission date",TRUE, "") -> Child Care Floorplan Approval Date cannot be blank if project includes child care. | DS18: =_xlfn.IFS(U18="",DS$7&" cannot be blank", $AC18="", "", U18>$AC18, DS$7&" must preceed construction start date.", TRUE, "") -> Initial Site Plan Submission Date cannot be blank | DT18: =_xlfn.IFS(W18<>"", "", V18="",DT$7&" cannot be blank", $AC18="", "", V18>$AC18, DT$7&" must preceed construction start date.", TRUE, "") -> Site Plan Approval Date cannot be blank | DV18: =_xlfn.IFS(Y18<>"", "", X18="",DV$7&" cannot be blank", $AC18="", "", X18>$AC18, DV$7&" must preceed construction start date.", TRUE, "") -> Build Permit Obtained Date cannot be blank | DX18: =_xlfn.IFS(Z18="",DX$7&" cannot be blank", $AC18="", "", Z18>$AC18, DX$7&" must preceed construction start date.", TRUE, "") -> Tender Issued Date cannot be blank | DY18: =_xlfn.IFS(AA18="",DY$7&" cannot be blank", $AC18="", "", AA18>$AC18, DY$7&" must preceed construction start date.", TRUE, "") -> Tender Closed Date cannot be blank | DZ18: =_xlfn.IFS(AB18="",DZ$7&" cannot be blank", $AC18="", "", AB18>$AC18, DZ$7&" must preceed construction start date.", TRUE, "") -> Contract Awarded Date cannot be blank | EA18: =_xlfn.IFS(AD18<>"", "", AC18="",EA$7&" cannot be blank", $AG18="", "", AC18>EDATE($AG18,-12), EA$7&" must preceed school opening date by more than 12 months.", TRUE, "") | EC18: =_xlfn.IFS(AF18<>"", "", AE18="",EC$7&" cannot be blank", $AG18="", "", AE18>EDATE($AG18,-1), EC$7&" must preceed school opening date by more than one month.", TRUE, "") | EE18: =_xlfn.IFS(AK18="", "", AG18="",EE$7&" cannot be blank",AH18<>"", "", $AG18="", "", AG18>=EDATE($AK18,-11), EE$7&" must preceed financial close date by at least 12 months.", TRUE, "") | EG18: =_xlfn.IFS(CE18=0, "", AI18="",EG$7&" cannot be blank",$AK18="", "",AJ18<>"", "", AI18>=EDATE($AK18,0), EG$7&" must preceed financial close date.", TRUE, "") | EI18: =_xlfn.IFS( AK18="",EI$7&" cannot be blank", TRUE, "") | EO18: =_xlfn.IFS(AQ18="", "Basis of Cost Estimate cannot be blank", AND(AC18<TODAY(), AQ18<>"Based on Tender Results"), "Contract awarded date suggests estimate should be based on tender results", AND(H18<TODAY(), AQ18<>"Based on Class A or B Cost Report"), "If project has already come in for a pre-tender budget, they must have a class A or B cost estimate.", TRUE, "") | EP18: =_xlfn.IFS(OR(AM18=0, AM18=""), "", AR18="", EP$7&" cannot be blank.", TRUE, "") -> Estimated Cost - Construction Project cannot be blank. | EQ18: =_xlfn.IFS(OR(AN18=0, AN18=""), "", AS18="", EQ$7&" cannot be blank.", TRUE, "") | ER18: =_xlfn.IFS(OR(AO18=0, AO18=""), "", AT18="", ER$7&" cannot be blank.", TRUE, "") -> Estimated Cost - Demolition cannot be blank. | ES18: =_xlfn.IFS(OR(AP18=0, AP18=""), "", AU18="", ES$7&" cannot be blank.", TRUE, "") | EW18: =_xlfn.IFS(EX18<>"", EX18, EY18<>"", EY18, EZ18<>"", EZ18, TRUE, "") | EX18: =IF(J18="MISSING", "This package is missing!", "") | EY18: =IF(K18="", "Confirm you reviewed the pretender checkin documents", "") | EZ18: =IF(AND(K18="Not yet submitted/reviewed", J18<>"Not yet submitted/reviewed"), "Pretender package submitted; col 9 cann't indicate otherwise.", "") | FA18: =_xlfn.IFS(FB18<>"", FB18, FC18<>"", FC18, FD18<>"", FD18, TRUE, "") | FB18: =IF(N18="MISSING", "The post tender package is missing!", "") | FC18: =IF(O18="", "Confirm you reviewed the post tender check-in documents", "") | FD18: =IF(AND(O18="Not yet submitted/reviewed", N18<>"Not yet submitted/reviewed"), "Post-tender package submitted; col 9 cann't indicate otherwise.", "") | FE18: =_xlfn.IFS(FF18<>"", FF18, FG18<>"", FG18, TRUE, FH18) | FF18: =IF(P18<>"", "", "Site Ownership Status cannot be blank") | FG18: =_xlfn.IFS(AND(Q18="", OR(P18="Site Purchased Prior to Capital Approval", P18="Site Purchased")), "", AND(OR(P18="Site Purchased Prior to Capital Approval", P18="Site Purchased"), Q18>TODAY()), "Site purchase date is in the future, but site ownership status indicates site is already purchaseed", TRUE, "") | FH18: =IF(AND(AND(P18<>"Site Purchased Prior to Capital Approval", P18<>"Site Purchased"), Q18<=TODAY()), "Site purchase date is in the past, but site ownership status indicates site has not yet been purchaseed", "") | FI18: =_xlfn.IFS(FJ18<>"", FJ18, FK18<>"", FK18, TRUE,FL18 ) | FJ18: =IF(AND(P18<>"Not Applicable",Q18=""),"Site Purchased Date cannot be blank","") | FK18: =FE18 | FL18: =_xlfn.IFS(Q18="", "", U18="", "", Q18>U18, "Site Purchase Date must preceed Site Plan Submission.", TRUE, "")
A19: 40-154 | B19: St. Margaret Catholic Elementary School | C19: ATP with ministry. Currently reviewing material. | D19: Addition | E19: Accommodation Pressure | F19: In Progress | G19: =_xlfn.IFS($C$3>AK19, "Complete", $C$3>AG19, "Open", $C$3>AC19, "Under Construction", TRUE, "Planning") -> Planning | H19: 45770 | I19: Additional Funding Required | J19: Not yet submitted/reviewed | K19: Not yet submitted/reviewed | M19: Not Yet Known | N19: Not yet submitted/reviewed | O19: Not yet submitted/reviewed | P19: Not Applicable | R19: >80% Complete | U19: 45881 | AC19: 46204 | AE19: 46600 | AG19: 46636 | AK19: 46721 | AL19: =SUM(AM19:AP19) -> 4936098 | AM19: 4936098 | AQ19: Based on Class A or B Cost Report | BD19: SPA executed/approved - August 12 2025. Building permit in review. Board to update the POD tab. "What else can be removed - | BE19: SPA executed/approved - August 12 2025. Building permit in review. Board to update the POD tab. "What else can be removed - | BF19: SPA executed/approved - August 12 2025. Building permit in review. Board to update the POD tab. "What else can be removed - | BG19: SPA executed/approved - August 12 2025. Building permit in review. Board to update the POD tab. "What else can be removed - | CD19: =IF(AND(Q19="", A19<>"", P19<>"Site Purchased Prior to Capital Approval"), 1, 0) -> 1 | CE19: 49 | CF19: =_xlfn.XLOOKUP($A19, 'Project Commitment'!$A:$A, 'Project Commitment'!M:M, "") -> 0 | CG19: =_xlfn.XLOOKUP($A19, 'Project Commitment'!$A:$A, 'Project Commitment'!N:N, "") -> #VALUE! | CH19: =_xlfn.XLOOKUP($A19, 'Project Commitment'!$A:$A, 'Project Commitment'!O:O, "") -> 0 | CI19: =_xlfn.XLOOKUP($A19, 'Project Commitment'!$A:$A, 'Project Commitment'!P:P, "") -> 0 | CJ19: =_xlfn.XLOOKUP($A19, 'Project Commitment'!$A:$A, 'Project Commitment'!Q:Q, "") -> 45717 | CK19: =_xlfn.XLOOKUP($A19, 'Project Commitment'!$A:$A, 'Project Commitment'!R:R, "") -> 0 | CL19: =_xlfn.XLOOKUP($A19, 'Project Commitment'!$A:$A, 'Project Commitment'!S:S, "") -> #VALUE! | CM19: =_xlfn.XLOOKUP($A19, 'Project Commitment'!$A:$A, 'Project Commitment'!T:T, "") -> 0 | CN19: =_xlfn.XLOOKUP($A19, 'Project Commitment'!$A:$A, 'Project Commitment'!U:U, "") -> #VALUE! | CO19: =_xlfn.XLOOKUP($A19, 'Project Commitment'!$A:$A, 'Project Commitment'!V:V, "") -> #VALUE! | CP19: =_xlfn.XLOOKUP($A19, 'Project Commitment'!$A:$A, 'Project Commitment'!W:W, "") -> 0 | CQ19: =_xlfn.XLOOKUP($A19, 'Project Commitment'!$A:$A, 'Project Commitment'!X:X, "") -> -395 | CR19: =_xlfn.XLOOKUP($A19, 'Project Commitment'!$A:$A, 'Project Commitment'!Y:Y, "") -> #VALUE! | CS19: =_xlfn.XLOOKUP($A19, 'Project Commitment'!$A:$A, 'Project Commitment'!Z:Z, "") -> -248 | CT19: =_xlfn.XLOOKUP($A19, 'Project Commitment'!$A:$A, 'Project Commitment'!AA:AA, "") -> 0 | CU19: =_xlfn.XLOOKUP($A19, 'Project Commitment'!$A:$A, 'Project Commitment'!AB:AB, "") -> #VALUE! | DA19: =IF(C19="", "Meeting Minutes cannot be blank", "") | DF19: =_xlfn.IFS(AND(J19="Not Applicable", H19<>""), "No date is needed if Column 10 is Not Applicable",J19= "Not Applicable", "", H19="",DF$7&" cannot be blank", $AC19="", "", H19>$AC19, DF$7&" must preceed construction start date.", TRUE, "") | DG19: =_xlfn.IFS(I19="", DG$7&" cannot be left blank.",H19="", "", AND( H19 < TODAY(), I19="Not Yet Known"), "After the submission date, the pre-tender package type must be selected.", TRUE, "") | DI19: =EW19 | DJ19: =_xlfn.IFS(AND(N19="Not Applicable", L19<>""), "No date is needed if Column 14 is Not Applicable",N19= "Not Applicable", "", L19="",DJ$7&" cannot be blank", $AC19="", "", L19>$AC19, DJ$7&" must preceed construction start date.", TRUE, "") -> Post-Tender Submission Date cannot be blank | DK19: =_xlfn.IFS(M19="", DK$7&" cannot be left blank.",L19="", "", AND( L19 < TODAY(), M19="Not Yet Known"), "After the submission date, the pre-tender package type must be selected.", TRUE, "") | DM19: =FA19 | DN19: =FE19 | DO19: =FI19 | DP19: =IF(R19="", DP$7&" cannot be blank", "") | DQ19: =_xlfn.IFS(S19="",DQ$7&" cannot be blank",AND(J19<>"Not yet submitted/reviewed",S19>TODAY()),DQ$7&" cannot be in the future if project is ready for a pre-tender package.",TRUE,"") -> Space Template Approval Date cannot be blank | DR19: =_xlfn.IFS(CE19=0, "", T19="",DR$7&" cannot be blank if project includes child care.", AND(J19="Not Applicable",T19>TODAY()), "Projects under construction must have a "&DR$7, J19="Not Applicable", "", T19<I19, T15&" must preceed pre-tender package submission date",TRUE, "") -> Child Care Floorplan Approval Date cannot be blank if project includes child care. | DS19: =_xlfn.IFS(U19="",DS$7&" cannot be blank", $AC19="", "", U19>$AC19, DS$7&" must preceed construction start date.", TRUE, "") | DT19: =_xlfn.IFS(W19<>"", "", V19="",DT$7&" cannot be blank", $AC19="", "", V19>$AC19, DT$7&" must preceed construction start date.", TRUE, "") -> Site Plan Approval Date cannot be blank | DV19: =_xlfn.IFS(Y19<>"", "", X19="",DV$7&" cannot be blank", $AC19="", "", X19>$AC19, DV$7&" must preceed construction start date.", TRUE, "") -> Build Permit Obtained Date cannot be blank | DX19: =_xlfn.IFS(Z19="",DX$7&" cannot be blank", $AC19="", "", Z19>$AC19, DX$7&" must preceed construction start date.", TRUE, "") -> Tender Issued Date cannot be blank | DY19: =_xlfn.IFS(AA19="",DY$7&" cannot be blank", $AC19="", "", AA19>$AC19, DY$7&" must preceed construction start date.", TRUE, "") -> Tender Closed Date cannot be blank | DZ19: =_xlfn.IFS(AB19="",DZ$7&" cannot be blank", $AC19="", "", AB19>$AC19, DZ$7&" must preceed construction start date.", TRUE, "") -> Contract Awarded Date cannot be blank | EA19: =_xlfn.IFS(AD19<>"", "", AC19="",EA$7&" cannot be blank", $AG19="", "", AC19>EDATE($AG19,-12), EA$7&" must preceed school opening date by more than 12 months.", TRUE, "") | EC19: =_xlfn.IFS(AF19<>"", "", AE19="",EC$7&" cannot be blank", $AG19="", "", AE19>EDATE($AG19,-1), EC$7&" must preceed school opening date by more than one month.", TRUE, "") | EE19: =_xlfn.IFS(AK19="", "", AG19="",EE$7&" cannot be blank",AH19<>"", "", $AG19="", "", AG19>=EDATE($AK19,-11), EE$7&" must preceed financial close date by at least 12 months.", TRUE, "") -> School Opening Date must preceed financial close date by at least 12 months. | EG19: =_xlfn.IFS(CE19=0, "", AI19="",EG$7&" cannot be blank",$AK19="", "",AJ19<>"", "", AI19>=EDATE($AK19,0), EG$7&" must preceed financial close date.", TRUE, "") -> Child Care Opening Date cannot be blank | EI19: =_xlfn.IFS( AK19="",EI$7&" cannot be blank", TRUE, "") | EO19: =_xlfn.IFS(AQ19="", "Basis of Cost Estimate cannot be blank", AND(AC19<TODAY(), AQ19<>"Based on Tender Results"), "Contract awarded date suggests estimate should be based on tender results", AND(H19<TODAY(), AQ19<>"Based on Class A or B Cost Report"), "If project has already come in for a pre-tender budget, they must have a class A or B cost estimate.", TRUE, "") | EP19: =_xlfn.IFS(OR(AM19=0, AM19=""), "", AR19="", EP$7&" cannot be blank.", TRUE, "") -> Estimated Cost - Construction Project cannot be blank. | EQ19: =_xlfn.IFS(OR(AN19=0, AN19=""), "", AS19="", EQ$7&" cannot be blank.", TRUE, "") | ER19: =_xlfn.IFS(OR(AO19=0, AO19=""), "", AT19="", ER$7&" cannot be blank.", TRUE, "") | ES19: =_xlfn.IFS(OR(AP19=0, AP19=""), "", AU19="", ES$7&" cannot be blank.", TRUE, "") | EW19: =_xlfn.IFS(EX19<>"", EX19, EY19<>"", EY19, EZ19<>"", EZ19, TRUE, "") | EX19: =IF(J19="MISSING", "This package is missing!", "") | EY19: =IF(K19="", "Confirm you reviewed the pretender checkin documents", "") | EZ19: =IF(AND(K19="Not yet submitted/reviewed", J19<>"Not yet submitted/reviewed"), "Pretender package submitted; col 9 cann't indicate otherwise.", "") | FA19: =_xlfn.IFS(FB19<>"", FB19, FC19<>"", FC19, FD19<>"", FD19, TRUE, "") | FB19: =IF(N19="MISSING", "The post tender package is missing!", "") | FC19: =IF(O19="", "Confirm you reviewed the post tender check-in documents", "") | FD19: =IF(AND(O19="Not yet submitted/reviewed", N19<>"Not yet submitted/reviewed"), "Post-tender package submitted; col 9 cann't indicate otherwise.", "") | FE19: =_xlfn.IFS(FF19<>"", FF19, FG19<>"", FG19, TRUE, FH19) | FF19: =IF(P19<>"", "", "Site Ownership Status cannot be blank") | FG19: =_xlfn.IFS(AND(Q19="", OR(P19="Site Purchased Prior to Capital Approval", P19="Site Purchased")), "", AND(OR(P19="Site Purchased Prior to Capital Approval", P19="Site Purchased"), Q19>TODAY()), "Site purchase date is in the future, but site ownership status indicates site is already purchaseed", TRUE, "") | FH19: =IF(AND(AND(P19<>"Site Purchased Prior to Capital Approval", P19<>"Site Purchased"), Q19<=TODAY()), "Site purchase date is in the past, but site ownership status indicates site has not yet been purchaseed", "") | FI19: =_xlfn.IFS(FJ19<>"", FJ19, FK19<>"", FK19, TRUE,FL19 ) | FJ19: =IF(AND(P19<>"Not Applicable",Q19=""),"Site Purchased Date cannot be blank","") | FK19: =FE19 | FL19: =_xlfn.IFS(Q19="", "", U19="", "", Q19>U19, "Site Purchase Date must preceed Site Plan Submission.", TRUE, "")
A20: 40-156 | B20: Baycrest Catholic Elementary School | C20: Board is close to clearing all NOAC conditions and hopes the SPA and Building Permit are finalized before construction begins. Derek and Didem spoke regarding POD funding for this project. Still no direction given if any POD can be applied to cost overages. Demolition is substantially complete. | D20: New Construction | E20: Accommodation Pressure | F20: In Progress | G20: =_xlfn.IFS($C$3>AK20, "Complete", $C$3>AG20, "Open", $C$3>AC20, "Under Construction", TRUE, "Planning") -> Planning | H20: 45812 | I20: Additional Funding Required | J20: Not yet submitted/reviewed | K20: Not yet submitted/reviewed | M20: Not Yet Known | N20: Not yet submitted/reviewed | O20: Not yet submitted/reviewed | P20: Site Purchased | Q20: 43733 | R20: >80% Complete | S20: 43881 | V20: 45748 | AC20: 46113 | AE20: 46569 | AG20: 46637 | AI20: 46637 | AK20: 46667 | AL20: =SUM(AM20:AP20) -> 12339687 | AM20: 12339687 | AQ20: Based on Class A or B Cost Report | BD20: NOAC received and SB responding to comments. SB to meet with city to discuss conditions. Board is close to clearing all NOAC conditions and hopes the SPA and Building Permit are finalized before construction begins. Derek and Didem spoke regarding POD funding for this project. Still no direction given if any POD can be applied to cost overages. | BE20: NOAC received and SB responding to comments. SB to meet with city to discuss conditions. Board is close to clearing all NOAC conditions. Hope are that the SPA and Building Permit are finalized before construction begins. Regarding ATP request, board to provide additional information shortly and will let ministry know if POD is an issue to move forward ($25M out of $34M is POD-Regular). | BF20: NOAC received and SB responding to comments. SB to meet with city to discuss conditions. | BG20: NOAC received and SB responding to comments. SB to meet with city to discuss conditions. | CD20: =IF(AND(Q20="", A20<>"", P20<>"Site Purchased Prior to Capital Approval"), 1, 0) -> 0 | CE20: 49 | CF20: =_xlfn.XLOOKUP($A20, 'Project Commitment'!$A:$A, 'Project Commitment'!M:M, "") -> 0 | CG20: =_xlfn.XLOOKUP($A20, 'Project Commitment'!$A:$A, 'Project Commitment'!N:N, "") -> 0 | CH20: =_xlfn.XLOOKUP($A20, 'Project Commitment'!$A:$A, 'Project Commitment'!O:O, "") -> 0 | CI20: =_xlfn.XLOOKUP($A20, 'Project Commitment'!$A:$A, 'Project Commitment'!P:P, "") -> 0 | CJ20: =_xlfn.XLOOKUP($A20, 'Project Commitment'!$A:$A, 'Project Commitment'!Q:Q, "") -> 0 | CK20: =_xlfn.XLOOKUP($A20, 'Project Commitment'!$A:$A, 'Project Commitment'!R:R, "") -> 0 | CL20: =_xlfn.XLOOKUP($A20, 'Project Commitment'!$A:$A, 'Project Commitment'!S:S, "") -> #VALUE! | CM20: =_xlfn.XLOOKUP($A20, 'Project Commitment'!$A:$A, 'Project Commitment'!T:T, "") -> 0 | CN20: =_xlfn.XLOOKUP($A20, 'Project Commitment'!$A:$A, 'Project Commitment'!U:U, "") -> #VALUE! | CO20: =_xlfn.XLOOKUP($A20, 'Project Commitment'!$A:$A, 'Project Commitment'!V:V, "") -> #VALUE! | CP20: =_xlfn.XLOOKUP($A20, 'Project Commitment'!$A:$A, 'Project Commitment'!W:W, "") -> 0 | CQ20: =_xlfn.XLOOKUP($A20, 'Project Commitment'!$A:$A, 'Project Commitment'!X:X, "") -> -274 | CR20: =_xlfn.XLOOKUP($A20, 'Project Commitment'!$A:$A, 'Project Commitment'!Y:Y, "") -> #VALUE! | CS20: =_xlfn.XLOOKUP($A20, 'Project Commitment'!$A:$A, 'Project Commitment'!Z:Z, "") -> -6 | CT20: =_xlfn.XLOOKUP($A20, 'Project Commitment'!$A:$A, 'Project Commitment'!AA:AA, "") -> 0 | CU20: =_xlfn.XLOOKUP($A20, 'Project Commitment'!$A:$A, 'Project Commitment'!AB:AB, "") -> #VALUE! | DA20: =IF(C20="", "Meeting Minutes cannot be blank", "") | DF20: =_xlfn.IFS(AND(J20="Not Applicable", H20<>""), "No date is needed if Column 10 is Not Applicable",J20= "Not Applicable", "", H20="",DF$7&" cannot be blank", $AC20="", "", H20>$AC20, DF$7&" must preceed construction start date.", TRUE, "") | DG20: =_xlfn.IFS(I20="", DG$7&" cannot be left blank.",H20="", "", AND( H20 < TODAY(), I20="Not Yet Known"), "After the submission date, the pre-tender package type must be selected.", TRUE, "") | DI20: =EW20 | DJ20: =_xlfn.IFS(AND(N20="Not Applicable", L20<>""), "No date is needed if Column 14 is Not Applicable",N20= "Not Applicable", "", L20="",DJ$7&" cannot be blank", $AC20="", "", L20>$AC20, DJ$7&" must preceed construction start date.", TRUE, "") -> Post-Tender Submission Date cannot be blank | DK20: =_xlfn.IFS(M20="", DK$7&" cannot be left blank.",L20="", "", AND( L20 < TODAY(), M20="Not Yet Known"), "After the submission date, the pre-tender package type must be selected.", TRUE, "") | DM20: =FA20 | DN20: =FE20 | DO20: =FI20 | DP20: =IF(R20="", DP$7&" cannot be blank", "") | DQ20: =_xlfn.IFS(S20="",DQ$7&" cannot be blank",AND(J20<>"Not yet submitted/reviewed",S20>TODAY()),DQ$7&" cannot be in the future if project is ready for a pre-tender package.",TRUE,"") | DR20: =_xlfn.IFS(CE20=0, "", T20="",DR$7&" cannot be blank if project includes child care.", AND(J20="Not Applicable",T20>TODAY()), "Projects under construction must have a "&DR$7, J20="Not Applicable", "", T20<I20, T16&" must preceed pre-tender package submission date",TRUE, "") -> Child Care Floorplan Approval Date cannot be blank if project includes child care. | DS20: =_xlfn.IFS(U20="",DS$7&" cannot be blank", $AC20="", "", U20>$AC20, DS$7&" must preceed construction start date.", TRUE, "") -> Initial Site Plan Submission Date cannot be blank | DT20: =_xlfn.IFS(W20<>"", "", V20="",DT$7&" cannot be blank", $AC20="", "", V20>$AC20, DT$7&" must preceed construction start date.", TRUE, "") | DV20: =_xlfn.IFS(Y20<>"", "", X20="",DV$7&" cannot be blank", $AC20="", "", X20>$AC20, DV$7&" must preceed construction start date.", TRUE, "") -> Build Permit Obtained Date cannot be blank | DX20: =_xlfn.IFS(Z20="",DX$7&" cannot be blank", $AC20="", "", Z20>$AC20, DX$7&" must preceed construction start date.", TRUE, "") -> Tender Issued Date cannot be blank | DY20: =_xlfn.IFS(AA20="",DY$7&" cannot be blank", $AC20="", "", AA20>$AC20, DY$7&" must preceed construction start date.", TRUE, "") -> Tender Closed Date cannot be blank | DZ20: =_xlfn.IFS(AB20="",DZ$7&" cannot be blank", $AC20="", "", AB20>$AC20, DZ$7&" must preceed construction start date.", TRUE, "") -> Contract Awarded Date cannot be blank | EA20: =_xlfn.IFS(AD20<>"", "", AC20="",EA$7&" cannot be blank", $AG20="", "", AC20>EDATE($AG20,-12), EA$7&" must preceed school opening date by more than 12 months.", TRUE, "") | EC20: =_xlfn.IFS(AF20<>"", "", AE20="",EC$7&" cannot be blank", $AG20="", "", AE20>EDATE($AG20,-1), EC$7&" must preceed school opening date by more than one month.", TRUE, "") | EE20: =_xlfn.IFS(AK20="", "", AG20="",EE$7&" cannot be blank",AH20<>"", "", $AG20="", "", AG20>=EDATE($AK20,-11), EE$7&" must preceed financial close date by at least 12 months.", TRUE, "") -> School Opening Date must preceed financial close date by at least 12 months. | EG20: =_xlfn.IFS(CE20=0, "", AI20="",EG$7&" cannot be blank",$AK20="", "",AJ20<>"", "", AI20>=EDATE($AK20,0), EG$7&" must preceed financial close date.", TRUE, "") | EI20: =_xlfn.IFS( AK20="",EI$7&" cannot be blank", TRUE, "") | EO20: =_xlfn.IFS(AQ20="", "Basis of Cost Estimate cannot be blank", AND(AC20<TODAY(), AQ20<>"Based on Tender Results"), "Contract awarded date suggests estimate should be based on tender results", AND(H20<TODAY(), AQ20<>"Based on Class A or B Cost Report"), "If project has already come in for a pre-tender budget, they must have a class A or B cost estimate.", TRUE, "") | EP20: =_xlfn.IFS(OR(AM20=0, AM20=""), "", AR20="", EP$7&" cannot be blank.", TRUE, "") -> Estimated Cost - Construction Project cannot be blank. | EQ20: =_xlfn.IFS(OR(AN20=0, AN20=""), "", AS20="", EQ$7&" cannot be blank.", TRUE, "") | ER20: =_xlfn.IFS(OR(AO20=0, AO20=""), "", AT20="", ER$7&" cannot be blank.", TRUE, "") | ES20: =_xlfn.IFS(OR(AP20=0, AP20=""), "", AU20="", ES$7&" cannot be blank.", TRUE, "") | EW20: =_xlfn.IFS(EX20<>"", EX20, EY20<>"", EY20, EZ20<>"", EZ20, TRUE, "") | EX20: =IF(J20="MISSING", "This package is missing!", "") | EY20: =IF(K20="", "Confirm you reviewed the pretender checkin documents", "") | EZ20: =IF(AND(K20="Not yet submitted/reviewed", J20<>"Not yet submitted/reviewed"), "Pretender package submitted; col 9 cann't indicate otherwise.", "") | FA20: =_xlfn.IFS(FB20<>"", FB20, FC20<>"", FC20, FD20<>"", FD20, TRUE, "") | FB20: =IF(N20="MISSING", "The post tender package is missing!", "") | FC20: =IF(O20="", "Confirm you reviewed the post tender check-in documents", "") | FD20: =IF(AND(O20="Not yet submitted/reviewed", N20<>"Not yet submitted/reviewed"), "Post-tender package submitted; col 9 cann't indicate otherwise.", "") | FE20: =_xlfn.IFS(FF20<>"", FF20, FG20<>"", FG20, TRUE, FH20) | FF20: =IF(P20<>"", "", "Site Ownership Status cannot be blank") | FG20: =_xlfn.IFS(AND(Q20="", OR(P20="Site Purchased Prior to Capital Approval", P20="Site Purchased")), "", AND(OR(P20="Site Purchased Prior to Capital Approval", P20="Site Purchased"), Q20>TODAY()), "Site purchase date is in the future, but site ownership status indicates site is already purchaseed", TRUE, "") | FH20: =IF(AND(AND(P20<>"Site Purchased Prior to Capital Approval", P20<>"Site Purchased"), Q20<=TODAY()), "Site purchase date is in the past, but site ownership status indicates site has not yet been purchaseed", "") | FI20: =_xlfn.IFS(FJ20<>"", FJ20, FK20<>"", FK20, TRUE,FL20 ) | FJ20: =IF(AND(P20<>"Not Applicable",Q20=""),"Site Purchased Date cannot be blank","") | FK20: =FE20 | FL20: =_xlfn.IFS(Q20="", "", U20="", "", Q20>U20, "Site Purchase Date must preceed Site Plan Submission.", TRUE, "")
A21: 40-157 | B21: Buttonwood Catholic Elementary School | C21: Construction is progressing well and remains on schedule. The ground floor concrete pour has been completed, and vertical construction is underway. A boundary review and school name selection process are currently underway. | D21: New Construction | E21: Accommodation Pressure | F21: In Progress | G21: =_xlfn.IFS($C$3>AK21, "Complete", $C$3>AG21, "Open", $C$3>AC21, "Under Construction", TRUE, "Planning") -> Under Construction | I21: Not Applicable | J21: Not Applicable | K21: Not Applicable | M21: Not Applicable | N21: Not Applicable | O21: Not Applicable | P21: Site Purchased | Q21: 43531 | R21: >80% Complete | S21: 44229 | T21: 45244 | U21: 45414 | V21: 45642 | X21: 45689 | Z21: 45567 | AA21: 45611 | AB21: 45646 | AC21: 45689 | AE21: 46600 | AG21: 46631 | AI21: 46631 | AK21: 47084 | AL21: =SUM(AM21:AP21) -> 41164070 | AM21: 41164070 | AQ21: Based on Class A or B Cost Report | BD21: Project progressing well. On schedule - finished pouring ground floor, concrete work. Walls are going up. Ground breaking ceremony to be scheduled with minister. TBD (original ground breaking set for Nov 25, but cancelled due to weather). Boundary review and name selection are currently underway for this school. | BE21: Project progressing well. On schedule - finished pouring ground floor, concrete work. Walls are going up. | BF21: Project progressing well. On schedule - finished pouring ground floor, concrete work. | BG21: Project progressing well. | CD21: =IF(AND(Q21="", A21<>"", P21<>"Site Purchased Prior to Capital Approval"), 1, 0) -> 0 | CE21: 88 | CF21: =_xlfn.XLOOKUP($A21, 'Project Commitment'!$A:$A, 'Project Commitment'!M:M, "") -> 0 | CG21: =_xlfn.XLOOKUP($A21, 'Project Commitment'!$A:$A, 'Project Commitment'!N:N, "") -> 0 | CH21: =_xlfn.XLOOKUP($A21, 'Project Commitment'!$A:$A, 'Project Commitment'!O:O, "") -> 0 | CI21: =_xlfn.XLOOKUP($A21, 'Project Commitment'!$A:$A, 'Project Commitment'!P:P, "") -> 0 | CJ21: =_xlfn.XLOOKUP($A21, 'Project Commitment'!$A:$A, 'Project Commitment'!Q:Q, "") -> -15 | CK21: =_xlfn.XLOOKUP($A21, 'Project Commitment'!$A:$A, 'Project Commitment'!R:R, "") -> 0 | CL21: =_xlfn.XLOOKUP($A21, 'Project Commitment'!$A:$A, 'Project Commitment'!S:S, "") -> #VALUE! | CM21: =_xlfn.XLOOKUP($A21, 'Project Commitment'!$A:$A, 'Project Commitment'!T:T, "") -> 0 | CN21: =_xlfn.XLOOKUP($A21, 'Project Commitment'!$A:$A, 'Project Commitment'!U:U, "") -> #VALUE! | CO21: =_xlfn.XLOOKUP($A21, 'Project Commitment'!$A:$A, 'Project Commitment'!V:V, "") -> #VALUE! | CP21: =_xlfn.XLOOKUP($A21, 'Project Commitment'!$A:$A, 'Project Commitment'!W:W, "") -> 0 | CQ21: =_xlfn.XLOOKUP($A21, 'Project Commitment'!$A:$A, 'Project Commitment'!X:X, "") -> -31 | CR21: =_xlfn.XLOOKUP($A21, 'Project Commitment'!$A:$A, 'Project Commitment'!Y:Y, "") -> #VALUE! | CS21: =_xlfn.XLOOKUP($A21, 'Project Commitment'!$A:$A, 'Project Commitment'!Z:Z, "") -> 0 | CT21: =_xlfn.XLOOKUP($A21, 'Project Commitment'!$A:$A, 'Project Commitment'!AA:AA, "") -> 0 | CU21: =_xlfn.XLOOKUP($A21, 'Project Commitment'!$A:$A, 'Project Commitment'!AB:AB, "") -> #VALUE! | DA21: =IF(C21="", "Meeting Minutes cannot be blank", "") | DF21: =_xlfn.IFS(AND(J21="Not Applicable", H21<>""), "No date is needed if Column 10 is Not Applicable",J21= "Not Applicable", "", H21="",DF$7&" cannot be blank", $AC21="", "", H21>$AC21, DF$7&" must preceed construction start date.", TRUE, "") | DG21: =_xlfn.IFS(I21="", DG$7&" cannot be left blank.",H21="", "", AND( H21 < TODAY(), I21="Not Yet Known"), "After the submission date, the pre-tender package type must be selected.", TRUE, "") | DI21: =EW21 | DJ21: =_xlfn.IFS(AND(N21="Not Applicable", L21<>""), "No date is needed if Column 14 is Not Applicable",N21= "Not Applicable", "", L21="",DJ$7&" cannot be blank", $AC21="", "", L21>$AC21, DJ$7&" must preceed construction start date.", TRUE, "") | DK21: =_xlfn.IFS(M21="", DK$7&" cannot be left blank.",L21="", "", AND( L21 < TODAY(), M21="Not Yet Known"), "After the submission date, the pre-tender package type must be selected.", TRUE, "") | DM21: =FA21 | DN21: =FE21 | DO21: =FI21 | DP21: =IF(R21="", DP$7&" cannot be blank", "") | DQ21: =_xlfn.IFS(S21="",DQ$7&" cannot be blank",AND(J21<>"Not yet submitted/reviewed",S21>TODAY()),DQ$7&" cannot be in the future if project is ready for a pre-tender package.",TRUE,"") | DR21: =_xlfn.IFS(CE21=0, "", T21="",DR$7&" cannot be blank if project includes child care.", AND(J21="Not Applicable",T21>TODAY()), "Projects under construction must have a "&DR$7, J21="Not Applicable", "", T21<I21, T17&" must preceed pre-tender package submission date",TRUE, "") | DS21: =_xlfn.IFS(U21="",DS$7&" cannot be blank", $AC21="", "", U21>$AC21, DS$7&" must preceed construction start date.", TRUE, "") | DT21: =_xlfn.IFS(W21<>"", "", V21="",DT$7&" cannot be blank", $AC21="", "", V21>$AC21, DT$7&" must preceed construction start date.", TRUE, "") | DV21: =_xlfn.IFS(Y21<>"", "", X21="",DV$7&" cannot be blank", $AC21="", "", X21>$AC21, DV$7&" must preceed construction start date.", TRUE, "") | DX21: =_xlfn.IFS(Z21="",DX$7&" cannot be blank", $AC21="", "", Z21>$AC21, DX$7&" must preceed construction start date.", TRUE, "") | DY21: =_xlfn.IFS(AA21="",DY$7&" cannot be blank", $AC21="", "", AA21>$AC21, DY$7&" must preceed construction start date.", TRUE, "") | DZ21: =_xlfn.IFS(AB21="",DZ$7&" cannot be blank", $AC21="", "", AB21>$AC21, DZ$7&" must preceed construction start date.", TRUE, "") | EA21: =_xlfn.IFS(AD21<>"", "", AC21="",EA$7&" cannot be blank", $AG21="", "", AC21>EDATE($AG21,-12), EA$7&" must preceed school opening date by more than 12 months.", TRUE, "") | EC21: =_xlfn.IFS(AF21<>"", "", AE21="",EC$7&" cannot be blank", $AG21="", "", AE21>EDATE($AG21,-1), EC$7&" must preceed school opening date by more than one month.", TRUE, "") | EE21: =_xlfn.IFS(AK21="", "", AG21="",EE$7&" cannot be blank",AH21<>"", "", $AG21="", "", AG21>=EDATE($AK21,-11), EE$7&" must preceed financial close date by at least 12 months.", TRUE, "") | EG21: =_xlfn.IFS(CE21=0, "", AI21="",EG$7&" cannot be blank",$AK21="", "",AJ21<>"", "", AI21>=EDATE($AK21,0), EG$7&" must preceed financial close date.", TRUE, "") | EI21: =_xlfn.IFS( AK21="",EI$7&" cannot be blank", TRUE, "") | EO21: =_xlfn.IFS(AQ21="", "Basis of Cost Estimate cannot be blank", AND(AC21<TODAY(), AQ21<>"Based on Tender Results"), "Contract awarded date suggests estimate should be based on tender results", AND(H21<TODAY(), AQ21<>"Based on Class A or B Cost Report"), "If project has already come in for a pre-tender budget, they must have a class A or B cost estimate.", TRUE, "") -> Contract awarded date suggests estimate should be based on tender results | EP21: =_xlfn.IFS(OR(AM21=0, AM21=""), "", AR21="", EP$7&" cannot be blank.", TRUE, "") -> Estimated Cost - Construction Project cannot be blank. | EQ21: =_xlfn.IFS(OR(AN21=0, AN21=""), "", AS21="", EQ$7&" cannot be blank.", TRUE, "") | ER21: =_xlfn.IFS(OR(AO21=0, AO21=""), "", AT21="", ER$7&" cannot be blank.", TRUE, "") | ES21: =_xlfn.IFS(OR(AP21=0, AP21=""), "", AU21="", ES$7&" cannot be blank.", TRUE, "") | EW21: =_xlfn.IFS(EX21<>"", EX21, EY21<>"", EY21, EZ21<>"", EZ21, TRUE, "") | EX21: =IF(J21="MISSING", "This package is missing!", "") | EY21: =IF(K21="", "Confirm you reviewed the pretender checkin documents", "") | EZ21: =IF(AND(K21="Not yet submitted/reviewed", J21<>"Not yet submitted/reviewed"), "Pretender package submitted; col 9 cann't indicate otherwise.", "") | FA21: =_xlfn.IFS(FB21<>"", FB21, FC21<>"", FC21, FD21<>"", FD21, TRUE, "") | FB21: =IF(N21="MISSING", "The post tender package is missing!", "") | FC21: =IF(O21="", "Confirm you reviewed the post tender check-in documents", "") | FD21: =IF(AND(O21="Not yet submitted/reviewed", N21<>"Not yet submitted/reviewed"), "Post-tender package submitted; col 9 cann't indicate otherwise.", "") | FE21: =_xlfn.IFS(FF21<>"", FF21, FG21<>"", FG21, TRUE, FH21) | FF21: =IF(P21<>"", "", "Site Ownership Status cannot be blank") | FG21: =_xlfn.IFS(AND(Q21="", OR(P21="Site Purchased Prior to Capital Approval", P21="Site Purchased")), "", AND(OR(P21="Site Purchased Prior to Capital Approval", P21="Site Purchased"), Q21>TODAY()), "Site purchase date is in the future, but site ownership status indicates site is already purchaseed", TRUE, "") | FH21: =IF(AND(AND(P21<>"Site Purchased Prior to Capital Approval", P21<>"Site Purchased"), Q21<=TODAY()), "Site purchase date is in the past, but site ownership status indicates site has not yet been purchaseed", "") | FI21: =_xlfn.IFS(FJ21<>"", FJ21, FK21<>"", FK21, TRUE,FL21 ) | FJ21: =IF(AND(P21<>"Not Applicable",Q21=""),"Site Purchased Date cannot be blank","") | FK21: =FE21 | FL21: =_xlfn.IFS(Q21="", "", U21="", "", Q21>U21, "Site Purchase Date must preceed Site Plan Submission.", TRUE, "")
A22: 40-158 | B22: Buttonwood Catholic Secondary School | C22: ATP has been submitted. Need to review the design vs. space template. Board reviewing if the chapel can be incorporated within the existing building, and not as an addition. School Board is reviewing the drawings. The contractor for this project indicated the project will not require an SPA, as it is a retrofit of an existing build. Asked if the chapel addition would trigger a SPA, the school board indicated it wouldn't. | D22: New Construction | E22: Accommodation Pressure | F22: In Progress | G22: =_xlfn.IFS($C$3>AK22, "Complete", $C$3>AG22, "Open", $C$3>AC22, "Under Construction", TRUE, "Planning") -> Planning | H22: 45972 | I22: Additional Funding Required | J22: Not yet submitted/reviewed | K22: No | L22: 46295 | M22: Not Yet Known | N22: Not yet submitted/reviewed | O22: Not yet submitted/reviewed | P22: Site Purchased | Q22: 45573 | R22: >80% Complete | S22: 45566 | Z22: 46203 | AA22: 46249 | AB22: 46295 | AC22: 46325 | AE22: 46741 | AG22: 46753 | AK22: 47119 | AL22: =SUM(AM22:AP22) -> 94755588 | AM22: 26355588 | AN22: 68400000 | AQ22: Based on estimate of $/sq ft | BD22: ATP has been submitted. Need to review the design vs. space template. Chapel size. Confirm with school board if a SPA required on this project, even with an addition? Planner from the consultant group advised that SPA is not required due to the location of the chapel ...it is in the back of the school, set away from Royal York Rd. Confirm dates with board to include in package. Pressure to hae this project moving | BE22: SB reviewing the design and cost estimate, look to see what can be cut to save on costs. No SPA required on this project, because of retrofit. SB would space template, scope change request and ATP. | BF22: SB reviewing the design and cost estimate, look to see what can be cut to save on costs. No SPA required on this project, because of retrofit. SB would space template, scope change request and ATP. | BG22: Cost estimate to be received in September. Design development to be complete. Board to look to see what can be cut to save on costs. No SPA required on this project, because of retrofit. SB would space template, scope change request and ATP. | CD22: =IF(AND(Q22="", A22<>"", P22<>"Site Purchased Prior to Capital Approval"), 1, 0) -> 0 | CE22: 0 | CF22: =_xlfn.XLOOKUP($A22, 'Project Commitment'!$A:$A, 'Project Commitment'!M:M, "") -> 0 | CG22: =_xlfn.XLOOKUP($A22, 'Project Commitment'!$A:$A, 'Project Commitment'!N:N, "") -> 0 | CH22: =_xlfn.XLOOKUP($A22, 'Project Commitment'!$A:$A, 'Project Commitment'!O:O, "") -> 0 | CI22: =_xlfn.XLOOKUP($A22, 'Project Commitment'!$A:$A, 'Project Commitment'!P:P, "") -> 0 | CJ22: =_xlfn.XLOOKUP($A22, 'Project Commitment'!$A:$A, 'Project Commitment'!Q:Q, "") -> #VALUE! | CK22: =_xlfn.XLOOKUP($A22, 'Project Commitment'!$A:$A, 'Project Commitment'!R:R, "") -> 0 | CL22: =_xlfn.XLOOKUP($A22, 'Project Commitment'!$A:$A, 'Project Commitment'!S:S, "") -> #VALUE! | CM22: =_xlfn.XLOOKUP($A22, 'Project Commitment'!$A:$A, 'Project Commitment'!T:T, "") -> 0 | CN22: =_xlfn.XLOOKUP($A22, 'Project Commitment'!$A:$A, 'Project Commitment'!U:U, "") -> #VALUE! | CO22: =_xlfn.XLOOKUP($A22, 'Project Commitment'!$A:$A, 'Project Commitment'!V:V, "") -> #VALUE! | CP22: =_xlfn.XLOOKUP($A22, 'Project Commitment'!$A:$A, 'Project Commitment'!W:W, "") -> 0 | CQ22: =_xlfn.XLOOKUP($A22, 'Project Commitment'!$A:$A, 'Project Commitment'!X:X, "") -> -1002 | CR22: =_xlfn.XLOOKUP($A22, 'Project Commitment'!$A:$A, 'Project Commitment'!Y:Y, "") -> #VALUE! | CS22: =_xlfn.XLOOKUP($A22, 'Project Commitment'!$A:$A, 'Project Commitment'!Z:Z, "") -> -487 | CT22: =_xlfn.XLOOKUP($A22, 'Project Commitment'!$A:$A, 'Project Commitment'!AA:AA, "") -> 0 | CU22: =_xlfn.XLOOKUP($A22, 'Project Commitment'!$A:$A, 'Project Commitment'!AB:AB, "") -> #VALUE! | DA22: =IF(C22="", "Meeting Minutes cannot be blank", "") | DF22: =_xlfn.IFS(AND(J22="Not Applicable", H22<>""), "No date is needed if Column 10 is Not Applicable",J22= "Not Applicable", "", H22="",DF$7&" cannot be blank", $AC22="", "", H22>$AC22, DF$7&" must preceed construction start date.", TRUE, "") | DG22: =_xlfn.IFS(I22="", DG$7&" cannot be left blank.",H22="", "", AND( H22 < TODAY(), I22="Not Yet Known"), "After the submission date, the pre-tender package type must be selected.", TRUE, "") | DI22: =EW22 | DJ22: =_xlfn.IFS(AND(N22="Not Applicable", L22<>""), "No date is needed if Column 14 is Not Applicable",N22= "Not Applicable", "", L22="",DJ$7&" cannot be blank", $AC22="", "", L22>$AC22, DJ$7&" must preceed construction start date.", TRUE, "") | DK22: =_xlfn.IFS(M22="", DK$7&" cannot be left blank.",L22="", "", AND( L22 < TODAY(), M22="Not Yet Known"), "After the submission date, the pre-tender package type must be selected.", TRUE, "") | DM22: =FA22 | DN22: =FE22 | DO22: =FI22 | DP22: =IF(R22="", DP$7&" cannot be blank", "") | DQ22: =_xlfn.IFS(S22="",DQ$7&" cannot be blank",AND(J22<>"Not yet submitted/reviewed",S22>TODAY()),DQ$7&" cannot be in the future if project is ready for a pre-tender package.",TRUE,"") | DR22: =_xlfn.IFS(CE22=0, "", T22="",DR$7&" cannot be blank if project includes child care.", AND(J22="Not Applicable",T22>TODAY()), "Projects under construction must have a "&DR$7, J22="Not Applicable", "", T22<I22, T18&" must preceed pre-tender package submission date",TRUE, "") | DS22: =_xlfn.IFS(U22="",DS$7&" cannot be blank", $AC22="", "", U22>$AC22, DS$7&" must preceed construction start date.", TRUE, "") -> Initial Site Plan Submission Date cannot be blank | DT22: =_xlfn.IFS(W22<>"", "", V22="",DT$7&" cannot be blank", $AC22="", "", V22>$AC22, DT$7&" must preceed construction start date.", TRUE, "") -> Site Plan Approval Date cannot be blank | DV22: =_xlfn.IFS(Y22<>"", "", X22="",DV$7&" cannot be blank", $AC22="", "", X22>$AC22, DV$7&" must preceed construction start date.", TRUE, "") -> Build Permit Obtained Date cannot be blank | DX22: =_xlfn.IFS(Z22="",DX$7&" cannot be blank", $AC22="", "", Z22>$AC22, DX$7&" must preceed construction start date.", TRUE, "") | DY22: =_xlfn.IFS(AA22="",DY$7&" cannot be blank", $AC22="", "", AA22>$AC22, DY$7&" must preceed construction start date.", TRUE, "") | DZ22: =_xlfn.IFS(AB22="",DZ$7&" cannot be blank", $AC22="", "", AB22>$AC22, DZ$7&" must preceed construction start date.", TRUE, "") | EA22: =_xlfn.IFS(AD22<>"", "", AC22="",EA$7&" cannot be blank", $AG22="", "", AC22>EDATE($AG22,-12), EA$7&" must preceed school opening date by more than 12 months.", TRUE, "") | EC22: =_xlfn.IFS(AF22<>"", "", AE22="",EC$7&" cannot be blank", $AG22="", "", AE22>EDATE($AG22,-1), EC$7&" must preceed school opening date by more than one month.", TRUE, "") -> Substantial Completion Date must preceed school opening date by more than one month. | EE22: =_xlfn.IFS(AK22="", "", AG22="",EE$7&" cannot be blank",AH22<>"", "", $AG22="", "", AG22>=EDATE($AK22,-11), EE$7&" must preceed financial close date by at least 12 months.", TRUE, "") | EG22: =_xlfn.IFS(CE22=0, "", AI22="",EG$7&" cannot be blank",$AK22="", "",AJ22<>"", "", AI22>=EDATE($AK22,0), EG$7&" must preceed financial close date.", TRUE, "") | EI22: =_xlfn.IFS( AK22="",EI$7&" cannot be blank", TRUE, "") | EO22: =_xlfn.IFS(AQ22="", "Basis of Cost Estimate cannot be blank", AND(AC22<TODAY(), AQ22<>"Based on Tender Results"), "Contract awarded date suggests estimate should be based on tender results", AND(H22<TODAY(), AQ22<>"Based on Class A or B Cost Report"), "If project has already come in for a pre-tender budget, they must have a class A or B cost estimate.", TRUE, "") -> If project has already come in for a pre-tender budget, they must have a class A or B cost estimate. | EP22: =_xlfn.IFS(OR(AM22=0, AM22=""), "", AR22="", EP$7&" cannot be blank.", TRUE, "") -> Estimated Cost - Construction Project cannot be blank. | EQ22: =_xlfn.IFS(OR(AN22=0, AN22=""), "", AS22="", EQ$7&" cannot be blank.", TRUE, "") -> Estimated Cost - Land cannot be blank. | ER22: =_xlfn.IFS(OR(AO22=0, AO22=""), "", AT22="", ER$7&" cannot be blank.", TRUE, "") | ES22: =_xlfn.IFS(OR(AP22=0, AP22=""), "", AU22="", ES$7&" cannot be blank.", TRUE, "") | EW22: =_xlfn.IFS(EX22<>"", EX22, EY22<>"", EY22, EZ22<>"", EZ22, TRUE, "") | EX22: =IF(J22="MISSING", "This package is missing!", "") | EY22: =IF(K22="", "Confirm you reviewed the pretender checkin documents", "") | EZ22: =IF(AND(K22="Not yet submitted/reviewed", J22<>"Not yet submitted/reviewed"), "Pretender package submitted; col 9 cann't indicate otherwise.", "") | FA22: =_xlfn.IFS(FB22<>"", FB22, FC22<>"", FC22, FD22<>"", FD22, TRUE, "") | FB22: =IF(N22="MISSING", "The post tender package is missing!", "") | FC22: =IF(O22="", "Confirm you reviewed the post tender check-in documents", "") | FD22: =IF(AND(O22="Not yet submitted/reviewed", N22<>"Not yet submitted/reviewed"), "Post-tender package submitted; col 9 cann't indicate otherwise.", "") | FE22: =_xlfn.IFS(FF22<>"", FF22, FG22<>"", FG22, TRUE, FH22) | FF22: =IF(P22<>"", "", "Site Ownership Status cannot be blank") | FG22: =_xlfn.IFS(AND(Q22="", OR(P22="Site Purchased Prior to Capital Approval", P22="Site Purchased")), "", AND(OR(P22="Site Purchased Prior to Capital Approval", P22="Site Purchased"), Q22>TODAY()), "Site purchase date is in the future, but site ownership status indicates site is already purchaseed", TRUE, "") | FH22: =IF(AND(AND(P22<>"Site Purchased Prior to Capital Approval", P22<>"Site Purchased"), Q22<=TODAY()), "Site purchase date is in the past, but site ownership status indicates site has not yet been purchaseed", "") | FI22: =_xlfn.IFS(FJ22<>"", FJ22, FK22<>"", FK22, TRUE,FL22 ) | FJ22: =IF(AND(P22<>"Not Applicable",Q22=""),"Site Purchased Date cannot be blank","") | FK22: =FE22 | FL22: =_xlfn.IFS(Q22="", "", U22="", "", Q22>U22, "Site Purchase Date must preceed Site Plan Submission.", TRUE, "")
A23: 40-159 | B23: Bishop Allen Academy Catholic Secondary School | C23: ATP Received December 12, 2025. | D23: New Construction | E23: Accommodation Pressure | F23: In Progress | G23: =_xlfn.IFS($C$3>AK23, "Complete", $C$3>AG23, "Open", $C$3>AC23, "Under Construction", TRUE, "Planning") -> Planning | H23: 46003 | I23: Additional Funding Required | J23: Not yet submitted/reviewed | K23: No | L23: 46233 | M23: Not Yet Known | N23: Not yet submitted/reviewed | O23: Not yet submitted/reviewed | P23: Not Applicable | R23: >80% Complete | S23: 44274 | V23: 45992 | AC23: 46266 | AE23: 46966 | AG23: 47003 | AK23: 47368 | AL23: =SUM(AM23:AP23) -> 36013876 | AM23: 36013876 | AQ23: Based on Class A or B Cost Report | BD23: Cost Estimate was received September22. Board will then review the costs, to find savings. Board recieved a revised Cost Estimate. Board to prepare ATP for submission, likely after the Scarlett Heights ATP submission (targetting November 2025). The submission will be submitted before the end of the year. | BE23: Cost Estimate was received September22. Board will then review the costs, to find savings. Board to prepare ATP for submission, likely after the Scarlett Heights ATP submission (targetting November 2025). The submission will be submitted before the end of the year. | BF23: Cost Estimate was received September22. Board will then review the costs, to find savings. | BG23: Cost Esimate to be received in September. Board will then review the costs. | CD23: =IF(AND(Q23="", A23<>"", P23<>"Site Purchased Prior to Capital Approval"), 1, 0) -> 1 | CE23: 0 | CF23: =_xlfn.XLOOKUP($A23, 'Project Commitment'!$A:$A, 'Project Commitment'!M:M, "") -> 0 | CG23: =_xlfn.XLOOKUP($A23, 'Project Commitment'!$A:$A, 'Project Commitment'!N:N, "") -> 0 | CH23: =_xlfn.XLOOKUP($A23, 'Project Commitment'!$A:$A, 'Project Commitment'!O:O, "") -> 0 | CI23: =_xlfn.XLOOKUP($A23, 'Project Commitment'!$A:$A, 'Project Commitment'!P:P, "") -> 0 | CJ23: =_xlfn.XLOOKUP($A23, 'Project Commitment'!$A:$A, 'Project Commitment'!Q:Q, "") -> 0 | CK23: =_xlfn.XLOOKUP($A23, 'Project Commitment'!$A:$A, 'Project Commitment'!R:R, "") -> 0 | CL23: =_xlfn.XLOOKUP($A23, 'Project Commitment'!$A:$A, 'Project Commitment'!S:S, "") -> #VALUE! | CM23: =_xlfn.XLOOKUP($A23, 'Project Commitment'!$A:$A, 'Project Commitment'!T:T, "") -> 0 | CN23: =_xlfn.XLOOKUP($A23, 'Project Commitment'!$A:$A, 'Project Commitment'!U:U, "") -> #VALUE! | CO23: =_xlfn.XLOOKUP($A23, 'Project Commitment'!$A:$A, 'Project Commitment'!V:V, "") -> #VALUE! | CP23: =_xlfn.XLOOKUP($A23, 'Project Commitment'!$A:$A, 'Project Commitment'!W:W, "") -> 0 | CQ23: =_xlfn.XLOOKUP($A23, 'Project Commitment'!$A:$A, 'Project Commitment'!X:X, "") -> -92 | CR23: =_xlfn.XLOOKUP($A23, 'Project Commitment'!$A:$A, 'Project Commitment'!Y:Y, "") -> #VALUE! | CS23: =_xlfn.XLOOKUP($A23, 'Project Commitment'!$A:$A, 'Project Commitment'!Z:Z, "") -> 359 | CT23: =_xlfn.XLOOKUP($A23, 'Project Commitment'!$A:$A, 'Project Commitment'!AA:AA, "") -> 0 | CU23: =_xlfn.XLOOKUP($A23, 'Project Commitment'!$A:$A, 'Project Commitment'!AB:AB, "") -> #VALUE! | DA23: =IF(C23="", "Meeting Minutes cannot be blank", "") | DF23: =_xlfn.IFS(AND(J23="Not Applicable", H23<>""), "No date is needed if Column 10 is Not Applicable",J23= "Not Applicable", "", H23="",DF$7&" cannot be blank", $AC23="", "", H23>$AC23, DF$7&" must preceed construction start date.", TRUE, "") | DG23: =_xlfn.IFS(I23="", DG$7&" cannot be left blank.",H23="", "", AND( H23 < TODAY(), I23="Not Yet Known"), "After the submission date, the pre-tender package type must be selected.", TRUE, "") | DI23: =EW23 | DJ23: =_xlfn.IFS(AND(N23="Not Applicable", L23<>""), "No date is needed if Column 14 is Not Applicable",N23= "Not Applicable", "", L23="",DJ$7&" cannot be blank", $AC23="", "", L23>$AC23, DJ$7&" must preceed construction start date.", TRUE, "") | DK23: =_xlfn.IFS(M23="", DK$7&" cannot be left blank.",L23="", "", AND( L23 < TODAY(), M23="Not Yet Known"), "After the submission date, the pre-tender package type must be selected.", TRUE, "") | DM23: =FA23 | DN23: =FE23 | DO23: =FI23 | DP23: =IF(R23="", DP$7&" cannot be blank", "") | DQ23: =_xlfn.IFS(S23="",DQ$7&" cannot be blank",AND(J23<>"Not yet submitted/reviewed",S23>TODAY()),DQ$7&" cannot be in the future if project is ready for a pre-tender package.",TRUE,"") | DR23: =_xlfn.IFS(CE23=0, "", T23="",DR$7&" cannot be blank if project includes child care.", AND(J23="Not Applicable",T23>TODAY()), "Projects under construction must have a "&DR$7, J23="Not Applicable", "", T23<I23, T19&" must preceed pre-tender package submission date",TRUE, "") | DS23: =_xlfn.IFS(U23="",DS$7&" cannot be blank", $AC23="", "", U23>$AC23, DS$7&" must preceed construction start date.", TRUE, "") -> Initial Site Plan Submission Date cannot be blank | DT23: =_xlfn.IFS(W23<>"", "", V23="",DT$7&" cannot be blank", $AC23="", "", V23>$AC23, DT$7&" must preceed construction start date.", TRUE, "") | DV23: =_xlfn.IFS(Y23<>"", "", X23="",DV$7&" cannot be blank", $AC23="", "", X23>$AC23, DV$7&" must preceed construction start date.", TRUE, "") -> Build Permit Obtained Date cannot be blank | DX23: =_xlfn.IFS(Z23="",DX$7&" cannot be blank", $AC23="", "", Z23>$AC23, DX$7&" must preceed construction start date.", TRUE, "") -> Tender Issued Date cannot be blank | DY23: =_xlfn.IFS(AA23="",DY$7&" cannot be blank", $AC23="", "", AA23>$AC23, DY$7&" must preceed construction start date.", TRUE, "") -> Tender Closed Date cannot be blank | DZ23: =_xlfn.IFS(AB23="",DZ$7&" cannot be blank", $AC23="", "", AB23>$AC23, DZ$7&" must preceed construction start date.", TRUE, "") -> Contract Awarded Date cannot be blank | EA23: =_xlfn.IFS(AD23<>"", "", AC23="",EA$7&" cannot be blank", $AG23="", "", AC23>EDATE($AG23,-12), EA$7&" must preceed school opening date by more than 12 months.", TRUE, "") | EC23: =_xlfn.IFS(AF23<>"", "", AE23="",EC$7&" cannot be blank", $AG23="", "", AE23>EDATE($AG23,-1), EC$7&" must preceed school opening date by more than one month.", TRUE, "") | EE23: =_xlfn.IFS(AK23="", "", AG23="",EE$7&" cannot be blank",AH23<>"", "", $AG23="", "", AG23>=EDATE($AK23,-11), EE$7&" must preceed financial close date by at least 12 months.", TRUE, "") | EG23: =_xlfn.IFS(CE23=0, "", AI23="",EG$7&" cannot be blank",$AK23="", "",AJ23<>"", "", AI23>=EDATE($AK23,0), EG$7&" must preceed financial close date.", TRUE, "") | EI23: =_xlfn.IFS( AK23="",EI$7&" cannot be blank", TRUE, "") | EO23: =_xlfn.IFS(AQ23="", "Basis of Cost Estimate cannot be blank", AND(AC23<TODAY(), AQ23<>"Based on Tender Results"), "Contract awarded date suggests estimate should be based on tender results", AND(H23<TODAY(), AQ23<>"Based on Class A or B Cost Report"), "If project has already come in for a pre-tender budget, they must have a class A or B cost estimate.", TRUE, "") | EP23: =_xlfn.IFS(OR(AM23=0, AM23=""), "", AR23="", EP$7&" cannot be blank.", TRUE, "") -> Estimated Cost - Construction Project cannot be blank. | EQ23: =_xlfn.IFS(OR(AN23=0, AN23=""), "", AS23="", EQ$7&" cannot be blank.", TRUE, "") | ER23: =_xlfn.IFS(OR(AO23=0, AO23=""), "", AT23="", ER$7&" cannot be blank.", TRUE, "") | ES23: =_xlfn.IFS(OR(AP23=0, AP23=""), "", AU23="", ES$7&" cannot be blank.", TRUE, "") | EW23: =_xlfn.IFS(EX23<>"", EX23, EY23<>"", EY23, EZ23<>"", EZ23, TRUE, "") | EX23: =IF(J23="MISSING", "This package is missing!", "") | EY23: =IF(K23="", "Confirm you reviewed the pretender checkin documents", "") | EZ23: =IF(AND(K23="Not yet submitted/reviewed", J23<>"Not yet submitted/reviewed"), "Pretender package submitted; col 9 cann't indicate otherwise.", "") | FA23: =_xlfn.IFS(FB23<>"", FB23, FC23<>"", FC23, FD23<>"", FD23, TRUE, "") | FB23: =IF(N23="MISSING", "The post tender package is missing!", "") | FC23: =IF(O23="", "Confirm you reviewed the post tender check-in documents", "") | FD23: =IF(AND(O23="Not yet submitted/reviewed", N23<>"Not yet submitted/reviewed"), "Post-tender package submitted; col 9 cann't indicate otherwise.", "") | FE23: =_xlfn.IFS(FF23<>"", FF23, FG23<>"", FG23, TRUE, FH23) | FF23: =IF(P23<>"", "", "Site Ownership Status cannot be blank") | FG23: =_xlfn.IFS(AND(Q23="", OR(P23="Site Purchased Prior to Capital Approval", P23="Site Purchased")), "", AND(OR(P23="Site Purchased Prior to Capital Approval", P23="Site Purchased"), Q23>TODAY()), "Site purchase date is in the future, but site ownership status indicates site is already purchaseed", TRUE, "") | FH23: =IF(AND(AND(P23<>"Site Purchased Prior to Capital Approval", P23<>"Site Purchased"), Q23<=TODAY()), "Site purchase date is in the past, but site ownership status indicates site has not yet been purchaseed", "") | FI23: =_xlfn.IFS(FJ23<>"", FJ23, FK23<>"", FK23, TRUE,FL23 ) | FJ23: =IF(AND(P23<>"Not Applicable",Q23=""),"Site Purchased Date cannot be blank","") | FK23: =FE23 | FL23: =_xlfn.IFS(Q23="", "", U23="", "", Q23>U23, "Site Purchase Date must preceed Site Plan Submission.", TRUE, "")
A24: 40-160 | B24: Loretto Abbey Catholic Secondary School | C24: The project tender is currently open and scheduled to close on January 29, 2026. The Notice of Approval to Construct (NOAC) has been issued. All conditions related to SPA have been cleared, and the schol board anticipates final SPA approval prior to the start of construction. Demolition is substantially complete, and the associated holdback has been released. | D24: Addition | E24: Accommodation Pressure | F24: In Progress | G24: =_xlfn.IFS($C$3>AK24, "Complete", $C$3>AG24, "Open", $C$3>AC24, "Under Construction", TRUE, "Planning") -> Planning | H24: 45565 | I24: Additional Funding Required | J24: 2025-09-04 (Additional Funding) | K24: Yes | L24: 46081 | M24: Not Yet Known | N24: MISSING | O24: Not Applicable | P24: Site Purchased Prior to Capital Approval | Q24: 40603 | R24: >80% Complete | S24: 45566 | V24: 46054 | AA24: 46051 | AC24: 46113 | AE24: 46971 | AG24: 47004 | AK24: 47369 | AL24: =SUM(AM24:AP24) -> 67917263 | AM24: 66581755 | AO24: 1335508 | AQ24: Based on Class A or B Cost Report | BD24: NOAC and SPA - lenghtly and complex for this project. Board wants to have an SPA before construction begins. Board clearing the NOAC conditions - fulfilling. Board was anticipating October tendering, but the architect is pushing back to tender in January. They've agreed that they will aim for November tendering (tentative). Board and architect to meet October 24th to determine what items still need to be complete, and the tendering timeline. | BE24: NOAC and SPA - lenghtly and complex for this project. Board wants to have an SPA before construction begins. Board clearing the NOAC conditions - fulfilling. Board was anticipating October tendering, but the architect is pushing back to tender in January. They've agreed that they will aim for November tendering (tentative). Board and architect to meet October 24th to determine what items still need to be complete, and the tendering timeline. | BF24: NOAC and SPA - lenghtly and complex for this project. Board wants to have an SPA before construction begins. Board clearing the NOAC conditions - fulfilling. Board is reviewing the tender package, hoping to release tender in October, and awarding the tender by end of year. | BG24: NOAC and SPA - lenghtly and complex for this project. Board wants to have an SPA before construction begins. | CD24: =IF(AND(Q24="", A24<>"", P24<>"Site Purchased Prior to Capital Approval"), 1, 0) -> 0 | CE24: 0 | CF24: =_xlfn.XLOOKUP($A24, 'Project Commitment'!$A:$A, 'Project Commitment'!M:M, "") -> 0 | CG24: =_xlfn.XLOOKUP($A24, 'Project Commitment'!$A:$A, 'Project Commitment'!N:N, "") -> 0 | CH24: =_xlfn.XLOOKUP($A24, 'Project Commitment'!$A:$A, 'Project Commitment'!O:O, "") -> 0 | CI24: =_xlfn.XLOOKUP($A24, 'Project Commitment'!$A:$A, 'Project Commitment'!P:P, "") -> 0 | CJ24: =_xlfn.XLOOKUP($A24, 'Project Commitment'!$A:$A, 'Project Commitment'!Q:Q, "") -> -408 | CK24: =_xlfn.XLOOKUP($A24, 'Project Commitment'!$A:$A, 'Project Commitment'!R:R, "") -> 0 | CL24: =_xlfn.XLOOKUP($A24, 'Project Commitment'!$A:$A, 'Project Commitment'!S:S, "") -> #VALUE! | CM24: =_xlfn.XLOOKUP($A24, 'Project Commitment'!$A:$A, 'Project Commitment'!T:T, "") -> 0 | CN24: =_xlfn.XLOOKUP($A24, 'Project Commitment'!$A:$A, 'Project Commitment'!U:U, "") -> #VALUE! | CO24: =_xlfn.XLOOKUP($A24, 'Project Commitment'!$A:$A, 'Project Commitment'!V:V, "") -> #VALUE! | CP24: =_xlfn.XLOOKUP($A24, 'Project Commitment'!$A:$A, 'Project Commitment'!W:W, "") -> 0 | CQ24: =_xlfn.XLOOKUP($A24, 'Project Commitment'!$A:$A, 'Project Commitment'!X:X, "") -> -365 | CR24: =_xlfn.XLOOKUP($A24, 'Project Commitment'!$A:$A, 'Project Commitment'!Y:Y, "") -> #VALUE! | CS24: =_xlfn.XLOOKUP($A24, 'Project Commitment'!$A:$A, 'Project Commitment'!Z:Z, "") -> -738 | CT24: =_xlfn.XLOOKUP($A24, 'Project Commitment'!$A:$A, 'Project Commitment'!AA:AA, "") -> 0 | CU24: =_xlfn.XLOOKUP($A24, 'Project Commitment'!$A:$A, 'Project Commitment'!AB:AB, "") -> #VALUE! | DA24: =IF(C24="", "Meeting Minutes cannot be blank", "") | DF24: =_xlfn.IFS(AND(J24="Not Applicable", H24<>""), "No date is needed if Column 10 is Not Applicable",J24= "Not Applicable", "", H24="",DF$7&" cannot be blank", $AC24="", "", H24>$AC24, DF$7&" must preceed construction start date.", TRUE, "") | DG24: =_xlfn.IFS(I24="", DG$7&" cannot be left blank.",H24="", "", AND( H24 < TODAY(), I24="Not Yet Known"), "After the submission date, the pre-tender package type must be selected.", TRUE, "") | DI24: =EW24 | DJ24: =_xlfn.IFS(AND(N24="Not Applicable", L24<>""), "No date is needed if Column 14 is Not Applicable",N24= "Not Applicable", "", L24="",DJ$7&" cannot be blank", $AC24="", "", L24>$AC24, DJ$7&" must preceed construction start date.", TRUE, "") | DK24: =_xlfn.IFS(M24="", DK$7&" cannot be left blank.",L24="", "", AND( L24 < TODAY(), M24="Not Yet Known"), "After the submission date, the pre-tender package type must be selected.", TRUE, "") | DM24: =FA24 -> The post tender package is missing! | DN24: =FE24 | DO24: =FI24 | DP24: =IF(R24="", DP$7&" cannot be blank", "") | DQ24: =_xlfn.IFS(S24="",DQ$7&" cannot be blank",AND(J24<>"Not yet submitted/reviewed",S24>TODAY()),DQ$7&" cannot be in the future if project is ready for a pre-tender package.",TRUE,"") | DR24: =_xlfn.IFS(CE24=0, "", T24="",DR$7&" cannot be blank if project includes child care.", AND(J24="Not Applicable",T24>TODAY()), "Projects under construction must have a "&DR$7, J24="Not Applicable", "", T24<I24, T20&" must preceed pre-tender package submission date",TRUE, "") | DS24: =_xlfn.IFS(U24="",DS$7&" cannot be blank", $AC24="", "", U24>$AC24, DS$7&" must preceed construction start date.", TRUE, "") -> Initial Site Plan Submission Date cannot be blank | DT24: =_xlfn.IFS(W24<>"", "", V24="",DT$7&" cannot be blank", $AC24="", "", V24>$AC24, DT$7&" must preceed construction start date.", TRUE, "") | DV24: =_xlfn.IFS(Y24<>"", "", X24="",DV$7&" cannot be blank", $AC24="", "", X24>$AC24, DV$7&" must preceed construction start date.", TRUE, "") -> Build Permit Obtained Date cannot be blank | DX24: =_xlfn.IFS(Z24="",DX$7&" cannot be blank", $AC24="", "", Z24>$AC24, DX$7&" must preceed construction start date.", TRUE, "") -> Tender Issued Date cannot be blank | DY24: =_xlfn.IFS(AA24="",DY$7&" cannot be blank", $AC24="", "", AA24>$AC24, DY$7&" must preceed construction start date.", TRUE, "") | DZ24: =_xlfn.IFS(AB24="",DZ$7&" cannot be blank", $AC24="", "", AB24>$AC24, DZ$7&" must preceed construction start date.", TRUE, "") -> Contract Awarded Date cannot be blank | EA24: =_xlfn.IFS(AD24<>"", "", AC24="",EA$7&" cannot be blank", $AG24="", "", AC24>EDATE($AG24,-12), EA$7&" must preceed school opening date by more than 12 months.", TRUE, "") | EC24: =_xlfn.IFS(AF24<>"", "", AE24="",EC$7&" cannot be blank", $AG24="", "", AE24>EDATE($AG24,-1), EC$7&" must preceed school opening date by more than one month.", TRUE, "") | EE24: =_xlfn.IFS(AK24="", "", AG24="",EE$7&" cannot be blank",AH24<>"", "", $AG24="", "", AG24>=EDATE($AK24,-11), EE$7&" must preceed financial close date by at least 12 months.", TRUE, "") | EG24: =_xlfn.IFS(CE24=0, "", AI24="",EG$7&" cannot be blank",$AK24="", "",AJ24<>"", "", AI24>=EDATE($AK24,0), EG$7&" must preceed financial close date.", TRUE, "") | EI24: =_xlfn.IFS( AK24="",EI$7&" cannot be blank", TRUE, "") | EO24: =_xlfn.IFS(AQ24="", "Basis of Cost Estimate cannot be blank", AND(AC24<TODAY(), AQ24<>"Based on Tender Results"), "Contract awarded date suggests estimate should be based on tender results", AND(H24<TODAY(), AQ24<>"Based on Class A or B Cost Report"), "If project has already come in for a pre-tender budget, they must have a class A or B cost estimate.", TRUE, "") | EP24: =_xlfn.IFS(OR(AM24=0, AM24=""), "", AR24="", EP$7&" cannot be blank.", TRUE, "") -> Estimated Cost - Construction Project cannot be blank. | EQ24: =_xlfn.IFS(OR(AN24=0, AN24=""), "", AS24="", EQ$7&" cannot be blank.", TRUE, "") | ER24: =_xlfn.IFS(OR(AO24=0, AO24=""), "", AT24="", ER$7&" cannot be blank.", TRUE, "") -> Estimated Cost - Demolition cannot be blank. | ES24: =_xlfn.IFS(OR(AP24=0, AP24=""), "", AU24="", ES$7&" cannot be blank.", TRUE, "") | EW24: =_xlfn.IFS(EX24<>"", EX24, EY24<>"", EY24, EZ24<>"", EZ24, TRUE, "") | EX24: =IF(J24="MISSING", "This package is missing!", "") | EY24: =IF(K24="", "Confirm you reviewed the pretender checkin documents", "") | EZ24: =IF(AND(K24="Not yet submitted/reviewed", J24<>"Not yet submitted/reviewed"), "Pretender package submitted; col 9 cann't indicate otherwise.", "") | FA24: =_xlfn.IFS(FB24<>"", FB24, FC24<>"", FC24, FD24<>"", FD24, TRUE, "") -> The post tender package is missing! | FB24: =IF(N24="MISSING", "The post tender package is missing!", "") -> The post tender package is missing! | FC24: =IF(O24="", "Confirm you reviewed the post tender check-in documents", "") | FD24: =IF(AND(O24="Not yet submitted/reviewed", N24<>"Not yet submitted/reviewed"), "Post-tender package submitted; col 9 cann't indicate otherwise.", "") | FE24: =_xlfn.IFS(FF24<>"", FF24, FG24<>"", FG24, TRUE, FH24) | FF24: =IF(P24<>"", "", "Site Ownership Status cannot be blank") | FG24: =_xlfn.IFS(AND(Q24="", OR(P24="Site Purchased Prior to Capital Approval", P24="Site Purchased")), "", AND(OR(P24="Site Purchased Prior to Capital Approval", P24="Site Purchased"), Q24>TODAY()), "Site purchase date is in the future, but site ownership status indicates site is already purchaseed", TRUE, "") | FH24: =IF(AND(AND(P24<>"Site Purchased Prior to Capital Approval", P24<>"Site Purchased"), Q24<=TODAY()), "Site purchase date is in the past, but site ownership status indicates site has not yet been purchaseed", "") | FI24: =_xlfn.IFS(FJ24<>"", FJ24, FK24<>"", FK24, TRUE,FL24 ) | FJ24: =IF(AND(P24<>"Not Applicable",Q24=""),"Site Purchased Date cannot be blank","") | FK24: =FE24 | FL24: =_xlfn.IFS(Q24="", "", U24="", "", Q24>U24, "Site Purchase Date must preceed Site Plan Submission.", TRUE, "")
A25: 40-167 | B25: St. Elizabeth Catholic Elementary School | C25: Board has submitted a request for an additional $29M in funding from the ministry. The review is currently underway. NOAC complete. SPA almost complete, the city is preparing the SPA documents, board paid letters of credit. | D25: New Construction | E25: Accommodation Pressure | F25: In Progress | G25: =_xlfn.IFS($C$3>AK25, "Complete", $C$3>AG25, "Open", $C$3>AC25, "Under Construction", TRUE, "Planning") -> Planning | H25: 45965 | I25: Additional Funding Required | J25: Not yet submitted/reviewed | K25: Yes | L25: 46188 | M25: Not Yet Known | N25: Not yet submitted/reviewed | O25: Not yet submitted/reviewed | P25: Not Applicable | R25: >80% Complete | S25: 44797 | T25: 45783 | U25: 45883 | V25: 45898 | X25: 46006 | Z25: 46113 | AA25: 46143 | AB25: 46193 | AC25: 46205 | AE25: 46940 | AG25: 47003 | AI25: 47003 | AK25: 47391 | AL25: =SUM(AM25:AP25) -> 19366938 | AM25: 19366938 | AQ25: Based on estimate of $/sq ft | BD25: ATP - Submitted to ministry. Additional and missing information has been shared with the ministry early November. The package can now be drafted. The cost per square foot $482, project is an alternative build --u/g parking, third storey, roof top play area, artificial turf etc. These elements would increase the cost per sq foot. Board is working with city on NOAC (Notice of Approval Conditions) approval. The NOAC was recieved in August 2025, and revisions made October 2025.Building Permit was submitted to city in August 2025 and anticipates the Building Permit to be approved December 15, 2025. Once NOAC, Building Permit and ATP are approved, the board will move ahead with tender package, and is hopeful this will happen early spring. At this point, the board will formally announce to the school community of the holding school for St. Elizabeth, which will be Christ the King on Kipling and Lakeshore. | BE25: Board submitted ATP. | BF25: Board submitted ATP. | CD25: =IF(AND(Q25="", A25<>"", P25<>"Site Purchased Prior to Capital Approval"), 1, 0) -> 1 | CE25: 88 | CF25: =_xlfn.XLOOKUP($A25, 'Project Commitment'!$A:$A, 'Project Commitment'!M:M, "") -> 0 | CG25: =_xlfn.XLOOKUP($A25, 'Project Commitment'!$A:$A, 'Project Commitment'!N:N, "") -> 0 | CH25: =_xlfn.XLOOKUP($A25, 'Project Commitment'!$A:$A, 'Project Commitment'!O:O, "") -> 0 | CI25: =_xlfn.XLOOKUP($A25, 'Project Commitment'!$A:$A, 'Project Commitment'!P:P, "") -> 0 | CJ25: =_xlfn.XLOOKUP($A25, 'Project Commitment'!$A:$A, 'Project Commitment'!Q:Q, "") -> 0 | CK25: =_xlfn.XLOOKUP($A25, 'Project Commitment'!$A:$A, 'Project Commitment'!R:R, "") -> 0 | CL25: =_xlfn.XLOOKUP($A25, 'Project Commitment'!$A:$A, 'Project Commitment'!S:S, "") -> -188 | CM25: =_xlfn.XLOOKUP($A25, 'Project Commitment'!$A:$A, 'Project Commitment'!T:T, "") -> 0 | CN25: =_xlfn.XLOOKUP($A25, 'Project Commitment'!$A:$A, 'Project Commitment'!U:U, "") -> -182 | CO25: =_xlfn.XLOOKUP($A25, 'Project Commitment'!$A:$A, 'Project Commitment'!V:V, "") -> -199 | CP25: =_xlfn.XLOOKUP($A25, 'Project Commitment'!$A:$A, 'Project Commitment'!W:W, "") -> 0 | CQ25: =_xlfn.XLOOKUP($A25, 'Project Commitment'!$A:$A, 'Project Commitment'!X:X, "") -> -182 | CR25: =_xlfn.XLOOKUP($A25, 'Project Commitment'!$A:$A, 'Project Commitment'!Y:Y, "") -> -6 | CS25: =_xlfn.XLOOKUP($A25, 'Project Commitment'!$A:$A, 'Project Commitment'!Z:Z, "") -> -3 | CT25: =_xlfn.XLOOKUP($A25, 'Project Commitment'!$A:$A, 'Project Commitment'!AA:AA, "") -> 0 | CU25: =_xlfn.XLOOKUP($A25, 'Project Commitment'!$A:$A, 'Project Commitment'!AB:AB, "") -> -26 | DA25: =IF(C25="", "Meeting Minutes cannot be blank", "") | DF25: =_xlfn.IFS(AND(J25="Not Applicable", H25<>""), "No date is needed if Column 10 is Not Applicable",J25= "Not Applicable", "", H25="",DF$7&" cannot be blank", $AC25="", "", H25>$AC25, DF$7&" must preceed construction start date.", TRUE, "") | DG25: =_xlfn.IFS(I25="", DG$7&" cannot be left blank.",H25="", "", AND( H25 < TODAY(), I25="Not Yet Known"), "After the submission date, the pre-tender package type must be selected.", TRUE, "") | DI25: =EW25 | DJ25: =_xlfn.IFS(AND(N25="Not Applicable", L25<>""), "No date is needed if Column 14 is Not Applicable",N25= "Not Applicable", "", L25="",DJ$7&" cannot be blank", $AC25="", "", L25>$AC25, DJ$7&" must preceed construction start date.", TRUE, "") | DK25: =_xlfn.IFS(M25="", DK$7&" cannot be left blank.",L25="", "", AND( L25 < TODAY(), M25="Not Yet Known"), "After the submission date, the pre-tender package type must be selected.", TRUE, "") | DM25: =FA25 | DN25: =FE25 | DO25: =FI25 | DP25: =IF(R25="", DP$7&" cannot be blank", "") | DQ25: =_xlfn.IFS(S25="",DQ$7&" cannot be blank",AND(J25<>"Not yet submitted/reviewed",S25>TODAY()),DQ$7&" cannot be in the future if project is ready for a pre-tender package.",TRUE,"") | DR25: =_xlfn.IFS(CE25=0, "", T25="",DR$7&" cannot be blank if project includes child care.", AND(J25="Not Applicable",T25>TODAY()), "Projects under construction must have a "&DR$7, J25="Not Applicable", "", T25<I25, T21&" must preceed pre-tender package submission date",TRUE, "") -> 45244 must preceed pre-tender package submission date | DS25: =_xlfn.IFS(U25="",DS$7&" cannot be blank", $AC25="", "", U25>$AC25, DS$7&" must preceed construction start date.", TRUE, "") | DT25: =_xlfn.IFS(W25<>"", "", V25="",DT$7&" cannot be blank", $AC25="", "", V25>$AC25, DT$7&" must preceed construction start date.", TRUE, "") | DV25: =_xlfn.IFS(Y25<>"", "", X25="",DV$7&" cannot be blank", $AC25="", "", X25>$AC25, DV$7&" must preceed construction start date.", TRUE, "") | DX25: =_xlfn.IFS(Z25="",DX$7&" cannot be blank", $AC25="", "", Z25>$AC25, DX$7&" must preceed construction start date.", TRUE, "") | DY25: =_xlfn.IFS(AA25="",DY$7&" cannot be blank", $AC25="", "", AA25>$AC25, DY$7&" must preceed construction start date.", TRUE, "") | DZ25: =_xlfn.IFS(AB25="",DZ$7&" cannot be blank", $AC25="", "", AB25>$AC25, DZ$7&" must preceed construction start date.", TRUE, "") | EA25: =_xlfn.IFS(AD25<>"", "", AC25="",EA$7&" cannot be blank", $AG25="", "", AC25>EDATE($AG25,-12), EA$7&" must preceed school opening date by more than 12 months.", TRUE, "") | EC25: =_xlfn.IFS(AF25<>"", "", AE25="",EC$7&" cannot be blank", $AG25="", "", AE25>EDATE($AG25,-1), EC$7&" must preceed school opening date by more than one month.", TRUE, "") | EE25: =_xlfn.IFS(AK25="", "", AG25="",EE$7&" cannot be blank",AH25<>"", "", $AG25="", "", AG25>=EDATE($AK25,-11), EE$7&" must preceed financial close date by at least 12 months.", TRUE, "") | EG25: =_xlfn.IFS(CE25=0, "", AI25="",EG$7&" cannot be blank",$AK25="", "",AJ25<>"", "", AI25>=EDATE($AK25,0), EG$7&" must preceed financial close date.", TRUE, "") | EI25: =_xlfn.IFS( AK25="",EI$7&" cannot be blank", TRUE, "") | EO25: =_xlfn.IFS(AQ25="", "Basis of Cost Estimate cannot be blank", AND(AC25<TODAY(), AQ25<>"Based on Tender Results"), "Contract awarded date suggests estimate should be based on tender results", AND(H25<TODAY(), AQ25<>"Based on Class A or B Cost Report"), "If project has already come in for a pre-tender budget, they must have a class A or B cost estimate.", TRUE, "") -> If project has already come in for a pre-tender budget, they must have a class A or B cost estimate. | EP25: =_xlfn.IFS(OR(AM25=0, AM25=""), "", AR25="", EP$7&" cannot be blank.", TRUE, "") -> Estimated Cost - Construction Project cannot be blank. | EQ25: =_xlfn.IFS(OR(AN25=0, AN25=""), "", AS25="", EQ$7&" cannot be blank.", TRUE, "") | ER25: =_xlfn.IFS(OR(AO25=0, AO25=""), "", AT25="", ER$7&" cannot be blank.", TRUE, "") | ES25: =_xlfn.IFS(OR(AP25=0, AP25=""), "", AU25="", ES$7&" cannot be blank.", TRUE, "") | EW25: =_xlfn.IFS(EX25<>"", EX25, EY25<>"", EY25, EZ25<>"", EZ25, TRUE, "") | EX25: =IF(J25="MISSING", "This package is missing!", "") | EY25: =IF(K25="", "Confirm you reviewed the pretender checkin documents", "") | EZ25: =IF(AND(K25="Not yet submitted/reviewed", J25<>"Not yet submitted/reviewed"), "Pretender package submitted; col 9 cann't indicate otherwise.", "") | FA25: =_xlfn.IFS(FB25<>"", FB25, FC25<>"", FC25, FD25<>"", FD25, TRUE, "") | FB25: =IF(N25="MISSING", "The post tender package is missing!", "") | FC25: =IF(O25="", "Confirm you reviewed the post tender check-in documents", "") | FD25: =IF(AND(O25="Not yet submitted/reviewed", N25<>"Not yet submitted/reviewed"), "Post-tender package submitted; col 9 cann't indicate otherwise.", "") | FE25: =_xlfn.IFS(FF25<>"", FF25, FG25<>"", FG25, TRUE, FH25) | FF25: =IF(P25<>"", "", "Site Ownership Status cannot be blank") | FG25: =_xlfn.IFS(AND(Q25="", OR(P25="Site Purchased Prior to Capital Approval", P25="Site Purchased")), "", AND(OR(P25="Site Purchased Prior to Capital Approval", P25="Site Purchased"), Q25>TODAY()), "Site purchase date is in the future, but site ownership status indicates site is already purchaseed", TRUE, "") | FH25: =IF(AND(AND(P25<>"Site Purchased Prior to Capital Approval", P25<>"Site Purchased"), Q25<=TODAY()), "Site purchase date is in the past, but site ownership status indicates site has not yet been purchaseed", "") | FI25: =_xlfn.IFS(FJ25<>"", FJ25, FK25<>"", FK25, TRUE,FL25 ) | FJ25: =IF(AND(P25<>"Not Applicable",Q25=""),"Site Purchased Date cannot be blank","") | FK25: =FE25 | FL25: =_xlfn.IFS(Q25="", "", U25="", "", Q25>U25, "Site Purchase Date must preceed Site Plan Submission.", TRUE, "")
