Workbook

Sheet form
A1: monthly_v2.0

Sheet Instructions and Glossary
A1: Project Tracker - Instructions
B4: Purpose | C4: The Project Tracker is a tool for capital analysts to capture information about each board's projects. This data provides a line of sight into project progress and details that is critical to both analysts, other folks within the branch, and management. The data gathered here facilitates project accountability and oversight of project milestones and finances.
B6: Instructions
B7: During Meetings with the Board | C7: When analysts meet with their board to discuss projects, you should use this tool to guide your meetings and capture information. Make sure you update the meeting date on the Monthly Tracker worksheet. You'll notice that this sheet has conditional formatting that greys out the sheet when the meeting date is not set to the current day. This is done so you have a visual reminder to update this date before you talk with your boards. Taking comprehensive minutes is especially important part of your meetings with the boards. The template provides space for you to enter project-specific minutes, as well as a section for minuting any more general information discussed that might not fall under one specific project. The data is scraped regularly and then the template is regenerated with updated information. During this process, minutes are archived and relocated to the far-left side of the template (column BD), sorted with the most recent minutes closest to the left.
B8: As Needed | C8: If you need to update information at any time other than during a meeting with the board, you are free to do so and the revised information will be captured the next time the data team extracts data from worksheet. Do NOT change the meeting date during any such ad-hoc updates. You should only change the meeting dates when you actually meet with the school board.
B9: General Information & Error Checking | C9: As mentioned above, the Monthly Update worksheet contains conditional formatting that incentivizes you not to forget to enter a meeting date when you talk with the school board. You will notice that once the meeting date is has passed (i.e., it is something other than the current date), the whole sheet goes grey. This provides a visual cue for you to update the date prior to meeting with your board. The sheet also contains some automatic error checking. Cells contain errors when they are highlighted in purple. To determine the reason for the error, scroll over to columns CY to ES. This section contains the same columns as the main table; cells in this table will only contains text if there is an error. That text will describe the cause of the error in the corresponding cell in the main table.
B11: Within-Budget Acknowledgement Process
B12: Analyst Checks | C12: Confirm that the board has submitted all necessary documentation: •Class A/B cost estimate •Revised CPBF form that reflects the Class A/B cost estimate. •80% design drawings that align with the cost estimate and approved space template. •Child care floor plan approval letter (if applicable). Ensure that all documents are saved in the appropriate folder on the Share Drive. Once you have checked and confirmed all documents, send an email to the board acknowledging receipt of the pre/post tender package.
B13: Record Keeping | C13: Create a folder in the following directory: \\csc.ad.gov.on.ca\dfs$\GrpData\CBSD\CAPITAL\STRATEGY\Operations\BOARDS\^Project Commitment\Pre & Post Tender Check-In •The folder should be named using the following naming format: project id # YYYY-MM-DD Example: 12-123 # 2025-12-30 •The date in the folder name should be the date of the email acknowledging receipt of the documents and confirming the board can proceed. •Save the following in the folder you created above: o The CPBF form that reflects the pre-tender/post-tender budget. o The email to the school board (sent within 7 days of the board’s submission) confirming all documents have been submitted and that the ministry has no concerns with the board proceeding to tender/awarding the contract.
A15: Project Tracker Glossary
B17: Overview of the Worksheets within the Project Tracker
B18: Board Contacts | C18: Use this worksheet to enter the contact information for your boards. This is a central location for Capital Analysts to store this information, as well as a place where management and other analysts can go if they need this information. This is important to support coverage for analysts who are absent.
B19: Monthly Update | C19: Use this tab to memorialize meetings with the school boards. See instructions above and glossary below for more information.
B20: Basic Project Info | C20: Use this worksheet to enter the official school name, the school's location information, sign installation information, and the opening ceremony date. See below for a glossary, defining what should be entered in each column.
B21: Ad-Hoc or Potential Projects | C21: Use this worksheet to enter data about potential projects that have not yet been approved or about ad-hoc, minor projects that don't show up on the Monthly Tracker sheet.
B22: Project Commitment | C22: This sheet is for your reference only. It is not editable. It provides information about the current project commitment for the projects for this board.
A24: Glossary - Basic Project Info Tab
A26: ='Basic Project Info'!A2 -> Section 1: Project Details
A27: Col 1 | B27: =_xlfn.XLOOKUP(A27,'Basic Project Info'!$A$3:$L$3, 'Basic Project Info'!$A$4:$L$4) -> Project ID | C27: =C44 -> Automatically generated and uneditable. Each project is assigned a unique ID for tracking throughout its lifecycle. The ID displayed here is the ID for the construction portion of the project.
A28: ="Col " & ROW() -ROW($A$27)+1 -> Col 2 | B28: =_xlfn.XLOOKUP(A28,'Basic Project Info'!$A$3:$L$3, 'Basic Project Info'!$A$4:$L$4) -> Project Name | C28: Automatically generated and uneditable. This is the name assigned to the project when it is first approved. It cannot be changed and is constant throughout the project's lifecycle.
A29: ="Col " & ROW() -ROW($A$27)+1 -> Col 3 | B29: =_xlfn.XLOOKUP(A29,'Basic Project Info'!$A$3:$L$3, 'Basic Project Info'!$A$4:$L$4) -> Official School Name | C29: Use this field to update the official school name that will be used after the school is open. Please use the complete name and do not use abbreviations (e.g. use "Example Public School" instead of "Example" or "Example P.S.". If this project is an addition, this field can be completed as soon as the project is approved.
A30: ="Col " & ROW() -ROW($A$27)+1 -> Col 4 | B30: =_xlfn.XLOOKUP(A30,'Basic Project Info'!$A$3:$L$3, 'Basic Project Info'!$A$4:$L$4) -> Project Type | C30: =C47 -> Automatically generated and uneditable. Project types potentially included in this tracker are: New Construction, Retrofit, Addition, and Purchase.
A31: ="Col " & ROW() -ROW($A$27)+1 -> Col 5 | B31: =_xlfn.XLOOKUP(A31,'Basic Project Info'!$A$3:$L$3, 'Basic Project Info'!$A$4:$L$4) -> Project Category | C31: =C48 -> Automatically generated and uneditable. This field identifies the need that is met by the project. Potential project categories that could be included on this tracker are: Accommodation Pressure, Child Care, Facility Condition, Consolidation, and French Language Access.
A32: ="Col " & ROW() -ROW($A$27)+1 -> Col 6 | B32: =_xlfn.XLOOKUP(A32,'Basic Project Info'!$A$3:$L$3, 'Basic Project Info'!$A$4:$L$4) -> Address | C32: Enter the address for the school. If it's not yet known, leave it blank.
A33: ="Col " & ROW() -ROW($A$27)+1 -> Col 7 | B33: =_xlfn.XLOOKUP(A33,'Basic Project Info'!$A$3:$L$3, 'Basic Project Info'!$A$4:$L$4) -> City | C33: Use this field to enter the city/town where the project is located. This should be known at the time of project approval and be pre-populated on the template. Therefore, this field can be left unedited except for very rare circumstances.
A34: ="Col " & ROW() -ROW($A$27)+1 -> Col 8 | B34: =_xlfn.XLOOKUP(A34,'Basic Project Info'!$A$3:$L$3, 'Basic Project Info'!$A$4:$L$4) -> Postal Code | C34: Enter the postal code of the school. If the it's not yet known, leave it blank.
A35: ="Col " & ROW() -ROW($A$27)+1 -> Col 9 | B35: =_xlfn.XLOOKUP(A35,'Basic Project Info'!$A$3:$L$3, 'Basic Project Info'!$A$4:$L$4) -> Latitude | C35: Enter the latitude of the school. This information should be updated once the site has been purchased.
A36: ="Col " & ROW() -ROW($A$27)+1 -> Col 10 | B36: =_xlfn.XLOOKUP(A36,'Basic Project Info'!$A$3:$L$3, 'Basic Project Info'!$A$4:$L$4) -> Longitude | C36: Enter the longitude of the school. This information should be updated once the site has been purchased.
A37: ='Basic Project Info'!K2 -> Section 2: Communications Issues
A38: ="Col " & ROW() -ROW($A$27) -> Col 11 | B38: =_xlfn.XLOOKUP(A38,'Basic Project Info'!$A$3:$L$3, 'Basic Project Info'!$A$4:$L$4) -> Sign Installed | C38: Indicate whether the board has installed a sign on the project site.
A39: ="Col " & ROW() -ROW($A$27) -> Col 12 | B39: =_xlfn.XLOOKUP(A39,'Basic Project Info'!$A$3:$L$3, 'Basic Project Info'!$A$4:$L$4) -> Opening Ceremony - Date | C39: Use this once the project approaches completion if the board plans an opening ceremony. Otherwise, leave this blank.
A41: Glossary - Monthly Update Tab
A43: ='Monthly Update'!A5 -> Section 1: Project Details
A44: Col 1 | B44: =_xlfn.XLOOKUP(A44, 'Monthly Update'!$A$6:$AW$6, 'Monthly Update'!$A$7:$AW$7) -> Project ID | C44: Automatically generated and uneditable. Each project is assigned a unique ID for tracking throughout its lifecycle. The ID displayed here is the ID for the construction portion of the project.
A45: Col 2 | B45: =_xlfn.XLOOKUP(A45, 'Monthly Update'!$A$6:$AW$6, 'Monthly Update'!$A$7:$AW$7) -> Project Name | C45: Automatically generated and uneditable. This is the name assigned to the project when it is first approved. It cannot be changed and is constant throughout the project's lifecycle. The official name of the school can be modified on the Basic Project Info tab.
A46: Col 3 | B46: =_xlfn.XLOOKUP(A46, 'Monthly Update'!$A$6:$AW$6, 'Monthly Update'!$A$7:$AW$7) -> Meeting Minutes | C46: Enter details about each project based on conversations with the school board.
A47: Col 4 | B47: =_xlfn.XLOOKUP(A47, 'Monthly Update'!$A$6:$AW$6, 'Monthly Update'!$A$7:$AW$7) -> Project Type | C47: Automatically generated and uneditable. Project types potentially included in this tracker are: New Construction, Retrofit, Addition, and Purchase.
A48: Col 5 | B48: =_xlfn.XLOOKUP(A48, 'Monthly Update'!$A$6:$AW$6, 'Monthly Update'!$A$7:$AW$7) -> Project Category | C48: Automatically generated and uneditable. This field identifies the need that is met by the project. Potential project categories that could be included on this tracker are: Accommodation Pressure, Child Care, Facility Condition, Consolidation, and French Language Access.
A49: Col 6 | B49: =_xlfn.XLOOKUP(A49, 'Monthly Update'!$A$6:$AW$6, 'Monthly Update'!$A$7:$AW$7) -> Record Status | C49: This drop-down determines which projects will be removed from your trackers. If you want to remove a project, you must identify whether it has been completed or cancelled. The default is for projects to remain on the tracker. When projects are removed from the tracker, it triggers an email notification to your manager and director.
A50: Col 7 | B50: =_xlfn.XLOOKUP(A50, 'Monthly Update'!$A$6:$AW$6, 'Monthly Update'!$A$7:$AW$7) -> Project Status | C50: Automatically generated and uneditable. This field is calculated based on the dates provided to the right in this sheet. If the meeting date is after the opening date, the construction status is "Open"; if the meeting date is after the construction date, the status is "Under Construction". Otherwise the project status is "Planning".
A51: ='Monthly Update'!H5 -> Section 2: Project Commitment Progress
A52: Col 8 | B52: =_xlfn.XLOOKUP(A52, 'Monthly Update'!$A$6:$AW$6, 'Monthly Update'!$A$7:$AW$7) -> Pre-Tender Submission Date | C52: This is the estimated/actual submission date for the pre-tender budget. This field must be a date value.
A53: Col 9 | B53: =_xlfn.XLOOKUP(A53, 'Monthly Update'!$A$6:$AW$6, 'Monthly Update'!$A$7:$AW$7) -> Pre-Tender Package Type | C53: Use this dropdown to indicate whether the pretender budget is within existing funding or requires additional ministry funds.
A54: Col 10 | B54: =_xlfn.XLOOKUP(A54, 'Monthly Update'!$A$6:$AW$6, 'Monthly Update'!$A$7:$AW$7) -> Pre-Tender Package Complete | C54: Automatically generated and uneditable. This indicates whether we have a record of the pre-tender budget in our data system and, if so, the date of the approval (for packages approved by the minister) or notification (for within-budget acknowledgments).
A55: Col 11 | B55: =_xlfn.XLOOKUP(A55, 'Monthly Update'!$A$6:$AW$6, 'Monthly Update'!$A$7:$AW$7) -> CA Reviewed All Pre-Tender Documents | C55: This is a manual confirmation that the CA has completed their review of the pre-tender package.
A56: Col 12 | B56: =_xlfn.XLOOKUP(A56, 'Monthly Update'!$A$6:$AW$6, 'Monthly Update'!$A$7:$AW$7) -> Post-Tender Submission Date | C56: This is the estimated/actual submission date for the post-tender budget. This field must be a date value.
A57: Col 13 | B57: =_xlfn.XLOOKUP(A57, 'Monthly Update'!$A$6:$AW$6, 'Monthly Update'!$A$7:$AW$7) -> Post-Tender Package Type | C57: Use this dropdown to indicate whether the post-tender budget is within existing funding or requires additional ministry funds.
A58: Col 14 | B58: =_xlfn.XLOOKUP(A58, 'Monthly Update'!$A$6:$AW$6, 'Monthly Update'!$A$7:$AW$7) -> Post-Tender Package Complete | C58: Automatically generated and uneditable. This indicates whether we have a record of the post-tender budget in our data system and, if so, the date of the approval (for packages approved by the minister) or notification (for within-budget acknowledgments).
A59: Col 15 | B59: =_xlfn.XLOOKUP(A59, 'Monthly Update'!$A$6:$AW$6, 'Monthly Update'!$A$7:$AW$7) -> CA Reviewed All Post-Tender Documents | C59: This is a manual confirmation that the CA has completed their review of the post-tender package.
A60: ='Monthly Update'!P5 -> Section 3: Pre-Tender
A61: Col 16 | B61: =_xlfn.XLOOKUP(A61, 'Monthly Update'!$A$6:$AW$6, 'Monthly Update'!$A$7:$AW$7) -> Site Ownership Status | C61: Use this dropdown to indicate the site status. Only use "Not Applicable" if the project is an addition/retrofit and does not require a site purchase.
A62: Col 17 | B62: =_xlfn.XLOOKUP(A62, 'Monthly Update'!$A$6:$AW$6, 'Monthly Update'!$A$7:$AW$7) -> Site Purchase Date | C62: This field must be a date value or blank. Indicate when the board will gain/gained ownership of the site or leave it blank if Site Ownership Status is "Not Applicable".
A63: Col 18 | B63: =_xlfn.XLOOKUP(A63, 'Monthly Update'!$A$6:$AW$6, 'Monthly Update'!$A$7:$AW$7) -> Site Purchase Date Error Explanation | C63: Use this dropdown to identify the progress on the project's designs.
A64: Col 19 | B64: =_xlfn.XLOOKUP(A64, 'Monthly Update'!$A$6:$AW$6, 'Monthly Update'!$A$7:$AW$7) -> Design Status | C64: This field must be a date value. Indicate expected/actual date of the space template approval.
A65: Col 20 | B65: =_xlfn.XLOOKUP(A65, 'Monthly Update'!$A$6:$AW$6, 'Monthly Update'!$A$7:$AW$7) -> Space Template Approval Date | C65: This field must be a date value or blank. Indicate the expected/actual date of the child care floorplan approval. Leave blank only if the project does not include child care.
A66: Col 21 | B66: =_xlfn.XLOOKUP(A66, 'Monthly Update'!$A$6:$AW$6, 'Monthly Update'!$A$7:$AW$7) -> Child Care Floorplan Approval Date | C66: This field must be a date value. Provide the expected/actual initial site plan submission date.
A67: Col 22 | B67: =_xlfn.XLOOKUP(A67, 'Monthly Update'!$A$6:$AW$6, 'Monthly Update'!$A$7:$AW$7) -> Child Care Floorplan Approval Date Error Explanation | C67: This field must be a date value. Provide the expected/actual site plan submission date.
A68: Col 23 | B68: =_xlfn.XLOOKUP(A68, 'Monthly Update'!$A$6:$AW$6, 'Monthly Update'!$A$7:$AW$7) -> Initial Site Plan Submission Date | C68: ="Use the field only if "& A67& " ("&B67&") indicates an error (cell is highlighted in purple) but you believe the information is correct, explain the descrpancy in this cell and it will remove the error formatting in "&A67&"." -> Use the field only if Col 22 (Child Care Floorplan Approval Date Error Explanation) indicates an error (cell is highlighted in purple) but you believe the information is correct, explain the descrpancy in this cell and it will remove the error formatting in Col 22.
A69: Col 24 | B69: =_xlfn.XLOOKUP(A69, 'Monthly Update'!$A$6:$AW$6, 'Monthly Update'!$A$7:$AW$7) -> Site Plan Approval Date | C69: This field must be a date value. Enter the expected/actual date the board received a building permit for this project.
A70: Col 25 | B70: =_xlfn.XLOOKUP(A70, 'Monthly Update'!$A$6:$AW$6, 'Monthly Update'!$A$7:$AW$7) -> Site Plan Approval Date Error Explanation | C70: ="Use the field only if "& A69& " ("&B69&") indicates an error (cell is highlighted in purple) but you believe the information is correct, explain the descrpancy in this cell and it will remove the error formatting in "&A69&"." -> Use the field only if Col 24 (Site Plan Approval Date) indicates an error (cell is highlighted in purple) but you believe the information is correct, explain the descrpancy in this cell and it will remove the error formatting in Col 24.
A71: Col 26 | B71: =_xlfn.XLOOKUP(A71, 'Monthly Update'!$A$6:$AW$6, 'Monthly Update'!$A$7:$AW$7) -> Build Permit Obtained Date | C71: This field must be a date value. Enter the expected/actual date the board opened the tender process.
A72: Col 27 | B72: =_xlfn.XLOOKUP(A72, 'Monthly Update'!$A$6:$AW$6, 'Monthly Update'!$A$7:$AW$7) -> Build Permit Obtained Date Error Explanation | C72: This field must be a date value. Enter the expected/actual date the board closed the tender process.
A73: ='Monthly Update'!AD5 -> Section 4: Construction
A74: Col 28 | B74: =_xlfn.XLOOKUP(A74, 'Monthly Update'!$A$6:$AW$6, 'Monthly Update'!$A$7:$AW$7) -> Tender Issued Date | C74: This field must be a date value. Enter the expected/actual date the board awards the contract to the successful bid.
A75: Col 29 | B75: =_xlfn.XLOOKUP(A75, 'Monthly Update'!$A$6:$AW$6, 'Monthly Update'!$A$7:$AW$7) -> Tender Closed Date | C75: This field must be a date value. Enter the expected/actual date that construction work will actually begin on the school site. This date must follow all tender dates and the contract awarded date.
A76: Col 30 | B76: =_xlfn.XLOOKUP(A76, 'Monthly Update'!$A$6:$AW$6, 'Monthly Update'!$A$7:$AW$7) -> Contract Awarded Date | C76: ="Use the field only if "& A75& " ("&B75&") indicates an error (cell is highlighted in purple) but you believe the information is correct, explain the descrpancy in this cell and it will remove the error formatting in "&A75&"." -> Use the field only if Col 29 (Tender Closed Date) indicates an error (cell is highlighted in purple) but you believe the information is correct, explain the descrpancy in this cell and it will remove the error formatting in Col 29.
A77: Col 31 | B77: =_xlfn.XLOOKUP(A77, 'Monthly Update'!$A$6:$AW$6, 'Monthly Update'!$A$7:$AW$7) -> Construction Start Date | C77: This field must be a date value. Enter the expected/actual date the project will be substantially complete - that is, the project is complete up to the point that it can be utilized for its intended purpose. Under all but very rare circumstances this date will precede the opening date.
A78: Col 32 | B78: =_xlfn.XLOOKUP(A78, 'Monthly Update'!$A$6:$AW$6, 'Monthly Update'!$A$7:$AW$7) -> Construction Start Date Error Explanation | C78: ="Use the field only if "& A77& " ("&B77&") indicates an error (cell is highlighted in purple) but you believe the information is correct, explain the descrpancy in this cell and it will remove the error formatting in "&A77&"." -> Use the field only if Col 31 (Construction Start Date) indicates an error (cell is highlighted in purple) but you believe the information is correct, explain the descrpancy in this cell and it will remove the error formatting in Col 31.
A79: ='Monthly Update'!AI5 -> Section 5: Project Completion
A80: Col 33 | B80: =_xlfn.XLOOKUP(A80, 'Monthly Update'!$A$6:$AW$6, 'Monthly Update'!$A$7:$AW$7) -> Substantial Completion Date | C80: This field must be a date value. Enter the expected/actual date the school portion of the project will be open (i.e., the date when kids will be in new seats).
A81: Col 34 | B81: =_xlfn.XLOOKUP(A81, 'Monthly Update'!$A$6:$AW$6, 'Monthly Update'!$A$7:$AW$7) -> Substantial Completion Date Error Explanation | C81: ="Use the field only if "& A80& " ("&B80&") indicates an error (cell is highlighted in purple) but you believe the information is correct, explain the descrpancy in this cell and it will remove the error formatting in "&A80&"." -> Use the field only if Col 33 (Substantial Completion Date) indicates an error (cell is highlighted in purple) but you believe the information is correct, explain the descrpancy in this cell and it will remove the error formatting in Col 33.
A82: Col 35 | B82: =_xlfn.XLOOKUP(A82, 'Monthly Update'!$A$6:$AW$6, 'Monthly Update'!$A$7:$AW$7) -> School Opening Date | C82: This field must be a date value or blank. Enter the expected/actual date the child care portion of the project will be open (when will the center be taking care of children?). This must be completed unless the project does not include child care.
A83: Col 36 | B83: =_xlfn.XLOOKUP(A83, 'Monthly Update'!$A$6:$AW$6, 'Monthly Update'!$A$7:$AW$7) -> School Opening Date Error Explanation | C83: ="Use the field only if "& A82& " ("&B82&") indicates an error (cell is highlighted in purple) but you believe the information is correct, explain the descrpancy in this cell and it will remove the error formatting in "&A82&"." -> Use the field only if Col 35 (School Opening Date ) indicates an error (cell is highlighted in purple) but you believe the information is correct, explain the descrpancy in this cell and it will remove the error formatting in Col 35.
A84: Col 37 | B84: =_xlfn.XLOOKUP(A84, 'Monthly Update'!$A$6:$AW$6, 'Monthly Update'!$A$7:$AW$7) -> Child Care Opening Date | C84: This field must be a date value. Enter the expected/actual date of financial close out for the project. At this point, all construction is complete, all deficiencies have been addressed and the financial close-out form has been submitted for final budget/cost reconciliation. This is generally 12-18 months after the opening date.
A85: ='Monthly Update'!AN5 -> Section 6: Approved Project Funding
A86: Col 38 | B86: =_xlfn.XLOOKUP(A86, 'Monthly Update'!$A$6:$AW$6, 'Monthly Update'!$A$7:$AW$7) -> Child Care Opening Date Error Explanation | C86: Automatically generated and uneditable.
A87: Col 39 | B87: =_xlfn.XLOOKUP(A87, 'Monthly Update'!$A$6:$AW$6, 'Monthly Update'!$A$7:$AW$7) -> Financial Close-Out Date | C87: Automatically generated and uneditable.
A88: Col 40 | B88: =_xlfn.XLOOKUP(A88, 'Monthly Update'!$A$6:$AW$6, 'Monthly Update'!$A$7:$AW$7) -> Funding - All Associated Projects | C88: Automatically generated and uneditable.
A89: Col 41 | B89: =_xlfn.XLOOKUP(A89, 'Monthly Update'!$A$6:$AW$6, 'Monthly Update'!$A$7:$AW$7) -> Funding - Construction Project | C89: Automatically generated and uneditable.
A90: Col 42 | B90: =_xlfn.XLOOKUP(A90, 'Monthly Update'!$A$6:$AW$6, 'Monthly Update'!$A$7:$AW$7) -> Funding - Site Acquisition | C90: Automatically generated and uneditable.
A91: ='Monthly Update'!AS5 -> Section 7: Projected Cost
A92: Col 43 | B92: =_xlfn.XLOOKUP(A92, 'Monthly Update'!$A$6:$AW$6, 'Monthly Update'!$A$7:$AW$7) -> Funding - Demolition | C92: Use the drop-down to indicate how the board determined the cost estimate.
A93: Col 44 | B93: =_xlfn.XLOOKUP(A93, 'Monthly Update'!$A$6:$AW$6, 'Monthly Update'!$A$7:$AW$7) -> Funding - All Other Associated Projects | C93: Enter the board's estimate of the total cost of the construction project. This includes the cost of the school portion, child care portion, site costs, and any other portion not captured in columns 45 to 47
A94: Col 45 | B94: =_xlfn.XLOOKUP(A94, 'Monthly Update'!$A$6:$AW$6, 'Monthly Update'!$A$7:$AW$7) -> Basis of Cost Estimate | C94: Enter the estimated/actual cost of any land purchase associated with this project. Leave it blank if no land is needed for this project.
A95: Col 46 | B95: =_xlfn.XLOOKUP(A95, 'Monthly Update'!$A$6:$AW$6, 'Monthly Update'!$A$7:$AW$7) -> Estimated Cost - Construction Project | C95: Use this only if the project will be associated with a separate project ID assigned to a demolition project. This would only happen if the board is demolishing an entire building as part of the project.
A96: Col 47 | B96: =_xlfn.XLOOKUP(A96, 'Monthly Update'!$A$6:$AW$6, 'Monthly Update'!$A$7:$AW$7) -> Estimated Cost - Land | C96: Use this only in the rare circumstance where there is/will be any other project ID(s) associated with this project.

Sheet Board Contacts
A1: School Board Contact List
A4: Name | B4: Role | C4: Title | D4: Email | E4: Phone
A5: *((tbl*((board_contacts*((col*((name | B5: *((col*((role | C5: *((col*((title | D5: *((col*((email | E5: *((col*((phone

Sheet Basic Project Info
A1: Basic Project Information
A2: =Translation!A5 -> Section 1: Project Details | K2: Section 2: Communications Issues
A3: ="Col "&COLUMN() -> Col 1 | B3: ="Col "&COLUMN() -> Col 2 | C3: ="Col "&COLUMN() -> Col 3 | D3: ="Col "&COLUMN() -> Col 4 | E3: ="Col "&COLUMN() -> Col 5 | F3: ="Col "&COLUMN() -> Col 6 | G3: ="Col "&COLUMN() -> Col 7 | H3: ="Col "&COLUMN() -> Col 8 | ... L3: ="Col "&COLUMN() -> Col 12
A4: =Translation!A6 -> Project ID | B4: =Translation!A7 -> Project Name | C4: Official School Name | D4: =Translation!A11 -> Project Type | E4: =Translation!A13 -> Project Category | F4: =Translation!A8 -> Address | G4: =Translation!A9 -> City | H4: =Translation!A10 -> Postal Code | I4: Latitude | J4: Longitude | K4: Sign Installed | L4: =Translation!A70 -> Opening Ceremony - Date
A5: No. de projet | B5: Nom du projet | D5: Type de projet | E5: Catégorie de projet
A7: *((tbl*((basic_project_info*((col*((project_id | B7: *((col*((project_name | C7: *((col*((project_name_official | D7: *((col*((project_type | E7: *((col*((project_category | F7: *((col*((location_address | G7: *((col*((location_city | H7: *((col*((location_postal_code | I7: *((col*((location_latitude | J7: *((col*((location_longitude | K7: *((col*((sign_installed | L7: *((col*((date_opening_ceremony
A100: 1 | B100: 1 | C100: 1 | D100: 1 | E100: 1 | F100: 1 | G100: 1 | H100: 1 | I100: 1 | J100: 1 | K100: 1 | L100: 1

Sheet Monthly Update
A1: Monthly Project Updates | C1: *((var*((board_number_name
E2: *((var*((missing_data_count*((formula*((right | F2: =COLUMNS($D$3:$AW$3) - COUNTIF($D$3:$AW$3, "") -> 0
A3: Meeting Date | C3: *((var*((date_meeting | CR3: *((var*((error_count*((formula*((down | CS3: =AND(CR3, ISBLANK(CS11)) -> TRUE | CT3: =AND(CT4, ISBLANK(CT11)) -> FALSE | CU3: =AND(CU4, ISBLANK(CU11)) -> FALSE | CV3: =AND(CV4, ISBLANK(CV11)) -> FALSE | CW3: =AND(CW4, ISBLANK(CW11)) -> FALSE | CX3: =AND(CX4, ISBLANK(CX11)) -> FALSE | CY3: =AND(CY4, ISBLANK(CY11)) -> FALSE | CZ3: =AND(CZ4, ISBLANK(CZ11)) -> FALSE | DA3: =AND(DA4, ISBLANK(DA11)) -> FALSE | ... DI3: =AND(DI4, ISBLANK(DI11)) -> FALSE | DK3: =AND(DK4, ISBLANK(DK11)) -> FALSE | DL3: =AND(DL4, ISBLANK(DL11)) -> FALSE | DM3: =AND(DM4, ISBLANK(DM11)) -> FALSE | DO3: =AND(DO4, ISBLANK(DO11)) -> FALSE | DP3: =AND(DP4, ISBLANK(DP11)) -> FALSE | DQ3: =AND(DQ4, ISBLANK(DQ11)) -> FALSE | DR3: =AND(DR4, ISBLANK(DR11)) -> FALSE | DS3: =AND(DS4, ISBLANK(DS11)) -> FALSE | DT3: =AND(DT4, ISBLANK(DT11)) -> FALSE | DU3: =AND(DU4, ISBLANK(DU11)) -> FALSE | DV3: =AND(DV4, ISBLANK(DV11)) -> FALSE | ... EO3: =AND(EO4, ISBLANK(EO11)) -> FALSE
B4: General Meeting Minutes: | C4: *((var*((meeting_minutes_general_current | AV4: Historical General Meeting Minutes -------------> | AX4: *((tbl*((meeting_minutes_general*((col*((meeting_minutes_general_minus_1 | AY4: ="*((col*((meeting_minutes_general_minus_"&COLUMN()-COLUMN($AX$4)+1 -> *((col*((meeting_minutes_general_minus_2 | AZ4: ="*((col*((meeting_minutes_general_minus_"&COLUMN()-COLUMN($AX$4)+1 -> *((col*((meeting_minutes_general_minus_3 | BA4: ="*((col*((meeting_minutes_general_minus_"&COLUMN()-COLUMN($AX$4)+1 -> *((col*((meeting_minutes_general_minus_4 | BB4: ="*((col*((meeting_minutes_general_minus_"&COLUMN()-COLUMN($AX$4)+1 -> *((col*((meeting_minutes_general_minus_5 | BC4: ="*((col*((meeting_minutes_general_minus_"&COLUMN()-COLUMN($AX$4)+1 -> *((col*((meeting_minutes_general_minus_6 | BD4: ="*((col*((meeting_minutes_general_minus_"&COLUMN()-COLUMN($AX$4)+1 -> *((col*((meeting_minutes_general_minus_7 | BE4: ="*((col*((meeting_minutes_general_minus_"&COLUMN()-COLUMN($AX$4)+1 -> *((col*((meeting_minutes_general_minus_8 | BF4: ="*((col*((meeting_minutes_general_minus_"&COLUMN()-COLUMN($AX$4)+1 -> *((col*((meeting_minutes_general_minus_9 | ... BU4: ="*((col*((meeting_minutes_general_minus_"&COLUMN()-COLUMN($AX$4)+1 -> *((col*((meeting_minutes_general_minus_24 | CR4: =COUNTA(CS10:EO105) -> 99 | CS4: =ISNUMBER(SEARCH("formula", CS10)) -> FALSE | CT4: =ISNUMBER(SEARCH("formula", CT10)) -> FALSE | CU4: =ISNUMBER(SEARCH("formula", CU10)) -> TRUE | CV4: =ISNUMBER(SEARCH("formula", CV10)) -> FALSE | CW4: =ISNUMBER(SEARCH("formula", CW10)) -> FALSE | CX4: =ISNUMBER(SEARCH("formula", CX10)) -> FALSE | CY4: =ISNUMBER(SEARCH("formula", CY10)) -> TRUE | CZ4: =ISNUMBER(SEARCH("formula", CZ10)) -> TRUE | ... DI4: =ISNUMBER(SEARCH("formula", DI10)) -> TRUE | DK4: =ISNUMBER(SEARCH("formula", DK10)) -> TRUE | DL4: =ISNUMBER(SEARCH("formula", DL10)) -> TRUE | DM4: =ISNUMBER(SEARCH("formula", DM10)) -> TRUE | DO4: =ISNUMBER(SEARCH("formula", DO10)) -> TRUE | DP4: =ISNUMBER(SEARCH("formula", DP10)) -> TRUE | DQ4: =ISNUMBER(SEARCH("formula", DQ10)) -> FALSE | DR4: =ISNUMBER(SEARCH("formula", DR10)) -> TRUE | DS4: =ISNUMBER(SEARCH("formula", DS10)) -> FALSE | DT4: =ISNUMBER(SEARCH("formula", DT10)) -> TRUE | DU4: =ISNUMBER(SEARCH("formula", DU10)) -> TRUE | DV4: =ISNUMBER(SEARCH("formula", DV10)) -> TRUE | ... EO4: =ISNUMBER(SEARCH("formula", EO10)) -> TRUE
A5: Section 1: Project Details | H5: Section 2: Project Commitment Progress | P5: Section 3: Pre-Tender | AD5: Section 4: Construction | AI5: Section 5: Project Completion | AN5: Section 6: Approved Project Funding | AS5: Section 7: Projected Cost | AX5: Section 8: Historical Meeting Minutes | CS5: Error Messages | CX5: Error Messages | DG5: Error Messages | DM5: Error Messages | DR5: Error Messages | DU5: Error Messages | DX5: Error Messages | EC5: Error Messages | EH5: Error Messages | EM5: Error Messages
A6: ="Col "&COLUMN() -> Col 1 | B6: ="Col "&COLUMN() -> Col 2 | C6: ="Col "&COLUMN() -> Col 3 | D6: ="Col "&COLUMN() -> Col 4 | E6: ="Col "&COLUMN() -> Col 5 | F6: ="Col "&COLUMN() -> Col 6 | G6: ="Col "&COLUMN() -> Col 7 | H6: ="Col "&COLUMN() -> Col 8 | ... BU6: ="Col "&COLUMN() -> Col 73 | CS6: =A6 -> Col 1 | CT6: =B6 -> Col 2 | CU6: =C6 -> Col 3 | CV6: =D6 -> Col 4 | CW6: =E6 -> Col 5 | CX6: =F6 -> Col 6 | CY6: =G6 -> Col 7 | CZ6: =H6 -> Col 8 | ... EO6: =AW6 -> Col 49 | ES6: =K6 -> Col 11 | ET6: =ES6 -> Col 11 | EU6: =ET6 -> Col 11 | EV6: =EU6 -> Col 11 | EW6: =O6 -> Col 15 | EX6: =EW6 -> Col 15 | EY6: =EX6 -> Col 15 | EZ6: =EY6 -> Col 15 | FA6: =P6 -> Col 16 | FB6: =FA6 -> Col 16 | FC6: =FB6 -> Col 16 | FD6: =FC6 -> Col 16 | FE6: =Q6 -> Col 17 | FF6: =FE6 -> Col 17 | FG6: =FF6 -> Col 17 | FH6: =FG6 -> Col 17
A7: Project ID | B7: Project Name | C7: Meeting Minutes | D7: Project Type | E7: Project Category | F7: Record Status | G7: Project Status | H7: Pre-Tender Submission Date | I7: Pre-Tender Package Type | J7: Pre-Tender Package Complete | K7: CA Reviewed All Pre-Tender Documents | L7: Post-Tender Submission Date | M7: Post-Tender Package Type | N7: Post-Tender Package Complete | O7: CA Reviewed All Post-Tender Documents | P7: Site Ownership Status | Q7: Site Purchase Date | R7: =Q7&" Error Explanation" -> Site Purchase Date Error Explanation | S7: Design Status | T7: Space Template Approval Date | U7: Child Care Floorplan Approval Date | V7: =U7&" Error Explanation" -> Child Care Floorplan Approval Date Error Explanation | W7: Initial Site Plan Submission Date | X7: Site Plan Approval Date | Y7: Site Plan Approval Date Error Explanation | Z7: Build Permit Obtained Date | AA7: =Z7&" Error Explanation" -> Build Permit Obtained Date Error Explanation | AB7: Tender Issued Date | AC7: Tender Closed Date | AD7: Contract Awarded Date | AE7: Construction Start Date | AF7: =AE7&" Error Explanation" -> Construction Start Date Error Explanation | AG7: Substantial Completion Date | AH7: =AG7&" Error Explanation" -> Substantial Completion Date Error Explanation | AI7: School Opening Date | AJ7: =AI7&" Error Explanation" -> School Opening Date Error Explanation | AK7: Child Care Opening Date | AL7: =AK7&" Error Explanation" -> Child Care Opening Date Error Explanation | AM7: Financial Close-Out Date | AN7: Funding - All Associated Projects | AO7: Funding - Construction Project | AP7: Funding - Site Acquisition | AQ7: Funding - Demolition | AR7: Funding - All Other Associated Projects | AS7: Basis of Cost Estimate | AT7: Estimated Cost - Construction Project | AU7: Estimated Cost - Land | AV7: Estimated Cost - Demolition | AW7: Estimated Cost - All Other Associated Projects | AX7: ="*((tbl*((meeting_minutes_heading"&AX10 -> *((tbl*((meeting_minutes_heading*((col*((meeting_minutes_minus_1 | AY7: =AY10 -> *((col*((meeting_minutes_minus_2 | AZ7: =AZ10 -> *((col*((meeting_minutes_minus_3 | BA7: =BA10 -> *((col*((meeting_minutes_minus_4 | BB7: =BB10 -> *((col*((meeting_minutes_minus_5 | BC7: =BC10 -> *((col*((meeting_minutes_minus_6 | BD7: =BD10 -> *((col*((meeting_minutes_minus_7 | BE7: =BE10 -> *((col*((meeting_minutes_minus_8 | BF7: =BF10 -> *((col*((meeting_minutes_minus_9 | ... BU7: =BU10 -> *((col*((meeting_minutes_minus_24 | BW7: *((table_end*((meeting_minutes_heading | BY7: cc_amount | BZ7: ='Project Commitment'!M4 -> Site Purchase Date | CA7: ='Project Commitment'!N4 -> Space Template Approval Date | CB7: ='Project Commitment'!O4 -> Child Care Floorplan Approval Date | CC7: ='Project Commitment'!P4 -> Initial Site Plan Submission Date | CD7: ='Project Commitment'!Q4 -> Site Plan Approval Date | CE7: ='Project Commitment'!R4 -> Build Permit Obtained Date | CF7: ='Project Commitment'!S4 -> Pre-Tender Submission Date | CG7: ='Project Commitment'!T4 -> Tender Issued Date | ... CO7: ='Project Commitment'!AB4 -> Financial Close-Out Date | CS7: =A7 -> Project ID | CT7: =B7 -> Project Name | CU7: =C7 -> Meeting Minutes | CV7: =D7 -> Project Type | CW7: =E7 -> Project Category | CX7: =F7 -> Record Status | CY7: =G7 -> Project Status | CZ7: =H7 -> Pre-Tender Submission Date | ... EO7: =AW7 -> Estimated Cost - All Other Associated Projects
A8: No. de projet | B8: Nom du projet | D8: Type de projet | E8: Catégorie de projet | AP8: IP | AQ8: Service de garde | AR8: Autre | AS8: Base de l'estimation des coûts | AW8: Coûts du site | DI8: =Q8 -> 0
DI9: =Q9 -> 0
A10: *((tbl*((monthly*((col*((project_id | B10: *((col*((project_name | C10: *((col*((meeting_minutes | D10: *((col*((project_type | E10: *((col*((project_category | F10: *((col*((record_status | G10: *((col*((construction_status*((formula*((down | H10: *((col*((date_pretender | I10: *((col*((pretender_package_type | J10: *((col*((pre_tender_complete | K10: *((col*((pre_tender_documents_reviewed | L10: *((col*((date_posttender | M10: *((col*((posttender_package_type | N10: *((col*((post_tender_complete | O10: *((col*((post_tender_documents_reviewed | P10: *((col*((site_status | Q10: *((col*((date_site_purchase | R10: ="*((col*((error_explained_"&RIGHT(Q10, LEN(Q10)-9) -> *((col*((error_explained_date_site_purchase | S10: *((col*((design_status | T10: *((col*((date_space_template | U10: *((col*((date_cc_floorplan | V10: ="*((col*((error_explained_"&RIGHT(U10, LEN(U10)-9) -> *((col*((error_explained_date_cc_floorplan | W10: *((col*((date_site_plan_submission | X10: *((col*((date_site_plan_approved | Y10: ="*((col*((error_explained_"&RIGHT(X10, LEN(X10)-9) -> *((col*((error_explained_date_site_plan_approved | Z10: *((col*((date_building_permit | AA10: ="*((col*((error_explained_date_building_permit" -> *((col*((error_explained_date_building_permit | AB10: *((col*((date_tender_issue | AC10: *((col*((date_tender_closed | AD10: *((col*((date_tender | AE10: *((col*((date_construction | AF10: ="*((col*((error_explained_date_construction" -> *((col*((error_explained_date_construction | AG10: *((col*((date_substantial_completion | AH10: ="*((col*((error_explained_date_substantial_completion" -> *((col*((error_explained_date_substantial_completion | AI10: *((col*((date_opening | AJ10: ="*((col*((error_explained_date_opening" -> *((col*((error_explained_date_opening | AK10: *((col*((date_opening_cc | AL10: ="*((col*((error_explained_date_opening_cc" -> *((col*((error_explained_date_opening_cc | AM10: *((col*((date_completion | AN10: *((col*((funding_all*((formula*((down | AO10: *((col*((funding_construction | AP10: *((col*((funding_site | AQ10: *((col*((funding_demo | AR10: *((col*((funding_other_projects | AS10: *((col*((cost_basis | AT10: *((col*((cost_estimate_construction | AU10: *((col*((cost_estimate_land | AV10: *((col*((cost_estimate_demo | AW10: *((col*((cost_estimate_other_projects | AX10: *((col*((meeting_minutes_minus_1 | AY10: *((col*((meeting_minutes_minus_2 | AZ10: *((col*((meeting_minutes_minus_3 | BA10: *((col*((meeting_minutes_minus_4 | BB10: *((col*((meeting_minutes_minus_5 | BC10: *((col*((meeting_minutes_minus_6 | BD10: *((col*((meeting_minutes_minus_7 | BE10: *((col*((meeting_minutes_minus_8 | BF10: *((col*((meeting_minutes_minus_9 | BG10: *((col*((meeting_minutes_minus_10 | BH10: *((col*((meeting_minutes_minus_11 | BI10: *((col*((meeting_minutes_minus_12 | BJ10: *((col*((meeting_minutes_minus_13 | BK10: *((col*((meeting_minutes_minus_14 | BL10: *((col*((meeting_minutes_minus_15 | BM10: *((col*((meeting_minutes_minus_16 | BN10: *((col*((meeting_minutes_minus_17 | BO10: *((col*((meeting_minutes_minus_18 | BP10: *((col*((meeting_minutes_minus_19 | BQ10: *((col*((meeting_minutes_minus_20 | BR10: *((col*((meeting_minutes_minus_21 | BS10: *((col*((meeting_minutes_minus_22 | BT10: *((col*((meeting_minutes_minus_23 | BU10: *((col*((meeting_minutes_minus_24 | BX10: *((col*((site_ownership_formula*((formula*((down | BY10: *((col*((scope_cc_spaces_added | BZ10: ="*((col*((temp_formula_"&COLUMN()&"*((formula*((down" -> *((col*((temp_formula_78*((formula*((down | CA10: ="*((col*((temp_formula_"&COLUMN()&"*((formula*((down" -> *((col*((temp_formula_79*((formula*((down | CB10: ="*((col*((temp_formula_"&COLUMN()&"*((formula*((down" -> *((col*((temp_formula_80*((formula*((down | CC10: ="*((col*((temp_formula_"&COLUMN()&"*((formula*((down" -> *((col*((temp_formula_81*((formula*((down | CD10: ="*((col*((temp_formula_"&COLUMN()&"*((formula*((down" -> *((col*((temp_formula_82*((formula*((down | CE10: ="*((col*((temp_formula_"&COLUMN()&"*((formula*((down" -> *((col*((temp_formula_83*((formula*((down | CF10: ="*((col*((temp_formula_"&COLUMN()&"*((formula*((down" -> *((col*((temp_formula_84*((formula*((down | CG10: ="*((col*((temp_formula_"&COLUMN()&"*((formula*((down" -> *((col*((temp_formula_85*((formula*((down | ... CO10: ="*((col*((temp_formula_"&COLUMN()&"*((formula*((down" -> *((col*((temp_formula_93*((formula*((down | CU10: ="*((col*((temp_formula_"&COLUMN()&"*((formula*((down" -> *((col*((temp_formula_99*((formula*((down | CY10: ="*((col*((temp_formula_"&COLUMN()&"*((formula*((down" -> *((col*((temp_formula_103*((formula*((down | CZ10: ="*((col*((temp_formula_"&COLUMN()&"*((formula*((down" -> *((col*((temp_formula_104*((formula*((down | DA10: ="*((col*((temp_formula_"&COLUMN()&"*((formula*((down" -> *((col*((temp_formula_105*((formula*((down | DC10: ="*((col*((temp_formula_"&COLUMN()&"*((formula*((down" -> *((col*((temp_formula_107*((formula*((down | DD10: ="*((col*((temp_formula_"&COLUMN()&"*((formula*((down" -> *((col*((temp_formula_108*((formula*((down | DE10: ="*((col*((temp_formula_"&COLUMN()&"*((formula*((down" -> *((col*((temp_formula_109*((formula*((down | DG10: ="*((col*((temp_formula_"&COLUMN()&"*((formula*((down" -> *((col*((temp_formula_111*((formula*((down | DH10: ="*((col*((temp_formula_"&COLUMN()&"*((formula*((down" -> *((col*((temp_formula_112*((formula*((down | DI10: ="*((col*((temp_formula_"&COLUMN()&"*((formula*((down" -> *((col*((temp_formula_113*((formula*((down | DK10: ="*((col*((temp_formula_"&COLUMN()&"*((formula*((down" -> *((col*((temp_formula_115*((formula*((down | DL10: ="*((col*((temp_formula_"&COLUMN()&"*((formula*((down" -> *((col*((temp_formula_116*((formula*((down | DM10: ="*((col*((temp_formula_"&COLUMN()&"*((formula*((down" -> *((col*((temp_formula_117*((formula*((down | DO10: ="*((col*((temp_formula_"&COLUMN()&"*((formula*((down" -> *((col*((temp_formula_119*((formula*((down | DP10: ="*((col*((temp_formula_"&COLUMN()&"*((formula*((down" -> *((col*((temp_formula_120*((formula*((down | DR10: ="*((col*((temp_formula_"&COLUMN()&"*((formula*((down" -> *((col*((temp_formula_122*((formula*((down | DT10: ="*((col*((temp_formula_"&COLUMN()&"*((formula*((down" -> *((col*((temp_formula_124*((formula*((down | DU10: ="*((col*((temp_formula_"&COLUMN()&"*((formula*((down" -> *((col*((temp_formula_125*((formula*((down | DV10: ="*((col*((temp_formula_"&COLUMN()&"*((formula*((down" -> *((col*((temp_formula_126*((formula*((down | DW10: ="*((col*((temp_formula_"&COLUMN()&"*((formula*((down" -> *((col*((temp_formula_127*((formula*((down | DY10: ="*((col*((temp_formula_"&COLUMN()&"*((formula*((down" -> *((col*((temp_formula_129*((formula*((down | EA10: ="*((col*((temp_formula_"&COLUMN()&"*((formula*((down" -> *((col*((temp_formula_131*((formula*((down | EC10: ="*((col*((temp_formula_"&COLUMN()&"*((formula*((down" -> *((col*((temp_formula_133*((formula*((down | EE10: ="*((col*((temp_formula_"&COLUMN()&"*((formula*((down" -> *((col*((temp_formula_135*((formula*((down | EK10: ="*((col*((temp_formula_"&COLUMN()&"*((formula*((down" -> *((col*((temp_formula_141*((formula*((down | EL10: ="*((col*((temp_formula_"&COLUMN()&"*((formula*((down" -> *((col*((temp_formula_142*((formula*((down | EM10: ="*((col*((temp_formula_"&COLUMN()&"*((formula*((down" -> *((col*((temp_formula_143*((formula*((down | EN10: ="*((col*((temp_formula_"&COLUMN()&"*((formula*((down" -> *((col*((temp_formula_144*((formula*((down | EO10: ="*((col*((temp_formula_"&COLUMN()&"*((formula*((down" -> *((col*((temp_formula_145*((formula*((down | ES10: ="*((col*((temp_formula_"&COLUMN()&"*((formula*((down" -> *((col*((temp_formula_149*((formula*((down | ET10: ="*((col*((temp_formula_"&COLUMN()&"*((formula*((down" -> *((col*((temp_formula_150*((formula*((down | EU10: ="*((col*((temp_formula_"&COLUMN()&"*((formula*((down" -> *((col*((temp_formula_151*((formula*((down | EV10: ="*((col*((temp_formula_"&COLUMN()&"*((formula*((down" -> *((col*((temp_formula_152*((formula*((down | EW10: ="*((col*((temp_formula_"&COLUMN()&"*((formula*((down" -> *((col*((temp_formula_153*((formula*((down | EX10: ="*((col*((temp_formula_"&COLUMN()&"*((formula*((down" -> *((col*((temp_formula_154*((formula*((down | EY10: ="*((col*((temp_formula_"&COLUMN()&"*((formula*((down" -> *((col*((temp_formula_155*((formula*((down | EZ10: ="*((col*((temp_formula_"&COLUMN()&"*((formula*((down" -> *((col*((temp_formula_156*((formula*((down | ... FH10: ="*((col*((temp_formula_"&COLUMN()&"*((formula*((down" -> *((col*((temp_formula_164*((formula*((down
G11: {=_xlfn.IFS(A11="", "", OR(AE11="", AI11="", AM11=""), "Missing Data", TODAY()>AM11, "Complete", TODAY()>AI11, "Open", TODAY()>AE11, "Under Construction", TRUE, "Planning")} | AN11: =SUM(AO11:AR11) -> 0 | BX11: =IF(AND(Q11="", A11<>"", P11<>"Site Purchased Prior to Capital Approval"), 1, 0) -> 0 | BZ11: =_xlfn.XLOOKUP($A11, 'Project Commitment'!$A:$A, 'Project Commitment'!M:M, "") -> 0 | CA11: =_xlfn.XLOOKUP($A11, 'Project Commitment'!$A:$A, 'Project Commitment'!N:N, "") -> 0 | CB11: =_xlfn.XLOOKUP($A11, 'Project Commitment'!$A:$A, 'Project Commitment'!O:O, "") -> 0 | CC11: =_xlfn.XLOOKUP($A11, 'Project Commitment'!$A:$A, 'Project Commitment'!P:P, "") -> 0 | CD11: =_xlfn.XLOOKUP($A11, 'Project Commitment'!$A:$A, 'Project Commitment'!Q:Q, "") -> 0 | CE11: =_xlfn.XLOOKUP($A11, 'Project Commitment'!$A:$A, 'Project Commitment'!R:R, "") -> 0 | CF11: =_xlfn.XLOOKUP($A11, 'Project Commitment'!$A:$A, 'Project Commitment'!S:S, "") -> 0 | CG11: =_xlfn.XLOOKUP($A11, 'Project Commitment'!$A:$A, 'Project Commitment'!T:T, "") -> 0 | CH11: =_xlfn.XLOOKUP($A11, 'Project Commitment'!$A:$A, 'Project Commitment'!U:U, "") -> 0 | CI11: =_xlfn.XLOOKUP($A11, 'Project Commitment'!$A:$A, 'Project Commitment'!V:V, "") -> 0 | CJ11: =_xlfn.XLOOKUP($A11, 'Project Commitment'!$A:$A, 'Project Commitment'!W:W, "") -> 0 | CK11: =_xlfn.XLOOKUP($A11, 'Project Commitment'!$A:$A, 'Project Commitment'!X:X, "") -> 0 | CL11: =_xlfn.XLOOKUP($A11, 'Project Commitment'!$A:$A, 'Project Commitment'!Y:Y, "") -> 0 | CM11: =_xlfn.XLOOKUP($A11, 'Project Commitment'!$A:$A, 'Project Commitment'!Z:Z, "") -> 0 | CN11: =_xlfn.XLOOKUP($A11, 'Project Commitment'!$A:$A, 'Project Commitment'!AA:AA, "") -> 0 | CO11: =_xlfn.XLOOKUP($A11, 'Project Commitment'!$A:$A, 'Project Commitment'!AB:AB, "") -> 0 | CU11: =IF(OR(A11="", C11<>""), "", "Meeting Minutes cannot be blank") | CY11: {=_xlfn.IFS(A11="", "", G11<>"Missing Data", "", AE11="", "Construction Start Date cannot be blank", AI11="", "School Opening Date cannot be blank", AM11="", "Financial Close-Out Date cannot be blank", TRUE, "")} | CZ11: {=_xlfn.IFS(A11="", "", AND(J11="Not Necessary", H11<>""), "No date is needed if Column 10 is Not Necessary", AND(J11<>"Not Necessary", H11=""), CZ$7&" cannot be blank", $AE11="", "", H11>$AE11, CZ$7&" must preceed construction start date.", TRUE, "")} | DA11: {=_xlfn.IFS(A11="", "", I11="", DA$7&" cannot be left blank.", H11="", "", AND(H11<TODAY(), I11="Not Yet Known"), "After the submission date, the pre-tender package type must be selected.", TRUE, "")} | DC11: {=_xlfn.IFS(A11="", "", J11="MISSING", "This package is missing!", K11="", "Confirm you reviewed the pretender checkin documents", AND(K11="Not yet submitted/reviewed", J11<>"Not yet submitted/reviewed"), "Pretender package submitted; col 9 can't indicate otherwise.", TRUE, "")} | DD11: {=_xlfn.IFS(A11="", "", AND(N11="Not Necessary", L11<>""), "No date is needed if Column 14 is Not Necessary", AND(N11<>"Not Necessary", L11=""), DD$7&" cannot be blank", $AE11="", "", L11>$AE11, DD$7&" must preceed construction start date.", TRUE, "")} | DE11: {=_xlfn.IFS(A11="", "", M11="", DE$7&" cannot be left blank.", L11="", "", AND(L11<TODAY(), M11="Not Yet Known"), "After the submission date, the pre-tender package type must be selected.", TRUE, "")} | DG11: {=_xlfn.IFS(A11="", "", N11="MISSING", "The post tender package is missing!", O11="", "Confirm you reviewed the post tender check-in documents", AND(O11="Not yet submitted/reviewed", N11<>"Not yet submitted/reviewed"), "Post-tender package submitted; col 9 can't indicate otherwise.", TRUE, "")} | DH11: {=_xlfn.IFS(A11="", "", P11="", "Site Ownership Status cannot be blank", AND(OR(P11="Site Purchased Prior to Capital Approval", P11="Site Purchased"), Q11>TODAY()), "Site purchase date is in the future, but site ownership status indicates site is already purchased", AND(P11<>"Site Purchased Prior to Capital Approval", P11<>"Site Purchased", Q11<=TODAY()), "Site purchase date is in the past, but site ownership status indicates site has not yet been purchased", TRUE, "")} | DI11: {=_xlfn.IFS(A11="", "", R11<>"", "", P11="Not Applicable", "", Q11="", "Site Purchased Date cannot be blank", W11="", "", Q11>W11, "Site Purchase Date must preceed Site Plan Submission.", TRUE, "")} | DK11: =IF(OR(A11="", S11<>""), "", DK$7&" cannot be blank") | DL11: {=_xlfn.IFS(A11="", "", T11="", DL$7&" cannot be blank", AND(J11<>"Not yet submitted/reviewed", T11>TODAY()), DL$7&" cannot be in the future if project is ready for a pre-tender package.", TRUE, "")} | DM11: {=_xlfn.IFS(A11="", "", V11<>"", "", BY11=0, "", U11="", DM$7&" cannot be blank if project includes child care.", U11<I11, DM$7&" must preceed pre-tender package submission date", TRUE, "")} | DO11: {=_xlfn.IFS(A11="", "", W11="", DO$7&" cannot be blank", $AE11="", "", W11>$AE11, DO$7&" must preceed construction start date.", TRUE, "")} | DP11: {=_xlfn.IFS(A11="", "", Y11<>"", "", X11="", DP$7&" cannot be blank", $AE11="", "", X11>$AE11, DP$7&" must preceed construction start date.", TRUE, "")} | DR11: {=_xlfn.IFS(A11="", "", AA11<>"", "", Z11="", DR$7&" cannot be blank", $AE11="", "", Z11>$AE11, DR$7&" must preceed construction start date.", TRUE, "")} | DT11: {=_xlfn.IFS(A11="", "", AB11="", DT$7&" cannot be blank", $AE11="", "", AB11>$AE11, DT$7&" must preceed construction start date.", TRUE, "")} | DU11: {=_xlfn.IFS(A11="", "", AC11="", DU$7&" cannot be blank", $AE11="", "", AC11>$AE11, DU$7&" must preceed construction start date.", TRUE, "")} | DV11: {=_xlfn.IFS(A11="", "", AD11="", DV$7&" cannot be blank", $AE11="", "", AD11>$AE11, DV$7&" must preceed construction start date.", TRUE, "")} | DW11: {=_xlfn.IFS(A11="", "", AF11<>"", "", AE11="", DW$7&" cannot be blank", $AI11="", "", AE11>EDATE($AI11,-12), DW$7&" must preceed school opening date by more than 12 months.", TRUE, "")} | DY11: {=_xlfn.IFS(A11="", "", AH11<>"", "", AG11="", DY$7&" cannot be blank", $AI11="", "", AG11>EDATE($AI11,-1), DY$7&" must preceed school opening date by more than one month.", TRUE, "")} | EA11: {=_xlfn.IFS(A11="", "", AM11="", "", AI11="", EA$7&" cannot be blank", AJ11<>"", "", $AI11="", "", AI11>=EDATE($AM11,-11), EA$7&" must preceed financial close date by at least 12 months.", TRUE, "")} | EC11: {=_xlfn.IFS(A11="", "", BY11=0, "", AK11="", EC$7&" cannot be blank", $AM11="", "", AL11<>"", "", AK11>=EDATE($AM11,0), EC$7&" must preceed financial close date.", TRUE, "")} | EE11: {=_xlfn.IFS(A11="", "", AM11="", EE$7&" cannot be blank", TRUE, "")} | EK11: {=_xlfn.IFS(A11="", "", AS11="", "Basis of Cost Estimate cannot be blank", AND(AE11<TODAY(), AS11<>"Based on Tender Results"), "Contract awarded date suggests estimate should be based on tender results", AND(H11<TODAY(), AS11<>"Based on Class A or B Cost Report"), "If project has already come in for a pre-tender budget, they must have a class A or B cost estimate.", TRUE, "")} | EL11: {=_xlfn.IFS(A11="", "", OR(AO11=0, AO11=""), "", AT11="", EL$7&" cannot be blank.", TRUE, "")} | EM11: {=_xlfn.IFS(A11="", "", OR(AP11=0, AP11=""), "", AU11="", EM$7&" cannot be blank.", TRUE, "")} | EN11: {=_xlfn.IFS(A11="", "", OR(AQ11=0, AQ11=""), "", AV11="", EN$7&" cannot be blank.", TRUE, "")} | EO11: {=_xlfn.IFS(A11="", "", OR(AR11=0, AR11=""), "", AW11="", EO$7&" cannot be blank.", TRUE, "")} | ES11: {=_xlfn.IFS(ET11<>"", ET11, EU11<>"", EU11, EV11<>"", EV11, TRUE, "")} -> Confirm you reviewed the pretender checkin documents | ET11: =IF(J11="MISSING", "This package is missing!", "") | EU11: =IF(K11="", "Confirm you reviewed the pretender checkin documents", "") -> Confirm you reviewed the pretender checkin documents | EV11: =IF(AND(K11="Not yet submitted/reviewed", J11<>"Not yet submitted/reviewed"), "Pretender package submitted; col 9 cann't indicate otherwise.", "") | EW11: {=_xlfn.IFS(EX11<>"", EX11, EY11<>"", EY11, EZ11<>"", EZ11, TRUE, "")} -> Confirm you reviewed the post tender check-in documents | EX11: =IF(N11="MISSING", "The post tender package is missing!", "") | EY11: =IF(O11="", "Confirm you reviewed the post tender check-in documents", "") -> Confirm you reviewed the post tender check-in documents | EZ11: =IF(AND(O11="Not yet submitted/reviewed", N11<>"Not yet submitted/reviewed"), "Post-tender package submitted; col 9 cann't indicate otherwise.", "") | FA11: {=_xlfn.IFS(FB11<>"", FB11, FC11<>"", FC11, TRUE, FD11)} -> Site Ownership Status cannot be blank | FB11: =IF(P11<>"", "", "Site Ownership Status cannot be blank") -> Site Ownership Status cannot be blank | FC11: {=_xlfn.IFS(AND(Q11="", OR(P11="Site Purchased Prior to Capital Approval", P11="Site Purchased")), "", AND(OR(P11="Site Purchased Prior to Capital Approval", P11="Site Purchased"), Q11>TODAY()), "Site purchase date is in the future, but site ownership status indicates site is already purchaseed", TRUE, "")} | FD11: =IF(AND(AND(P11<>"Site Purchased Prior to Capital Approval", P11<>"Site Purchased"), Q11<=TODAY()), "Site purchase date is in the past, but site ownership status indicates site has not yet been purchaseed", "") -> Site purchase date is in the past, but site ownership status indicates site has not yet been purchaseed | FE11: {=_xlfn.IFS(FF11<>"", FF11, FG11<>"", FG11, TRUE,FH11 )} -> Site Purchased Date cannot be blank | FF11: =IF(AND(P11<>"Not Applicable",Q11=""),"Site Purchased Date cannot be blank","") -> Site Purchased Date cannot be blank | FG11: =FA11 -> Site Ownership Status cannot be blank | FH11: {=_xlfn.IFS(Q11="", "", W11="", "", Q11>W11, "Site Purchase Date must preceed Site Plan Submission.", TRUE, "")}
A86: 1 | B86: 1 | C86: 1 | D86: 1 | E86: 1 | F86: 1 | G86: 1 | H86: 1 | I86: 1 | J86: 1 | K86: 1 | L86: 1 | M86: 1 | N86: 1 | O86: 1 | P86: 1 | Q86: 1 | R86: 1 | S86: 1 | T86: 1 | U86: 1 | V86: 1 | W86: 1 | X86: 1 | Y86: 1 | Z86: 1 | AA86: 1 | AB86: 1 | AC86: 1 | AD86: 1 | AE86: 1 | AF86: 1 | AG86: 1 | AH86: 1 | AI86: 1 | AJ86: 1 | AK86: 1 | AL86: 1 | AM86: 1 | AN86: 1 | AO86: 1 | AP86: 1 | AQ86: 1 | AR86: 1 | AS86: 1 | AT86: 1 | AU86: 1 | AV86: 1 | AW86: 1 | AX86: 1 | AY86: 1 | AZ86: 1 | BA86: 1 | BB86: 1 | BC86: 1 | BD86: 1 | BE86: 1 | BF86: 1 | BG86: 1 | BH86: 1 | BI86: 1 | BJ86: 1 | BK86: 1 | BL86: 1 | BM86: 1 | BN86: 1 | BO86: 1 | BP86: 1 | BQ86: 1 | BR86: 1 | BS86: 1 | BT86: 1 | BU86: 1 | BV86: 1 | BW86: 1 | BX86: 1 | BY86: 1 | BZ86: 1 | CA86: 1 | CB86: 1 | CC86: 1 | CD86: 1 | CE86: 1 | CF86: 1 | CG86: 1 | CH86: 1 | CI86: 1 | CJ86: 1 | CK86: 1 | CL86: 1 | CM86: 1 | CN86: 1 | CO86: 1 | CP86: 1 | CQ86: 1 | CR86: 1 | CS86: 1 | CT86: 1 | CU86: 1 | CV86: 1 | CW86: 1 | CX86: 1 | CY86: 1 | CZ86: 1 | DB86: 1 | DC86: 1 | DD86: 1 | DF86: 1 | DG86: 1 | DH86: 1 | DI86: 1 | DK86: 1 | DL86: 1 | DM86: 1 | DO86: 1 | DP86: 1 | DQ86: 1 | DR86: 1 | DS86: 1 | DT86: 1 | DU86: 1 | DV86: 1 | DW86: 1 | DY86: 1 | EA86: 1 | EC86: 1 | EE86: 1 | EF86: 1 | EG86: 1 | EH86: 1 | EI86: 1 | EJ86: 1 | EK86: 1 | EL86: 1 | EM86: 1 | EN86: 1 | EO86: 1 | EP86: 1 | EQ86: 1 | ER86: 1 | ES86: 1 | ET86: 1 | EU86: 1 | EV86: 1 | EW86: 1 | EX86: 1 | EY86: 1 | EZ86: 1 | FA86: 1 | FB86: 1 | FC86: 1 | FD86: 1 | FE86: 1 | FF86: 1 | FG86: 1 | FH86: 1 | FI86: 1 | FJ86: 1 | FK86: 1 | FL86: 1 | FM86: 1 | FN86: 1 | FO86: 1 | FP86: 1 | FQ86: 1 | FR86: 1 | FS86: 1 | FT86: 1 | FU86: 1 | FV86: 1 | FW86: 1 | FX86: 1 | FY86: 1 | FZ86: 1 | GA86: 1 | GB86: 1 | GC86: 1 | GD86: 1 | GE86: 1 | GF86: 1 | GG86: 1 | GH86: 1 | GI86: 1 | GJ86: 1 | GK86: 1 | GL86: 1 | GM86: 1 | GN86: 1 | GO86: 1 | GP86: 1 | GQ86: 1 | GR86: 1 | GS86: 1 | GT86: 1 | GU86: 1 | GV86: 1 | GW86: 1 | GX86: 1 | GY86: 1 | GZ86: 1 | HA86: 1 | HB86: 1 | HC86: 1 | HD86: 1 | HE86: 1 | HF86: 1 | HG86: 1 | HH86: 1

Sheet Errors
A1: Monthly Project Updates - Error Details
A3: Meeting Date
A5: Section 1: Project Details | H5: Section 2: Project Commitment Progress | P5: Section 3: Pre-Tender | AD5: Section 4: Construction | AI5: Section 5: Project Completion | AN5: Section 6: Approved Project Funding | AS5: Section 7: Projected Cost
A6: ="Col "&COLUMN() -> Col 1 | B6: ="Col "&COLUMN() -> Col 2 | C6: ="Col "&COLUMN() -> Col 3 | D6: ="Col "&COLUMN() -> Col 4 | E6: ="Col "&COLUMN() -> Col 5 | F6: ="Col "&COLUMN() -> Col 6 | G6: ="Col "&COLUMN() -> Col 7 | H6: ="Col "&COLUMN() -> Col 8 | ... AW6: ="Col "&COLUMN() -> Col 49
A7: Project ID | B7: Project Name | C7: Meeting Minutes | D7: Project Type | E7: Project Category | F7: Record Status | G7: Construction Status | H7: Pre-Tender Submission Date | I7: Pre-Tender Package Type | J7: Pre-Tender Package Complete | K7: CA Reviewed All Pre-Tender Documents | L7: Post-Tender Submission Date | M7: Post-Tender Package Type | N7: Post-Tender Package Complete | O7: CA Reviewed All Post-Tender Documents | P7: Site Ownership Status | Q7: Site Purchase Date | R7: =Q7&" Error Explanation" -> Site Purchase Date Error Explanation | S7: Design Status | T7: Space Template Approval Date | U7: Child Care Floorplan Approval Date | V7: =U7&" Error Explanation" -> Child Care Floorplan Approval Date Error Explanation | W7: Initial Site Plan Submission Date | X7: Site Plan Approval Date | Y7: Site Plan Approval Date Error Explanation | Z7: Build Permit Obtained Date | AA7: =Z7&" Error Explanation" -> Build Permit Obtained Date Error Explanation | AB7: Tender Issued Date | AC7: Tender Closed Date | AD7: Contract Awarded Date | AE7: Construction Start Date | AF7: =AE7&" Error Explanation" -> Construction Start Date Error Explanation | AG7: Substantial Completion Date | AH7: =AG7&" Error Explanation" -> Substantial Completion Date Error Explanation | AI7: School Opening Date | AJ7: =AI7&" Error Explanation" -> School Opening Date Error Explanation | AK7: Child Care Opening Date | AL7: =AK7&" Error Explanation" -> Child Care Opening Date Error Explanation | AM7: Financial Close-Out Date | AN7: Funding - All Associated Projects | AO7: Funding - Construction Project | AP7: Funding - Site Acquisition | AQ7: Funding - Demolition | AR7: Funding - All Other Associated Projects | AS7: Basis of Cost Estimate | AT7: Estimated Cost - Construction Project | AU7: Estimated Cost - Land | AV7: Estimated Cost - Demolition | AW7: Estimated Cost - All Other Associated Projects
A8: No. de projet | B8: Nom du projet | D8: Type de projet | E8: Catégorie de projet | AP8: IP | AQ8: Service de garde | AR8: Autre | AS8: Base de l'estimation des coûts | AW8: Coûts du site
A10: {=_xlfn.IFS(LEFT('Monthly Update'!A10, 3) = "*((", "", 'Monthly Update'!A10="", "", TRUE, 'Monthly Update'!A10)} | B10: {=_xlfn.IFS(LEFT('Monthly Update'!B10, 3) = "*((", "", 'Monthly Update'!B10="", "", TRUE, 'Monthly Update'!B10)} | C10: {=_xlfn.IFS(LEFT('Monthly Update'!CU10, 3) = "*((", "", 'Monthly Update'!CU10="", "", TRUE, 'Monthly Update'!CU10)} | D10: {=_xlfn.IFS(LEFT('Monthly Update'!CV10, 3) = "*((", "", 'Monthly Update'!CV10="", "", TRUE, 'Monthly Update'!CV10)} | E10: {=_xlfn.IFS(LEFT('Monthly Update'!CW10, 3) = "*((", "", 'Monthly Update'!CW10="", "", TRUE, 'Monthly Update'!CW10)} | F10: {=_xlfn.IFS(LEFT('Monthly Update'!CX10, 3) = "*((", "", 'Monthly Update'!CX10="", "", TRUE, 'Monthly Update'!CX10)} | G10: {=_xlfn.IFS(LEFT('Monthly Update'!CY10, 3) = "*((", "", 'Monthly Update'!CY10="", "", TRUE, 'Monthly Update'!CY10)} | H10: {=_xlfn.IFS(LEFT('Monthly Update'!CZ10, 3) = "*((", "", 'Monthly Update'!CZ10="", "", TRUE, 'Monthly Update'!CZ10)} | I10: {=_xlfn.IFS(LEFT('Monthly Update'!DA10, 3) = "*((", "", 'Monthly Update'!DA10="", "", TRUE, 'Monthly Update'!DA10)} | J10: {=_xlfn.IFS(LEFT('Monthly Update'!DB10, 3) = "*((", "", 'Monthly Update'!DB10="", "", TRUE, 'Monthly Update'!DB10)} | ... AW10: {=_xlfn.IFS(LEFT('Monthly Update'!EO10, 3) = "*((", "", 'Monthly Update'!EO10="", "", TRUE, 'Monthly Update'!EO10)}
A11: {=_xlfn.IFS(LEFT('Monthly Update'!A11, 3) = "*((", "", 'Monthly Update'!A11="", "", TRUE, 'Monthly Update'!A11)} | B11: {=_xlfn.IFS(LEFT('Monthly Update'!B11, 3) = "*((", "", 'Monthly Update'!B11="", "", TRUE, 'Monthly Update'!B11)} | C11: {=_xlfn.IFS(LEFT('Monthly Update'!CU11, 3) = "*((", "", 'Monthly Update'!CU11="", "", TRUE, 'Monthly Update'!CU11)} | D11: {=_xlfn.IFS(LEFT('Monthly Update'!CV11, 3) = "*((", "", 'Monthly Update'!CV11="", "", TRUE, 'Monthly Update'!CV11)} | E11: {=_xlfn.IFS(LEFT('Monthly Update'!CW11, 3) = "*((", "", 'Monthly Update'!CW11="", "", TRUE, 'Monthly Update'!CW11)} | F11: {=_xlfn.IFS(LEFT('Monthly Update'!CX11, 3) = "*((", "", 'Monthly Update'!CX11="", "", TRUE, 'Monthly Update'!CX11)} | G11: {=_xlfn.IFS(LEFT('Monthly Update'!CY11, 3) = "*((", "", 'Monthly Update'!CY11="", "", TRUE, 'Monthly Update'!CY11)} | H11: {=_xlfn.IFS(LEFT('Monthly Update'!CZ11, 3) = "*((", "", 'Monthly Update'!CZ11="", "", TRUE, 'Monthly Update'!CZ11)} | I11: {=_xlfn.IFS(LEFT('Monthly Update'!DA11, 3) = "*((", "", 'Monthly Update'!DA11="", "", TRUE, 'Monthly Update'!DA11)} | J11: {=_xlfn.IFS(LEFT('Monthly Update'!DB11, 3) = "*((", "", 'Monthly Update'!DB11="", "", TRUE, 'Monthly Update'!DB11)} | ... AW11: {=_xlfn.IFS(LEFT('Monthly Update'!EO11, 3) = "*((", "", 'Monthly Update'!EO11="", "", TRUE, 'Monthly Update'!EO11)}
A12: {=_xlfn.IFS(LEFT('Monthly Update'!A12, 3) = "*((", "", 'Monthly Update'!A12="", "", TRUE, 'Monthly Update'!A12)} | B12: {=_xlfn.IFS(LEFT('Monthly Update'!B12, 3) = "*((", "", 'Monthly Update'!B12="", "", TRUE, 'Monthly Update'!B12)} | C12: {=_xlfn.IFS(LEFT('Monthly Update'!CU12, 3) = "*((", "", 'Monthly Update'!CU12="", "", TRUE, 'Monthly Update'!CU12)} | D12: {=_xlfn.IFS(LEFT('Monthly Update'!CV12, 3) = "*((", "", 'Monthly Update'!CV12="", "", TRUE, 'Monthly Update'!CV12)} | E12: {=_xlfn.IFS(LEFT('Monthly Update'!CW12, 3) = "*((", "", 'Monthly Update'!CW12="", "", TRUE, 'Monthly Update'!CW12)} | F12: {=_xlfn.IFS(LEFT('Monthly Update'!CX12, 3) = "*((", "", 'Monthly Update'!CX12="", "", TRUE, 'Monthly Update'!CX12)} | G12: {=_xlfn.IFS(LEFT('Monthly Update'!CY12, 3) = "*((", "", 'Monthly Update'!CY12="", "", TRUE, 'Monthly Update'!CY12)} | H12: {=_xlfn.IFS(LEFT('Monthly Update'!CZ12, 3) = "*((", "", 'Monthly Update'!CZ12="", "", TRUE, 'Monthly Update'!CZ12)} | I12: {=_xlfn.IFS(LEFT('Monthly Update'!DA12, 3) = "*((", "", 'Monthly Update'!DA12="", "", TRUE, 'Monthly Update'!DA12)} | J12: {=_xlfn.IFS(LEFT('Monthly Update'!DB12, 3) = "*((", "", 'Monthly Update'!DB12="", "", TRUE, 'Monthly Update'!DB12)} | ... AW12: {=_xlfn.IFS(LEFT('Monthly Update'!EO12, 3) = "*((", "", 'Monthly Update'!EO12="", "", TRUE, 'Monthly Update'!EO12)}
A13: {=_xlfn.IFS(LEFT('Monthly Update'!A13, 3) = "*((", "", 'Monthly Update'!A13="", "", TRUE, 'Monthly Update'!A13)} | B13: {=_xlfn.IFS(LEFT('Monthly Update'!B13, 3) = "*((", "", 'Monthly Update'!B13="", "", TRUE, 'Monthly Update'!B13)} | C13: {=_xlfn.IFS(LEFT('Monthly Update'!CU13, 3) = "*((", "", 'Monthly Update'!CU13="", "", TRUE, 'Monthly Update'!CU13)} | D13: {=_xlfn.IFS(LEFT('Monthly Update'!CV13, 3) = "*((", "", 'Monthly Update'!CV13="", "", TRUE, 'Monthly Update'!CV13)} | E13: {=_xlfn.IFS(LEFT('Monthly Update'!CW13, 3) = "*((", "", 'Monthly Update'!CW13="", "", TRUE, 'Monthly Update'!CW13)} | F13: {=_xlfn.IFS(LEFT('Monthly Update'!CX13, 3) = "*((", "", 'Monthly Update'!CX13="", "", TRUE, 'Monthly Update'!CX13)} | G13: {=_xlfn.IFS(LEFT('Monthly Update'!CY13, 3) = "*((", "", 'Monthly Update'!CY13="", "", TRUE, 'Monthly Update'!CY13)} | H13: {=_xlfn.IFS(LEFT('Monthly Update'!CZ13, 3) = "*((", "", 'Monthly Update'!CZ13="", "", TRUE, 'Monthly Update'!CZ13)} | I13: {=_xlfn.IFS(LEFT('Monthly Update'!DA13, 3) = "*((", "", 'Monthly Update'!DA13="", "", TRUE, 'Monthly Update'!DA13)} | J13: {=_xlfn.IFS(LEFT('Monthly Update'!DB13, 3) = "*((", "", 'Monthly Update'!DB13="", "", TRUE, 'Monthly Update'!DB13)} | ... AW13: {=_xlfn.IFS(LEFT('Monthly Update'!EO13, 3) = "*((", "", 'Monthly Update'!EO13="", "", TRUE, 'Monthly Update'!EO13)}
A14: {=_xlfn.IFS(LEFT('Monthly Update'!A14, 3) = "*((", "", 'Monthly Update'!A14="", "", TRUE, 'Monthly Update'!A14)} | B14: {=_xlfn.IFS(LEFT('Monthly Update'!B14, 3) = "*((", "", 'Monthly Update'!B14="", "", TRUE, 'Monthly Update'!B14)} | C14: {=_xlfn.IFS(LEFT('Monthly Update'!CU14, 3) = "*((", "", 'Monthly Update'!CU14="", "", TRUE, 'Monthly Update'!CU14)} | D14: {=_xlfn.IFS(LEFT('Monthly Update'!CV14, 3) = "*((", "", 'Monthly Update'!CV14="", "", TRUE, 'Monthly Update'!CV14)} | E14: {=_xlfn.IFS(LEFT('Monthly Update'!CW14, 3) = "*((", "", 'Monthly Update'!CW14="", "", TRUE, 'Monthly Update'!CW14)} | F14: {=_xlfn.IFS(LEFT('Monthly Update'!CX14, 3) = "*((", "", 'Monthly Update'!CX14="", "", TRUE, 'Monthly Update'!CX14)} | G14: {=_xlfn.IFS(LEFT('Monthly Update'!CY14, 3) = "*((", "", 'Monthly Update'!CY14="", "", TRUE, 'Monthly Update'!CY14)} | H14: {=_xlfn.IFS(LEFT('Monthly Update'!CZ14, 3) = "*((", "", 'Monthly Update'!CZ14="", "", TRUE, 'Monthly Update'!CZ14)} | I14: {=_xlfn.IFS(LEFT('Monthly Update'!DA14, 3) = "*((", "", 'Monthly Update'!DA14="", "", TRUE, 'Monthly Update'!DA14)} | J14: {=_xlfn.IFS(LEFT('Monthly Update'!DB14, 3) = "*((", "", 'Monthly Update'!DB14="", "", TRUE, 'Monthly Update'!DB14)} | ... AW14: {=_xlfn.IFS(LEFT('Monthly Update'!EO14, 3) = "*((", "", 'Monthly Update'!EO14="", "", TRUE, 'Monthly Update'!EO14)}
A15: {=_xlfn.IFS(LEFT('Monthly Update'!A15, 3) = "*((", "", 'Monthly Update'!A15="", "", TRUE, 'Monthly Update'!A15)} | B15: {=_xlfn.IFS(LEFT('Monthly Update'!B15, 3) = "*((", "", 'Monthly Update'!B15="", "", TRUE, 'Monthly Update'!B15)} | C15: {=_xlfn.IFS(LEFT('Monthly Update'!CU15, 3) = "*((", "", 'Monthly Update'!CU15="", "", TRUE, 'Monthly Update'!CU15)} | D15: {=_xlfn.IFS(LEFT('Monthly Update'!CV15, 3) = "*((", "", 'Monthly Update'!CV15="", "", TRUE, 'Monthly Update'!CV15)} | E15: {=_xlfn.IFS(LEFT('Monthly Update'!CW15, 3) = "*((", "", 'Monthly Update'!CW15="", "", TRUE, 'Monthly Update'!CW15)} | F15: {=_xlfn.IFS(LEFT('Monthly Update'!CX15, 3) = "*((", "", 'Monthly Update'!CX15="", "", TRUE, 'Monthly Update'!CX15)} | G15: {=_xlfn.IFS(LEFT('Monthly Update'!CY15, 3) = "*((", "", 'Monthly Update'!CY15="", "", TRUE, 'Monthly Update'!CY15)} | H15: {=_xlfn.IFS(LEFT('Monthly Update'!CZ15, 3) = "*((", "", 'Monthly Update'!CZ15="", "", TRUE, 'Monthly Update'!CZ15)} | I15: {=_xlfn.IFS(LEFT('Monthly Update'!DA15, 3) = "*((", "", 'Monthly Update'!DA15="", "", TRUE, 'Monthly Update'!DA15)} | J15: {=_xlfn.IFS(LEFT('Monthly Update'!DB15, 3) = "*((", "", 'Monthly Update'!DB15="", "", TRUE, 'Monthly Update'!DB15)} | ... AW15: {=_xlfn.IFS(LEFT('Monthly Update'!EO15, 3) = "*((", "", 'Monthly Update'!EO15="", "", TRUE, 'Monthly Update'!EO15)}
A16: {=_xlfn.IFS(LEFT('Monthly Update'!A16, 3) = "*((", "", 'Monthly Update'!A16="", "", TRUE, 'Monthly Update'!A16)} | B16: {=_xlfn.IFS(LEFT('Monthly Update'!B16, 3) = "*((", "", 'Monthly Update'!B16="", "", TRUE, 'Monthly Update'!B16)} | C16: {=_xlfn.IFS(LEFT('Monthly Update'!CU16, 3) = "*((", "", 'Monthly Update'!CU16="", "", TRUE, 'Monthly Update'!CU16)} | D16: {=_xlfn.IFS(LEFT('Monthly Update'!CV16, 3) = "*((", "", 'Monthly Update'!CV16="", "", TRUE, 'Monthly Update'!CV16)} | E16: {=_xlfn.IFS(LEFT('Monthly Update'!CW16, 3) = "*((", "", 'Monthly Update'!CW16="", "", TRUE, 'Monthly Update'!CW16)} | F16: {=_xlfn.IFS(LEFT('Monthly Update'!CX16, 3) = "*((", "", 'Monthly Update'!CX16="", "", TRUE, 'Monthly Update'!CX16)} | G16: {=_xlfn.IFS(LEFT('Monthly Update'!CY16, 3) = "*((", "", 'Monthly Update'!CY16="", "", TRUE, 'Monthly Update'!CY16)} | H16: {=_xlfn.IFS(LEFT('Monthly Update'!CZ16, 3) = "*((", "", 'Monthly Update'!CZ16="", "", TRUE, 'Monthly Update'!CZ16)} | I16: {=_xlfn.IFS(LEFT('Monthly Update'!DA16, 3) = "*((", "", 'Monthly Update'!DA16="", "", TRUE, 'Monthly Update'!DA16)} | J16: {=_xlfn.IFS(LEFT('Monthly Update'!DB16, 3) = "*((", "", 'Monthly Update'!DB16="", "", TRUE, 'Monthly Update'!DB16)} | ... AW16: {=_xlfn.IFS(LEFT('Monthly Update'!EO16, 3) = "*((", "", 'Monthly Update'!EO16="", "", TRUE, 'Monthly Update'!EO16)}
A17: {=_xlfn.IFS(LEFT('Monthly Update'!A17, 3) = "*((", "", 'Monthly Update'!A17="", "", TRUE, 'Monthly Update'!A17)} | B17: {=_xlfn.IFS(LEFT('Monthly Update'!B17, 3) = "*((", "", 'Monthly Update'!B17="", "", TRUE, 'Monthly Update'!B17)} | C17: {=_xlfn.IFS(LEFT('Monthly Update'!CU17, 3) = "*((", "", 'Monthly Update'!CU17="", "", TRUE, 'Monthly Update'!CU17)} | D17: {=_xlfn.IFS(LEFT('Monthly Update'!CV17, 3) = "*((", "", 'Monthly Update'!CV17="", "", TRUE, 'Monthly Update'!CV17)} | E17: {=_xlfn.IFS(LEFT('Monthly Update'!CW17, 3) = "*((", "", 'Monthly Update'!CW17="", "", TRUE, 'Monthly Update'!CW17)} | F17: {=_xlfn.IFS(LEFT('Monthly Update'!CX17, 3) = "*((", "", 'Monthly Update'!CX17="", "", TRUE, 'Monthly Update'!CX17)} | G17: {=_xlfn.IFS(LEFT('Monthly Update'!CY17, 3) = "*((", "", 'Monthly Update'!CY17="", "", TRUE, 'Monthly Update'!CY17)} | H17: {=_xlfn.IFS(LEFT('Monthly Update'!CZ17, 3) = "*((", "", 'Monthly Update'!CZ17="", "", TRUE, 'Monthly Update'!CZ17)} | I17: {=_xlfn.IFS(LEFT('Monthly Update'!DA17, 3) = "*((", "", 'Monthly Update'!DA17="", "", TRUE, 'Monthly Update'!DA17)} | J17: {=_xlfn.IFS(LEFT('Monthly Update'!DB17, 3) = "*((", "", 'Monthly Update'!DB17="", "", TRUE, 'Monthly Update'!DB17)} | ... AW17: {=_xlfn.IFS(LEFT('Monthly Update'!EO17, 3) = "*((", "", 'Monthly Update'!EO17="", "", TRUE, 'Monthly Update'!EO17)}
A18: {=_xlfn.IFS(LEFT('Monthly Update'!A18, 3) = "*((", "", 'Monthly Update'!A18="", "", TRUE, 'Monthly Update'!A18)} | B18: {=_xlfn.IFS(LEFT('Monthly Update'!B18, 3) = "*((", "", 'Monthly Update'!B18="", "", TRUE, 'Monthly Update'!B18)} | C18: {=_xlfn.IFS(LEFT('Monthly Update'!CU18, 3) = "*((", "", 'Monthly Update'!CU18="", "", TRUE, 'Monthly Update'!CU18)} | D18: {=_xlfn.IFS(LEFT('Monthly Update'!CV18, 3) = "*((", "", 'Monthly Update'!CV18="", "", TRUE, 'Monthly Update'!CV18)} | E18: {=_xlfn.IFS(LEFT('Monthly Update'!CW18, 3) = "*((", "", 'Monthly Update'!CW18="", "", TRUE, 'Monthly Update'!CW18)} | F18: {=_xlfn.IFS(LEFT('Monthly Update'!CX18, 3) = "*((", "", 'Monthly Update'!CX18="", "", TRUE, 'Monthly Update'!CX18)} | G18: {=_xlfn.IFS(LEFT('Monthly Update'!CY18, 3) = "*((", "", 'Monthly Update'!CY18="", "", TRUE, 'Monthly Update'!CY18)} | H18: {=_xlfn.IFS(LEFT('Monthly Update'!CZ18, 3) = "*((", "", 'Monthly Update'!CZ18="", "", TRUE, 'Monthly Update'!CZ18)} | I18: {=_xlfn.IFS(LEFT('Monthly Update'!DA18, 3) = "*((", "", 'Monthly Update'!DA18="", "", TRUE, 'Monthly Update'!DA18)} | J18: {=_xlfn.IFS(LEFT('Monthly Update'!DB18, 3) = "*((", "", 'Monthly Update'!DB18="", "", TRUE, 'Monthly Update'!DB18)} | ... AW18: {=_xlfn.IFS(LEFT('Monthly Update'!EO18, 3) = "*((", "", 'Monthly Update'!EO18="", "", TRUE, 'Monthly Update'!EO18)}
A19: {=_xlfn.IFS(LEFT('Monthly Update'!A19, 3) = "*((", "", 'Monthly Update'!A19="", "", TRUE, 'Monthly Update'!A19)} | B19: {=_xlfn.IFS(LEFT('Monthly Update'!B19, 3) = "*((", "", 'Monthly Update'!B19="", "", TRUE, 'Monthly Update'!B19)} | C19: {=_xlfn.IFS(LEFT('Monthly Update'!CU19, 3) = "*((", "", 'Monthly Update'!CU19="", "", TRUE, 'Monthly Update'!CU19)} | D19: {=_xlfn.IFS(LEFT('Monthly Update'!CV19, 3) = "*((", "", 'Monthly Update'!CV19="", "", TRUE, 'Monthly Update'!CV19)} | E19: {=_xlfn.IFS(LEFT('Monthly Update'!CW19, 3) = "*((", "", 'Monthly Update'!CW19="", "", TRUE, 'Monthly Update'!CW19)} | F19: {=_xlfn.IFS(LEFT('Monthly Update'!CX19, 3) = "*((", "", 'Monthly Update'!CX19="", "", TRUE, 'Monthly Update'!CX19)} | G19: {=_xlfn.IFS(LEFT('Monthly Update'!CY19, 3) = "*((", "", 'Monthly Update'!CY19="", "", TRUE, 'Monthly Update'!CY19)} | H19: {=_xlfn.IFS(LEFT('Monthly Update'!CZ19, 3) = "*((", "", 'Monthly Update'!CZ19="", "", TRUE, 'Monthly Update'!CZ19)} | I19: {=_xlfn.IFS(LEFT('Monthly Update'!DA19, 3) = "*((", "", 'Monthly Update'!DA19="", "", TRUE, 'Monthly Update'!DA19)} | J19: {=_xlfn.IFS(LEFT('Monthly Update'!DB19, 3) = "*((", "", 'Monthly Update'!DB19="", "", TRUE, 'Monthly Update'!DB19)} | ... AW19: {=_xlfn.IFS(LEFT('Monthly Update'!EO19, 3) = "*((", "", 'Monthly Update'!EO19="", "", TRUE, 'Monthly Update'!EO19)}
A20: {=_xlfn.IFS(LEFT('Monthly Update'!A20, 3) = "*((", "", 'Monthly Update'!A20="", "", TRUE, 'Monthly Update'!A20)} | B20: {=_xlfn.IFS(LEFT('Monthly Update'!B20, 3) = "*((", "", 'Monthly Update'!B20="", "", TRUE, 'Monthly Update'!B20)} | C20: {=_xlfn.IFS(LEFT('Monthly Update'!CU20, 3) = "*((", "", 'Monthly Update'!CU20="", "", TRUE, 'Monthly Update'!CU20)} | D20: {=_xlfn.IFS(LEFT('Monthly Update'!CV20, 3) = "*((", "", 'Monthly Update'!CV20="", "", TRUE, 'Monthly Update'!CV20)} | E20: {=_xlfn.IFS(LEFT('Monthly Update'!CW20, 3) = "*((", "", 'Monthly Update'!CW20="", "", TRUE, 'Monthly Update'!CW20)} | F20: {=_xlfn.IFS(LEFT('Monthly Update'!CX20, 3) = "*((", "", 'Monthly Update'!CX20="", "", TRUE, 'Monthly Update'!CX20)} | G20: {=_xlfn.IFS(LEFT('Monthly Update'!CY20, 3) = "*((", "", 'Monthly Update'!CY20="", "", TRUE, 'Monthly Update'!CY20)} | H20: {=_xlfn.IFS(LEFT('Monthly Update'!CZ20, 3) = "*((", "", 'Monthly Update'!CZ20="", "", TRUE, 'Monthly Update'!CZ20)} | I20: {=_xlfn.IFS(LEFT('Monthly Update'!DA20, 3) = "*((", "", 'Monthly Update'!DA20="", "", TRUE, 'Monthly Update'!DA20)} | J20: {=_xlfn.IFS(LEFT('Monthly Update'!DB20, 3) = "*((", "", 'Monthly Update'!DB20="", "", TRUE, 'Monthly Update'!DB20)} | ... AW20: {=_xlfn.IFS(LEFT('Monthly Update'!EO20, 3) = "*((", "", 'Monthly Update'!EO20="", "", TRUE, 'Monthly Update'!EO20)}
A21: {=_xlfn.IFS(LEFT('Monthly Update'!A21, 3) = "*((", "", 'Monthly Update'!A21="", "", TRUE, 'Monthly Update'!A21)} | B21: {=_xlfn.IFS(LEFT('Monthly Update'!B21, 3) = "*((", "", 'Monthly Update'!B21="", "", TRUE, 'Monthly Update'!B21)} | C21: {=_xlfn.IFS(LEFT('Monthly Update'!CU21, 3) = "*((", "", 'Monthly Update'!CU21="", "", TRUE, 'Monthly Update'!CU21)} | D21: {=_xlfn.IFS(LEFT('Monthly Update'!CV21, 3) = "*((", "", 'Monthly Update'!CV21="", "", TRUE, 'Monthly Update'!CV21)} | E21: {=_xlfn.IFS(LEFT('Monthly Update'!CW21, 3) = "*((", "", 'Monthly Update'!CW21="", "", TRUE, 'Monthly Update'!CW21)} | F21: {=_xlfn.IFS(LEFT('Monthly Update'!CX21, 3) = "*((", "", 'Monthly Update'!CX21="", "", TRUE, 'Monthly Update'!CX21)} | G21: {=_xlfn.IFS(LEFT('Monthly Update'!CY21, 3) = "*((", "", 'Monthly Update'!CY21="", "", TRUE, 'Monthly Update'!CY21)} | H21: {=_xlfn.IFS(LEFT('Monthly Update'!CZ21, 3) = "*((", "", 'Monthly Update'!CZ21="", "", TRUE, 'Monthly Update'!CZ21)} | I21: {=_xlfn.IFS(LEFT('Monthly Update'!DA21, 3) = "*((", "", 'Monthly Update'!DA21="", "", TRUE, 'Monthly Update'!DA21)} | J21: {=_xlfn.IFS(LEFT('Monthly Update'!DB21, 3) = "*((", "", 'Monthly Update'!DB21="", "", TRUE, 'Monthly Update'!DB21)} | ... AW21: {=_xlfn.IFS(LEFT('Monthly Update'!EO21, 3) = "*((", "", 'Monthly Update'!EO21="", "", TRUE, 'Monthly Update'!EO21)}
... A85: {=_xlfn.IFS(LEFT('Monthly Update'!A85, 3) = "*((", "", 'Monthly Update'!A85="", "", TRUE, 'Monthly Update'!A85)} | B85: {=_xlfn.IFS(LEFT('Monthly Update'!B85, 3) = "*((", "", 'Monthly Update'!B85="", "", TRUE, 'Monthly Update'!B85)} | C85: {=_xlfn.IFS(LEFT('Monthly Update'!CU85, 3) = "*((", "", 'Monthly Update'!CU85="", "", TRUE, 'Monthly Update'!CU85)} | D85: {=_xlfn.IFS(LEFT('Monthly Update'!CV85, 3) = "*((", "", 'Monthly Update'!CV85="", "", TRUE, 'Monthly Update'!CV85)} | E85: {=_xlfn.IFS(LEFT('Monthly Update'!CW85, 3) = "*((", "", 'Monthly Update'!CW85="", "", TRUE, 'Monthly Update'!CW85)} | F85: {=_xlfn.IFS(LEFT('Monthly Update'!CX85, 3) = "*((", "", 'Monthly Update'!CX85="", "", TRUE, 'Monthly Update'!CX85)} | G85: {=_xlfn.IFS(LEFT('Monthly Update'!CY85, 3) = "*((", "", 'Monthly Update'!CY85="", "", TRUE, 'Monthly Update'!CY85)} | H85: {=_xlfn.IFS(LEFT('Monthly Update'!CZ85, 3) = "*((", "", 'Monthly Update'!CZ85="", "", TRUE, 'Monthly Update'!CZ85)} | I85: {=_xlfn.IFS(LEFT('Monthly Update'!DA85, 3) = "*((", "", 'Monthly Update'!DA85="", "", TRUE, 'Monthly Update'!DA85)} | J85: {=_xlfn.IFS(LEFT('Monthly Update'!DB85, 3) = "*((", "", 'Monthly Update'!DB85="", "", TRUE, 'Monthly Update'!DB85)} | ... AW85: {=_xlfn.IFS(LEFT('Monthly Update'!EO85, 3) = "*((", "", 'Monthly Update'!EO85="", "", TRUE, 'Monthly Update'!EO85)}
A86: 1 | B86: 1 | C86: {=_xlfn.IFS(LEFT('Monthly Update'!CU86, 3) = "*((", "", 'Monthly Update'!CU86="", "", TRUE, 'Monthly Update'!CU86)} -> 1 | D86: {=_xlfn.IFS(LEFT('Monthly Update'!CV86, 3) = "*((", "", 'Monthly Update'!CV86="", "", TRUE, 'Monthly Update'!CV86)} -> 1 | E86: {=_xlfn.IFS(LEFT('Monthly Update'!CW86, 3) = "*((", "", 'Monthly Update'!CW86="", "", TRUE, 'Monthly Update'!CW86)} -> 1 | F86: {=_xlfn.IFS(LEFT('Monthly Update'!CX86, 3) = "*((", "", 'Monthly Update'!CX86="", "", TRUE, 'Monthly Update'!CX86)} -> 1 | G86: {=_xlfn.IFS(LEFT('Monthly Update'!CY86, 3) = "*((", "", 'Monthly Update'!CY86="", "", TRUE, 'Monthly Update'!CY86)} -> 1 | H86: {=_xlfn.IFS(LEFT('Monthly Update'!CZ86, 3) = "*((", "", 'Monthly Update'!CZ86="", "", TRUE, 'Monthly Update'!CZ86)} -> 1 | I86: {=_xlfn.IFS(LEFT('Monthly Update'!DA86, 3) = "*((", "", 'Monthly Update'!DA86="", "", TRUE, 'Monthly Update'!DA86)} | J86: {=_xlfn.IFS(LEFT('Monthly Update'!DB86, 3) = "*((", "", 'Monthly Update'!DB86="", "", TRUE, 'Monthly Update'!DB86)} -> 1 | ... AW86: {=_xlfn.IFS(LEFT('Monthly Update'!EO86, 3) = "*((", "", 'Monthly Update'!EO86="", "", TRUE, 'Monthly Update'!EO86)} -> 1 | AX86: 1 | AY86: 1 | AZ86: 1 | BA86: 1 | BB86: 1 | BC86: 1 | BD86: 1 | BE86: 1 | BF86: 1 | BG86: 1 | BH86: 1 | BI86: 1 | BJ86: 1 | BK86: 1 | BL86: 1 | BM86: 1 | BN86: 1 | BO86: 1 | BP86: 1 | BQ86: 1 | BR86: 1 | BS86: 1 | BT86: 1 | BU86: 1 | BV86: 1 | BW86: 1 | BX86: 1 | BY86: 1 | BZ86: 1 | CA86: 1 | CB86: 1 | CC86: 1 | CD86: 1 | CE86: 1 | CF86: 1 | CG86: 1 | CH86: 1 | CI86: 1 | CJ86: 1 | CK86: 1 | CL86: 1 | CM86: 1 | CN86: 1

Sheet Ad-Hoc or Potential Projects
A1: Ad-hoc & Potential Projects
A2: Parent ID | B2: Project ID | C2: Project Name | D2: Submission Type | E2: Project Type | F2: Year Open | G2: Project Category | H2: Project Type | I2: Timing | J2: Cost | K2: Funding Source | L2: Comments
B3: 99-123 | C3: Example Project | D3: Ad Hoc | E3: Land | F3: 2025 | G3: Accommodation Pressure | H3: Land

Sheet Project Commitment
A1: Project Commitments
A2: English | B2: =COLUMN() -> 2 | C2: =COLUMN() -> 3 | D2: =COLUMN() -> 4 | E2: =COLUMN() -> 5 | F2: =COLUMN() -> 6 | G2: =COLUMN() -> 7 | H2: =COLUMN() -> 8 | I2: =COLUMN() -> 9 | ... L2: =COLUMN() -> 12
A3: =Translation!A97 -> Project Info | C3: =Translation!A110 -> Key Milestones
A4: =Translation!A99 -> Project ID | B4: =Translation!A100 -> Project Name | C4: =Translation!A111 -> Site Purchase | D4: Space Template Approved | E4: Site Plan Approved | F4: Pre-Tender Checkin | G4: Tender Approved | H4: Post-Tender Checkin | I4: Construction Start | J4: Substantial Completion | K4: =Translation!A120 -> School/Addition Opening | L4: Financial Close | M4: ='Monthly Update'!Q7 -> Site Purchase Date | N4: ='Monthly Update'!T7 -> Space Template Approval Date | O4: ='Monthly Update'!U7 -> Child Care Floorplan Approval Date | P4: ='Monthly Update'!W7 -> Initial Site Plan Submission Date | Q4: ='Monthly Update'!X7 -> Site Plan Approval Date | R4: ='Monthly Update'!Z7 -> Build Permit Obtained Date | S4: ='Monthly Update'!H7 -> Pre-Tender Submission Date | T4: ='Monthly Update'!AB7 -> Tender Issued Date | U4: ='Monthly Update'!AC7 -> Tender Closed Date | V4: ='Monthly Update'!L7 -> Post-Tender Submission Date | W4: ='Monthly Update'!AD7 -> Contract Awarded Date | X4: ='Monthly Update'!AE7 -> Construction Start Date | Y4: ='Monthly Update'!AG7 -> Substantial Completion Date | Z4: ='Monthly Update'!AI7 -> School Opening Date | AA4: ='Monthly Update'!AK7 -> Child Care Opening Date | AB4: ='Monthly Update'!AM7 -> Financial Close-Out Date
A5: *((tbl*((pc*((col*((project_id | B5: *((col*((project_name | C5: *((col*((date_site_purchase | D5: *((col*((date_space_template | E5: *((col*((date_site_plan_approved | F5: *((col*((date_pretender | G5: *((col*((date_tender | H5: *((col*((date_posttender | I5: *((col*((date_construction | J5: *((col*((date_substantial_completion | K5: *((col*((date_opening | L5: *((col*((date_completion | M5: =C5&"_comparison*((formula*((down" -> *((col*((date_site_purchase_comparison*((formula*((down | N5: =D5&"_comparison*((formula*((down" -> *((col*((date_space_template_comparison*((formula*((down | O5: =E5&"_comparison*((formula*((down" -> *((col*((date_site_plan_approved_comparison*((formula*((down | P5: =F5&"_comparison*((formula*((down" -> *((col*((date_pretender_comparison*((formula*((down | Q5: =G5&"_comparison*((formula*((down" -> *((col*((date_tender_comparison*((formula*((down | R5: =H5&"_comparison*((formula*((down" -> *((col*((date_posttender_comparison*((formula*((down | S5: =I5&"_comparison*((formula*((down" -> *((col*((date_construction_comparison*((formula*((down | T5: =J5&"_comparison*((formula*((down" -> *((col*((date_substantial_completion_comparison*((formula*((down | ... AB5: =R5&"_comparison*((formula*((down" -> *((col*((date_posttender_comparison*((formula*((down_comparison*((formula*((down
M6: =C6-SUMIF('Monthly Update'!$A:$A,'Project Commitment'!$A6, 'Monthly Update'!Q:Q) -> 0 | N6: =D6-SUMIF('Monthly Update'!$A:$A,'Project Commitment'!$A6, 'Monthly Update'!T:T) -> 0 | O6: =0 -> 0 | P6: =0 -> 0 | Q6: =E6-SUMIF('Monthly Update'!$A:$A,'Project Commitment'!$A6, 'Monthly Update'!X:X) -> 0 | R6: =0 -> 0 | S6: =F6-SUMIF('Monthly Update'!$A:$A,'Project Commitment'!$A6, 'Monthly Update'!H:H) -> 0 | T6: =0 -> 0 | U6: =G6-SUMIF('Monthly Update'!$A:$A,'Project Commitment'!$A6, 'Monthly Update'!AC:AC) -> 0 | V6: =H6-SUMIF('Monthly Update'!$A:$A,'Project Commitment'!$A6, 'Monthly Update'!L:L) -> 0 | W6: =0 -> 0 | X6: =I6-SUMIF('Monthly Update'!$A:$A,'Project Commitment'!$A6, 'Monthly Update'!AE:AE) -> 0 | Y6: =J6-SUMIF('Monthly Update'!$A:$A,'Project Commitment'!$A6, 'Monthly Update'!AG:AG) -> 0 | Z6: =K6-SUMIF('Monthly Update'!$A:$A,'Project Commitment'!$A6, 'Monthly Update'!AI:AI) -> 0 | AA6: =0 -> 0 | AB6: =L6-SUMIF('Monthly Update'!$A:$A,'Project Commitment'!$A6, 'Monthly Update'!AM:AM) -> 0

Sheet Constants
A1: Constants
A3: Orange Date | B3: =-365*0.75 -> -273.75
A4: Red Date | B4: -365

Sheet List
A1: Actual/Estimated | B1: Language | C1: Construction Status | D1: Phase | E1: Yes / No | F1: Site Ownership Status | G1: Design Status | H1: Cost Basis | I1: Design | J1: Site Plan | K1: Project Category | L1: Project Type | M1: Package Type
A2: Actual | B2: English | C2: Planning | D2: 1 | E2: Yes | F2: No Site Identified | G2: <30% Complete | H2: Based on estimate of $/sq ft | I2: New | J2: Yes | K2: Accommodation Pressure | L2: Land | M2: Within Budget
A3: Estimate | B3: French | C3: Pre-Procurement | D3: 1 | E3: No | F3: Site Identified Only | G3: 30%-80% Complete | H3: Based on repeat design | I3: Repeat | J3: No | K3: Facility Condition | L3: New School | M3: Additional Funding Required
C4: Tender Issuance | D4: 1 | E4: Not Applicable | F4: Site Under Option Agreement | G4: >80% Complete | H4: Based on Class C or lower Cost Report | I4: EDU Catalogue | K4: School Consolidation | L4: Addition | M4: Not Applicable
C5: Tender Closed | D5: 1 | F5: Site Purchased | H5: Based on Class A or B Cost Report | K5: French Language Access | L5: Renovation | M5: Not Yet Known
C6: Contract Awarded | D6: 1 | F6: Site Purchased Prior to Capital Approval | H6: Based on Tender Results | K6: Other | L6: Disposition
C7: Site Preparation | D7: 2 | F7: Not Applicable | L7: Demolition
C8: Construction | D8: 2 | L8: Purchase
C9: Substantial Completion | D9: 3 | L9: Other
C10: Completion | D10: 4
C11: Cost Reconciliation
A13: % Construction Progress | C13: Phase (List) | D13: Project Status | E13: Submission Type | F13: Project Risks | G13: Risk Rating | H13: Site Funding Source | I13: Mitigation Strategies | J13: Sign Installed
A14: 10 | C14: 0 | D14: In Progress | E14: CP | F14: Cost | G14: Low | H14: EDC | I14: Accept | J14: Yes
A15: 20 | C15: 1 | D15: Remove from tracker (Cancelled) | E15: Ad Hoc | F15: Delay | G15: Medium | H15: LP | I15: Mitigate | J15: No
A16: 30 | C16: 2 | D16: Remove from tracker (Complete) | F16: Delay/Cost | G16: High | H16: LP/EDC | I16: Transfer | J16: No Site Purchased
A17: 40 | C17: 3 | I17: Avoid
A18: 50 | C18: 4 | F18: Market Risk
A19: 60 | F19: Governance Risk
A20: 70 | F20: Organization/Project Management Risk
A21: 80 | F21: Design Risk
A22: 90 | F22: Procurement/Tender Risk
A23: 100 | F23: Site Readiness/Enabling Works
F24: Permit, Licenses and Approvals
A25: Type of Design | F25: Construction Risk
A26: New | F26: Testing and Commissioning
A27: Repeat
A28: Catalogue
B32: Primary Contact
B33: Senior Buisness Official
B34: Director of Education
B35: Finance Contact
B36: Construction/Project Management Contact

Sheet Translation
A1: ='Project Commitment'!A2 -> English
A2: Output | B2: English | C2: French
A3: Monthly Update Sheet
A4: =IF($A$1="English",B4,C4) -> Meeting Date | B4: Meeting Date
A5: =IF($A$1="English",B5,C5) -> Section 1: Project Details | B5: Section 1: Project Details | C5: Détails associés aux projets
A6: =IF($A$1="English",B6,C6) -> Project ID | B6: Project ID
A7: =IF($A$1="English",B7,C7) -> Project Name | B7: Project Name
A8: =IF($A$1="English",B8,C8) -> Address | B8: Address
A9: =IF($A$1="English",B9,C9) -> City | B9: City
A10: =IF($A$1="English",B10,C10) -> Postal Code | B10: Postal Code
A11: =IF($A$1="English",B11,C11) -> Project Type | B11: Project Type
A12: =IF($A$1="English",B12,C12) -> Approval Period | B12: Approval Period
A13: =IF($A$1="English",B13,C13) -> Project Category | B13: Project Category
A14: =IF($A$1="English",B14,C14) -> Project Status | B14: Project Status
A15: =IF($A$1="English",B15,C15) -> Construction Status | B15: Construction Status
A16: =IF($A$1="English",B16,C16) -> Section 2: Square Footage Specification | B16: Section 2: Square Footage Specification
A17: =IF($A$1="English",B17,C17) -> Anticipate Design Change? | B17: Anticipate Design Change?
... A45: =IF($A$1="English",B45,C45) -> Project Reconciliation | B45: Project Reconciliation
A46: =IF($A$1="English",B46,C46) -> Section 7: Approved Project Funding | B46: Section 7: Approved Project Funding | C46: Financement approuvé du projet
A47: =IF($A$1="English",B47,C47) -> LP/EDC | B47: LP/EDC
A48: =IF($A$1="English",B48,C48) -> CP | B48: CP
A49: =IF($A$1="English",B49,C49) -> CC | B49: CC
A50: =IF($A$1="English",B50,C50) -> Other | B50: Other
A51: =IF($A$1="English",B51,C51) -> Total Approved Funding | B51: Total Approved Funding
A52: =IF($A$1="English",B52,C52) -> Section 8: Projected Construction Cost | B52: Section 8: Projected Construction Cost | C52: Coût prévu du projet
A53: =IF($A$1="English",B53,C53) -> Basis of Cost Estimate | B53: Basis of Cost Estimate
A54: =IF($A$1="English",B54,C54) -> Land Cost | B54: Land Cost
A55: =IF($A$1="English",B55,C55) -> Building Cost - School | B55: Building Cost - School
A56: =IF($A$1="English",B56,C56) -> Soft Costs - School | B56: Soft Costs - School
A57: =IF($A$1="English",B57,C57) -> Building Cost - Child Care | B57: Building Cost - Child Care
A58: =IF($A$1="English",B58,C58) -> Soft Costs -Child Care | B58: Soft Costs -Child Care
A59: =IF($A$1="English",B59,C59) -> Unique Site Costs - School | B59: Unique Site Costs - School
A60: =IF($A$1="English",B60,C60) -> Unique Site Costs - Child Care | B60: Unique Site Costs - Child Care
A61: =IF($A$1="English",B61,C61) -> Unique Site Costs - Other | B61: Unique Site Costs - Other
A62: =IF($A$1="English",B62,C62) -> Municipal/Extraordinary Cost - School | B62: Municipal/Extraordinary Cost - School
A63: =IF($A$1="English",B63,C63) -> Municipal/Extraordinary Cost - Child Care | B63: Municipal/Extraordinary Cost - Child Care
A64: =IF($A$1="English",B64,C64) -> Municipal/Extraordinary Cost - Other | B64: Municipal/Extraordinary Cost - Other
... A70: =IF($A$1="English",B70,C70) -> Opening Ceremony - Date | B70: Opening Ceremony - Date
A71: =IF($A$1="English",B71,C71) -> Section 10: General Comments | B71: Section 10: General Comments | C71: Commentaires
A72: =IF($A$1="English",B72,C72) -> Section 10: Project Risks and Mitigation Stategies | B72: Section 10: Project Risks and Mitigation Stategies
A73: =IF($A$1="English",B73,C73) -> Risk Type | B73: Risk Type
A74: =IF($A$1="English",B74,C74) -> Risk Rating | B74: Risk Rating
A75: =IF($A$1="English",B75,C75) -> Risk Exposure Start Date | B75: Risk Exposure Start Date
A76: =IF($A$1="English",B76,C76) -> Min-Max Cost of Risk ($M) | B76: Min-Max Cost of Risk ($M)
A77: =IF($A$1="English",B77,C77) -> Min-Max Delay of Risk (Months) | B77: Min-Max Delay of Risk (Months)
A78: =IF($A$1="English",B78,C78) -> Mitigation Stategies/Comments | B78: Mitigation Stategies/Comments
A79: =IF($A$1="English",B79,C79) -> CA Comments | B79: CA Comments
A80: =IF($A$1="English",B80,C80) -> Contract Awarded | B80: Contract Awarded
A81: =IF($A$1="English",B81,C81) -> Build Permit Obtained | B81: Build Permit Obtained
A82: =IF($A$1="English",B82,C82) -> Site Preparation Cost | B82: Site Preparation Cost
A83: =IF($A$1="English",B83,C83) -> Site Funding Source | B83: Site Funding Source
... A86: =IF($A$1="English",B86,C86) -> ALL ESTIMATED DATES = UNBOLDED ALL ACTUAL DATES = BOLDED | B86: ALL ESTIMATED DATES = UNBOLDED ALL ACTUAL DATES = BOLDED
A87: =IF($A$1="English",B87,C87) -> 0
A88: =IF($A$1="English",B88,C88) -> 0
A89: =IF($A$1="English",B89,C89) -> 0
A94: Output | B94: English | C94: French
A95: Project Commitment
A96: Label Out | B96: Label English | C96: Label French
A97: =IF($A$1="English",B97,C97) -> Project Info | B97: Project Info
A98: =IF($A$1="English",B98,C98) -> Key | B98: Key
A99: =IF($A$1="English",B99,C99) -> Project ID | B99: Project ID | C99: Identification du projet
A100: =IF($A$1="English",B100,C100) -> Project Name | B100: Project Name | C100: Nom du projet
A101: =IF($A$1="English",B101,C101) -> Phase 1 - Start | B101: Phase 1 - Start | C101: Phase 1 - Début
A102: =IF($A$1="English",B102,C102) -> Phase 1 - End | B102: Phase 1 - End | C102: Phase 1 - Fin
A103: =IF($A$1="English",B103,C103) -> Phase 2 - Start | B103: Phase 2 - Start | C103: Phase 2 - Début
A104: =IF($A$1="English",B104,C104) -> Phase 2 - End | B104: Phase 2 - End | C104: Phase 2 - Fin
A105: =IF($A$1="English",B105,C105) -> Phase 3 - Start | B105: Phase 3 - Start | C105: Phase 3 - Début
A106: =IF($A$1="English",B106,C106) -> Phase 3 - End | B106: Phase 3 - End | C106: Phase 3 - Fin
A107: =IF($A$1="English",B107,C107) -> Phase 4 - Start | B107: Phase 4 - Start | C107: Phase 4 - Début
A108: =IF($A$1="English",B108,C108) -> Phase 4 - End | B108: Phase 4 - End | C108: Phase 4 - Fin
A109: =IF($A$1="English",B109,C109) -> Phase Dates | B109: Phase Dates | C109: Dates de phase
A110: =IF($A$1="English",B110,C110) -> Key Milestones | B110: Key Milestones | C110: Étapes Clés
... A112: =IF($A$1="English",B112,C112) -> Space Template Finalized | B112: Space Template Finalized | C112: Gabarit des espaces finalisé
A113: =IF($A$1="English",B113,C113) -> Signed Joint Use Agreement | B113: Signed Joint Use Agreement
A114: =IF($A$1="English",B114,C114) -> 80% Design | B114: 80% Design | C114: Design à 80%
A115: =IF($A$1="English",B115,C115) -> Class A Cost Estimate | B115: Class A Cost Estimate | C115: Rapport du consultant en coûts de classe A
A116: =IF($A$1="English",B116,C116) -> Site Plan Approval | B116: Site Plan Approval | C116: Approbation du plan de site
A117: =IF($A$1="English",B117,C117) -> Build Permit Obtained | B117: Build Permit Obtained | C117: Permis de construire obtenu
A118: =IF($A$1="English",B118,C118) -> Tender Issued | B118: Tender Issued | C118: Projet soumissionné
A119: =IF($A$1="English",B119,C119) -> Construction Start | B119: Construction Start | C119: Début de la construction
A120: =IF($A$1="English",B120,C120) -> School/Addition Opening | B120: School/Addition Opening | C120: école/ajout ouverte
A121: =IF($A$1="English",B121,C121) -> Project Reconciliation | B121: Project Reconciliation | C121: Réconciliation du projet
A122: =IF($A$1="English",B122,C122) -> Funding Requested | B122: Funding Requested | C122: Financement demandé
A123: =IF($A$1="English",B123,C123) -> Cost of Project (Excluding Site) | B123: Cost of Project (Excluding Site) | C123: Coût du projet (Excluant coût du site)
A124: =IF($A$1="English",B124,C124) -> Total Cost of Project (Including Site) | B124: Total Cost of Project (Including Site) | C124: Coût total
A125: =IF($A$1="English",B125,C125) -> Total CP Request | B125: Total CP Request
A126: =IF($A$1="English",B126,C126) -> Total Child Care Request | B126: Total Child Care Request
